Workbook

Sheet Rent vs. Buy
B1: Low | C1: High
A3: Increase in Price of New Home vs. Current | B3: 750000 | C3: 1500000
A4: Down Payment Range | B4: 0.3 | C4: 0.3
A5: Down Payment | B5: =+B3*B4 -> 225000 | C5: =+C3*C4 -> 450000
A7: Origination Fee | B7: =+B8*B3 -> 3750 | C7: =+C8*C3 -> 15000 | D7: Fee for processing the loan (may be negotiable)
A8: % of Loan | B8: 0.005 | C8: 0.01
A9: Underwriting Fee | B9: 400 | C9: 900 | D9: Lender fee for evaluating your loan
A10: Appraisal Fee | B10: 300 | C10: 700 | D10: Required to assess home value
A11: Credit Report Fee | B11: 25 | C11: 50 | D11: Pulling your credit
A12: Title Search & Insurance | B12: 500 | C12: 1500 | D12: Protects against ownership disputes
A13: Recording Fees | B13: 100 | C13: 300 | D13: County/city fee to record the new deed
A14: Escrow Fees | B14: 500 | C14: 2000
A15: Fixed Transaction Costs | B15: =+SUM(B9:B14)+B7 -> 5575 | C15: =+SUM(C9:C14)+C7 -> 20450
A16: Total Cash Need to Buy a Larger Home | B16: =+B15+B7+B5 -> 234325 | C16: =+C15+C7+C5 -> 485450
A17: Average | C17: =AVERAGE(B16:C16) -> 359887.5
A18: Less: Positive Net Cash Flow Over Next Three Years | C18: =-Charts!Q43*2.5 -> -165845.79
A19: Total for Medum Term Category | C19: =+C17+C18 -> 194041.71

Sheet MoneyBoard - Key Metrics
A1: Net Worth | B1: Increasing | C1: =+Charts!S9 -> 4648384
A2: Annual Salary + Bonus | B2: Increasing | C2: =+'Cash Flow'!AX10 -> 970000
A3: Annual Net Cash Flow | B3: Stable | C3: =+Charts!Q43 -> 66338.316 | D3: 14% of cash income | F3: 3000 | G3: 12000
A4: Monthly Cash Flow (1) | B4: Stable | C4: =+Charts!T43 -> -4358.5094 | D4: 11 months in a cash outflow position | F4: =+F3/C3 -> 0.045222734 | G4: =+G3/C3 -> 0.18089094
A5: Monthly Expenses (1) | B5: Increasing | C5: =++Charts!T42 -> -24939.42 | D5: High volatility with $20-60K a month
A6: Cash Needed for Next 12 Months | C6: =-OPTIMIZER!J16 -> -129384.79 | D6: Cumulative cash trough (Nov 2025)
A7: Cash Management | C7: Optimizer Notification
A8: Cash in Bank Accounts | B8: Increasing | C8: =+Charts!Z12 -> 372050
A9: Months of Expenses Covered by Cash | C9: =+Charts!Q48 -> 15.815411 | D9: Too conservative
A10: Cash Excess/Deficit Positon | B10: CLICK HERE | C10: =+SUM(OPTIMIZER!E24:E26)-SUM(OPTIMIZER!G24:G26) -> 162684.07
A11: Identified Additional Cash Income / Year | B11: CLICK HERE | C11: =+OPTIMIZER!AZ29 -> 7207.434 | D11: =+TEXT(C11/C3,"0%")&" increase to your cash flow" -> 11% increase to your cash flow
A12: Investments | C12: Optimizer Notification
A13: A: Cash in Investment Accounts to be Deployed | C13: =+Charts!AB137 -> 222965.43
A14: B: Excess cash to be reallocate to investments | C14: =+OPTIMIZER!H27 -> 162684.07
A15: Total Cash You Should Invest Today (A+B): | B15: CLICK HERE | C15: =SUM(C13:C14) -> 385649.51 | D15: =TEXT(C15/Charts!AB148,"0%")&" increase to investments" -> 15% increase to investments

Sheet Execute on Securities Trades
E2: GURU Recommendation | H2: Make Your Selection
C3: Execute Trade? | E3: Product | F3: Expense Ratio | G3: Total Amount | H3: Total Amount | I3: How many months to buy into the position | J3: Monthly Amount
D4: ='Model Portfolios'!H11 -> US Large Cap | E4: Vanguard S&P 500 (VOO) | F4: 0.0003 | G4: ='Model Portfolios'!M11 -> 0 | H4: =G4 -> 0 | I4: 6 | J4: =IF(ISERROR(H4/I4),"-",H4/I4) -> 0
D5: ='Model Portfolios'!H12 -> US Total Market | E5: Vanguard Total Stock Market (VTI) | F5: 0.0003 | G5: ='Model Portfolios'!M12 -> 0 | H5: 0 | I5: 0 | J5: =IF(ISERROR(H5/I5),"-",H5/I5) -> -
D6: ='Model Portfolios'!H13 -> US Large Cap Growth | E6: Invesco QQQ Trust | F6: 0.002 | G6: ='Model Portfolios'!M13 -> 80000 | H6: =G6 -> 80000 | I6: 6 | J6: =IF(ISERROR(H6/I6),"-",H6/I6) -> 13333.333
D7: ='Model Portfolios'!H14 -> US Dividend / Value | E7: Schwab U.S. Dividend Equity ETF | F7: 0.0006 | G7: ='Model Portfolios'!M14 -> 0 | H7: =G7 -> 0 | I7: 6 | J7: =IF(ISERROR(H7/I7),"-",H7/I7) -> 0
D8: ='Model Portfolios'!H15 -> US Small Cap | E8: iShares Russell 2000 ETF (IWM) | F8: 0.0019 | G8: ='Model Portfolios'!M15 -> 0 | H8: =G8 -> 0 | I8: 6 | J8: =IF(ISERROR(H8/I8),"-",H8/I8) -> 0
D9: ='Model Portfolios'!H17 -> Developed International | E9: iShares Core MSCI EAFE ETF | F9: 0.0007 | G9: ='Model Portfolios'!M17 -> 0 | H9: =G9 -> 0 | I9: 6 | J9: =IF(ISERROR(H9/I9),"-",H9/I9) -> 0
D10: ='Model Portfolios'!H18 -> Emerging Markets | E10: iShares Core MSCI Emerging Markets ETF | F10: 0.0009 | G10: ='Model Portfolios'!M18 -> 0 | H10: =G10 -> 0 | I10: 6 | J10: =IF(ISERROR(H10/I10),"-",H10/I10) -> 0
D11: ='Model Portfolios'!H20 -> REITS, Commodities | E11: Invesco Optimum Yield Diversification Commodity | F11: 0.0067 | G11: ='Model Portfolios'!M20/2 -> 0 | H11: =G11 -> 0 | I11: 6 | J11: =IF(ISERROR(H11/I11),"-",H11/I11) -> 0
D12: ='Model Portfolios'!H21 -> Bonds | E12: Bloomberg Aggregate Bond Inex | F12: 0.0067 | G12: ='Model Portfolios'!M21/2 -> 41342.037 | H12: =G12 -> 41342.037 | I12: 6 | J12: =IF(ISERROR(H12/I12),"-",H12/I12) -> 6890.3396
D13: ='Model Portfolios'!H22 -> Crypto | G13: =G11 -> 0 | H13: 0 | I13: 0 | J13: =IF(ISERROR(H13/I13),"-",H13/I13) -> -
B14: Total | G14: =SUM(G4:G13) -> 121342.04 | H14: =SUM(H4:H13) -> 121342.04 | J14: =SUM(J4:J13) -> 20223.673
G15: Remaining Cash | H15: =G14-H14 -> 0

Sheet Model Portfolios
H2: LIQUID BROKERAGE ASSETS | AE2: A growth-leaning portfolio designed for a medium-short time horizon, balancing upside potential with downside protection. It incorporates high-quality U.S. equities, global diversification, and a meaningful bond allocation (10%) to buffer volatility. Ideal for investors who want growth but may need liquidity within 3–5 years. | AF2: A globally diversified, equity-heavy portfolio for investors with a 10-year horizon who are comfortable with market fluctuations. This portfolio tilts toward U.S. total market and growth equities, while still maintaining meaningful international exposure to capture broader global opportunities. | AG2: Built for investors with a long time horizon and high risk tolerance, this portfolio maximizes growth potential through aggressive equity allocations. It includes a strong U.S. tilt with a heavy focus on large cap growth and small cap value, while maintaining robust international exposure.
H3: Cash Available to Allocate
H4: Cash in Brokerage | I4: =+I10 -> 186585.93 | AC4: MODEL PORTFOLIOS
H5: Reallocation from Cash Mgmt | I5: =+OPTIMIZER!AR27-OPTIMIZER!AM27 -> 162684.07 | R5: SELECT YOUR MODEL PORTFOLIO | AC5: CURRENT - moderately more US focused | AI5: moderately more US focused | AO5: heavy us focus with 15-20% international. But chat gpt says that blackrock model portfolios suggest 30-40% | AV5: growth oriented
H6: Next 12 Month Paycheck | I6: =+OPTIMIZER!P27*12+OPTIMIZER!S27 -> 0
H7: Total | I7: =+SUM(I4:I6) -> 349270.01 | L7: =+I7/I25 -> 0.23138126
L8: Reabalancing Your Portfolio with Cash | S8: Your Current Balances | U8: GURU Suggestion | W8: Make Your Selection | Y8: GURU | AA8: Customer Selected | AC8: Portfolio Investment Horizon | AE8: 5 Years | AF8: 10 Year | AG8: 20+ Year | AK8: 5-Year Portfolio | AL8: 10-Year Portfolio | AM8: 20+ Year Portfolio | AQ8: 5-year Portfolio | AR8: 10-year portfolio | AS8: 20+ year portfolio | AX8: 5-year Portfolio | AY8: 10-year portfolio | AZ8: 20+ year portfolio
C9: Category | D9: Current Balances | E9: Your Model Portfolio | F9: Difference Between Current and Model Portfolio | H9: Category | I9: Current Balances | J9: Your Model Portfolio | K9: Difference Between Current and Model Portfolio | L9: + Invest Your Cash in Brokerage | M9: + Cash From Reallocation and Next 12 Months Pay | N9: Ending Balance | O9: Ending Composition | P9: Vs. Your Model Portfolio | R9: Category | S9: Liquid Brokerage | T9: Retirement | U9: Liquid Brokerage | V9: Retirement | W9: Liquid Brokerage | X9: Retirement | Y9: Liquid Brokerage | Z9: Retirement | AA9: Liquid Brokerage | AB9: Retirement | AC9: Category | AD9: Description | AE9: Capital preservation and Liquidity | AF9: Global Core Growth with Equity-Heavy Portfolio | AG9: High Risk Tolerance with Greater U.S. Tilt | AI9: Category | AK9: Conservative Growth with Downside Protection in Bonds | AL9: Global Core Growth with Equity-Heavy Portfolio | AM9: High Risk Tolerance with Greater U.S. Tilt | AO9: Category | AQ9: Conservative growth + Real Assets | AV9: Category | AX9: Conservative growth + Real Assets
C10: Cash | D10: =+Charts!AB130 -> 36379.5 | E10: =+X10*(E$23) -> 0 | F10: =+E10-D10 -> -36379.5 | H10: Cash | I10: =+Charts!AC103 -> 186585.93 | J10: =+W10*(J$23) -> 0 | K10: =+J10-I10 -> -186585.93 | L10: =+K10 -> -186585.93 | M10: 0 | N10: =+L10+I10+M10 -> 0 | O10: =+N10/$N$25 -> 0 | P10: =+W10 -> 0 | R10: =+H10 -> Cash | S10: =+I10/$I$25 -> 0.12360777 | T10: =+D10/$D$25 -> 0.0363795 | U10: 0 | V10: 0 | W10: 0 | X10: 0 | Y10: =+U10*$I$25 -> 0 | Z10: =+X10*$D$25 -> 0 | AA10: =+W10*$I$25 -> 0 | AB10: =+X10*$D$25 -> 0 | AC10: US Large Cap | AD10: Large, stable (S&P 500) | AE10: 0.1 | AF10: 0.15 | AG10: 0.2 | AI10: U.S. Large Cap (S&P 500) | AJ10: VOO (Vanguard S&P 500) | AK10: 0.25 | AO10: U.S. Large Cap (S&P 500) | AP10: S&P 500 | AQ10: 0.25 | AT10: VTI or VOO | AV10: U.S. Large Cap (S&P 500) | AW10: S&P 500 | AX10: 0.25 | BA10: VTI or VOO
C11: US Large Cap | D11: =+Charts!AB126 -> 100000 | E11: =+X11*(E$23) -> 250000 | F11: =+E11-D11 -> 150000 | H11: =+C11 -> US Large Cap | I11: =+Charts!AC106 -> 435000 | J11: =+W11*(J$23) -> 358468.16 | K11: =+J11-I11 -> -76531.84 | L11: 0 | M11: 0 | N11: =+L11+I11+M11 -> 435000 | O11: =+N11/$N$25 -> 0.26013882 | P11: =+W11 -> 0.25 | R11: =+H11 -> US Large Cap | S11: =+I11/$I$25 -> 0.28817489 | T11: =+D11/$D$25 -> 0.1 | U11: =+AF10 -> 0.15 | V11: 0.2 | W11: 0.25 | X11: 0.25 | Y11: =+U11*$I$25 -> 226425 | Z11: =+X11*$D$25 -> 250000 | AA11: =+W11*$I$25 -> 377375 | AB11: =+X11*$D$25 -> 250000 | AC11: US Total Market | AD11: Catch-all allocation (~75% large & ~25% small/mid cap) | AE11: 0.05 | AF11: 0.05 | AG11: 0.05 | AI11: U.S. Total Market | AJ11: VTI (Vanguard Total Stock Market) | AK11: 0 | AL11: 0.4 | AM11: 0.35 | AO11: U.S. Total Market | AP11: 70-80% large cap and 20-30% small & mid cap | AQ11: 0 | AR11: 0.45 | AS11: 0.4 | AV11: U.S. Total Market | AW11: 70-80% large cap and 20-30% small & mid cap | AX11: 0 | AY11: 0.35 | AZ11: 0.3
C12: US Total Market | D12: =+Charts!AB125 -> 400000 | E12: =+X12*(E$23) -> 150000 | F12: =+E12-D12 -> -250000 | H12: =+C12 -> US Total Market | I12: =+Charts!AC105 -> 379877.58 | J12: =+W12*(J$23) -> 143387.26 | K12: =+J12-I12 -> -236490.32 | L12: 0 | N12: =+L12+I12+M12 -> 379877.58 | O12: =+N12/$N$25 -> 0.2271745 | P12: =+W12 -> 0.1 | R12: =+H12 -> US Total Market | S12: =+I12/$I$25 -> 0.25165789 | T12: =+D12/$D$25 -> 0.4 | U12: =+AF11 -> 0.05 | V12: 0.05 | W12: 0.1 | X12: 0.15 | Y12: =+U12*$I$25 -> 75475 | Z12: =+X12*$D$25 -> 150000 | AA12: =+W12*$I$25 -> 150950 | AB12: =+X12*$D$25 -> 150000 | AC12: US Large Cap Growth | AD12: Innovation, tech, volatile | AE12: 0.05 | AF12: 0.1 | AG12: 0.15 | AI12: Large Cap Growth | AJ12: QQQ (Invesco QQQ Trust - Nasdaq 100) or VUG (Vanguard Growth ETF - Russell 1000) | AK12: 0.15 | AL12: 0.15 | AM12: 0.2 | AO12: Large Cap Growth | AP12: Nasdaq 100 | AQ12: 0.15 | AR12: 0.2 | AS12: 0.25 | AV12: Large Cap Growth | AW12: Nasdaq 100 | AX12: 0.15 | AY12: 0.15 | AZ12: 0.2
C13: US Large Cap Growth | D13: 0 | E13: =+X13*(E$23) -> 150000 | F13: =+E13-D13 -> 150000 | H13: =+C13 -> US Large Cap Growth | I13: 0 | J13: =+W13*(J$23) -> 143387.26 | K13: =+J13-I13 -> 143387.26 | L13: 100000 | M13: 80000 | N13: =+L13+I13+M13 -> 180000 | O13: =+N13/$N$25 -> 0.10764365 | P13: =+W13 -> 0.1 | R13: =+H13 -> US Large Cap Growth | S13: =+I13/$I$25 -> 0 | T13: =+D13/$D$25 -> 0 | U13: =+AF12 -> 0.1 | V13: 0.15 | W13: 0.1 | X13: 0.15 | Y13: =+U13*$I$25 -> 150950 | Z13: =+X13*$D$25 -> 150000 | AA13: =+W13*$I$25 -> 150950 | AB13: =+X13*$D$25 -> 150000 | AC13: US Dividend / Value | AD13: Defensive stocks, reliable income, lower volatility | AE13: 0.1 | AF13: 0.05 | AG13: 0.05 | AI13: U.S. Dividend/Quality | AJ13: SCHD (Schwab U.S. Dividend Equity ETF) or DGRO (iShares Core Dividend Growth ETF) | AK13: 0.1 | AO13: U.S. Dividend/Quality | AQ13: 0.1 | AT13: SCHD or DGRO | AV13: U.S. Dividend/Quality | AX13: 0.1 | BA13: SCHD or DGRO
C14: US Dividend / Value | D14: 0 | E14: =+X14*(E$23) -> 50000 | F14: =+E14-D14 -> 50000 | H14: =+C14 -> US Dividend / Value | I14: =+Charts!AC108 -> 94368.991 | J14: =+W14*(J$23) -> 71693.632 | K14: =+J14-I14 -> -22675.359 | N14: =+L14+I14+M14 -> 94368.991 | O14: =+N14/$N$25 -> 0.056434571 | P14: =+W14 -> 0.05 | R14: =+H14 -> US Dividend / Value | S14: =+I14/$I$25 -> 0.062516722 | T14: =+D14/$D$25 -> 0 | U14: =+AF13 -> 0.05 | V14: 0.05 | W14: 0.05 | X14: =+V14 -> 0.05 | Y14: =+U14*$I$25 -> 75475 | Z14: =+X14*$D$25 -> 50000 | AA14: =+W14*$I$25 -> 75475 | AB14: =+X14*$D$25 -> 50000 | AC14: US Small Cap | AD14: Higher growth but more volatile | AE14: 0.05 | AF14: 0.1 | AG14: 0.15 | AI14: U.S. Small Cap | AJ14: VB (Vanguard Small Cap ETF) or IWM (iShares Russell 2000 ETF) | AK14: 0 | AL14: 0.1 | AM14: 0.15 | AO14: U.S. Small Cap | AQ14: 0 | AR14: 0.1 | AS14: 0.15 | AT14: SCHD or DGRO | AV14: U.S. Small Cap | AX14: 0 | AY14: 0.1 | AZ14: 0.1 | BA14: SCHD or DGRO
C15: US Small Cap | D15: =+Charts!AB127 -> 274264.47 | E15: =+X15*(E$23) -> 100000 | F15: =+E15-D15 -> -174264.47 | H15: =+C15 -> US Small Cap | I15: =+Charts!AC107 -> 49317.756 | J15: =+W15*(J$23) -> 84066.319 | K15: =+J15-I15 -> 34748.563 | N15: =+L15+I15+M15 -> 49317.756 | O15: =+N15/$N$25 -> 0.029493019 | P15: =+W15 -> 0.058628861 | R15: =+H15 -> US Small Cap | S15: =+I15/$I$25 -> 0.032671584 | T15: =+D15/$D$25 -> 0.27426447 | U15: =+AF14 -> 0.1 | V15: 0.1 | W15: =1-SUM(W10:W14,W19:W22,W24) -> 0.058628861 | X15: 0.1 | Y15: =+U15*$I$25 -> 150950 | Z15: =+X15*$D$25 -> 100000 | AA15: =+W15*$I$25 -> 88500.265 | AB15: =+X15*$D$25 -> 100000 | AC15: Total US | AD15: Backbone of most portfolios | AE15: =+SUM(AE10:AE14) -> 0.35 | AF15: =+SUM(AF10:AF14) -> 0.45 | AG15: =+SUM(AG10:AG14) -> 0.6 | AI15: Total US | AK15: =+SUM(AK10:AK14) -> 0.5 | AL15: =+SUM(AL10:AL14) -> 0.65 | AM15: =+SUM(AM10:AM14) -> 0.7 | AO15: Total US | AQ15: =+SUM(AQ10:AQ14) -> 0.5 | AR15: =+SUM(AR10:AR14) -> 0.75 | AS15: =+SUM(AS10:AS14) -> 0.8 | AV15: Total US | AX15: =+SUM(AX10:AX14) -> 0.5 | AY15: =+SUM(AY10:AY14) -> 0.6 | AZ15: =+SUM(AZ10:AZ14) -> 0.6
C16: Total US | D16: =+SUM(D11:D15) -> 774264.47 | E16: =+SUM(E11:E15) -> 700000 | F16: =+SUM(F11:F15) -> -74264.475 | H16: Total US | I16: =+SUM(I11:I15) -> 958564.33 | J16: =+SUM(J11:J15) -> 801002.64 | K16: =+SUM(K11:K15) -> -157561.69 | L16: =+SUM(L11:L15) -> 100000 | N16: =+SUM(N11:N15) -> 1138564.3 | O16: =+SUM(O11:O15) -> 0.68088457 | P16: =+SUM(P11:P15) -> 0.55862886 | R16: Total US | S16: =+SUM(S11:S15) -> 0.63502109 | T16: =+SUM(T11:T15) -> 0.77426447 | U16: =+SUM(U11:U15) -> 0.45 | V16: =+SUM(V11:V15) -> 0.55 | W16: =+SUM(W11:W15) -> 0.55862886 | X16: =+SUM(X11:X15) -> 0.7 | Y16: =+U16*$I$25 -> 679275 | Z16: =+X16*$D$25 -> 700000 | AA16: =+W16*$I$25 -> 843250.27 | AB16: =+X16*$D$25 -> 700000 | AC16: Developed International | AD16: European and Japanese markets | AE16: 0.15 | AF16: 0.15 | AG16: 0.2 | AI16: Developed Markets | AJ16: VEA (Vanguard FTSE Deveoped Market ETF) or IEFA (iShares Core MSCI EAFE ETF) | AK16: 0.1 | AL16: 0.15 | AM16: 0.15 | AO16: Developed Markets | AQ16: 0.1 | AR16: 0.1 | AS16: 0.1 | AT16: VEA | AV16: Developed Markets | AX16: 0.1 | AY16: 0.2 | AZ16: 0.2 | BA16: VEA
C17: Developed International | D17: =+Charts!AB124*85% -> 108924.31 | E17: =+X17*(E$23) -> 150000 | F17: =+E17-D17 -> 41075.687 | H17: =+C17 -> Developed International | I17: =+Charts!AC104 -> 116538.3 | J17: =+W17*(J$23) -> 110699.62 | K17: =+J17-I17 -> -5838.6777 | M17: 0 | N17: =+L17+I17+M17 -> 116538.3 | O17: =+N17/$N$25 -> 0.069692268 | P17: =+W17 -> 0.077203247 | R17: =+H17 -> Developed International | S17: =+I17/$I$25 -> 0.077203247 | T17: =+D17/$D$25 -> 0.10892431 | U17: =+AF16 -> 0.15 | V17: 0.2 | W17: =S17 -> 0.077203247 | X17: 0.15 | Y17: =+U17*$I$25 -> 226425 | Z17: =+X17*$D$25 -> 150000 | AA17: =+W17*$I$25 -> 116538.3 | AB17: =+X17*$D$25 -> 150000 | AC17: Emerging Markets | AD17: Fast growing economies | AE17: 0 | AF17: 0.05 | AG17: 0.1 | AI17: Emerging Markets | AJ17: VWO (Vanguard FTSE Emerging Markets ETF) or IEMG (iShares Core MSCI Emerging Markets ETF) | AK17: 0.1 | AL17: 0.1 | AM17: 0.1 | AO17: Emerging Markets | AQ17: 0.1 | AR17: 0.05 | AS17: 0.05 | AT17: VWO | AV17: Emerging Markets | AX17: 0.1 | AY17: 0.1 | AZ17: 0.15 | BA17: VWO
C18: Emerging Markets | D18: =+Charts!AB124*15% -> 19221.938 | E18: =+X18*(E$23) -> 50000 | F18: =+E18-D18 -> 30778.062 | H18: =+C18 -> Emerging Markets | I18: 0 | J18: =+W18*(J$23) -> 0 | K18: =+J18-I18 -> 0 | N18: =+L18+I18+M18 -> 0 | O18: =+N18/$N$25 -> 0 | P18: =+W18 -> 0 | R18: =+H18 -> Emerging Markets | S18: =+I18/$I$25 -> 0 | T18: =+D18/$D$25 -> 0.019221938 | U18: =+AF17 -> 0.05 | V18: 0.1 | W18: 0 | X18: 0.05 | Y18: =+U18*$I$25 -> 75475 | Z18: =+X18*$D$25 -> 50000 | AA18: =+W18*$I$25 -> 0 | AB18: =+X18*$D$25 -> 50000 | AC18: Total International | AE18: =+SUM(AE16:AE17) -> 0.15 | AF18: =+SUM(AF16:AF17) -> 0.2 | AG18: =+SUM(AG16:AG17) -> 0.3 | AI18: Total International | AK18: =+SUM(AK16:AK17) -> 0.2 | AL18: =+SUM(AL16:AL17) -> 0.25 | AM18: =+SUM(AM16:AM17) -> 0.25 | AO18: Total International | AQ18: =+SUM(AQ16:AQ17) -> 0.2 | AR18: =+SUM(AR16:AR17) -> 0.15 | AS18: =+SUM(AS16:AS17) -> 0.15 | AV18: Total Internaitonal | AX18: =+SUM(AX16:AX17) -> 0.2 | AY18: =+SUM(AY16:AY17) -> 0.3 | AZ18: =+SUM(AZ16:AZ17) -> 0.35
C19: Total International | D19: =SUM(D17:D18) -> 128146.25 | E19: =+SUM(E17:E18) -> 200000 | F19: =+SUM(F17:F18) -> 71853.75 | H19: Total International | I19: =SUM(I17:I18) -> 116538.3 | J19: =+SUM(J17:J18) -> 110699.62 | K19: =+SUM(K17:K18) -> -5838.6777 | L19: =+SUM(L17:L18) -> 0 | N19: =+SUM(N17:N18) -> 116538.3 | O19: =+SUM(O17:O18) -> 0.069692268 | P19: =+SUM(P17:P18) -> 0.077203247 | R19: Total International | S19: =+SUM(S17:S18) -> 0.077203247 | T19: =+SUM(T17:T18) -> 0.12814625 | U19: =+SUM(U17:U18) -> 0.2 | V19: =+SUM(V17:V18) -> 0.3 | W19: =+SUM(W17:W18) -> 0.077203247 | X19: =+SUM(X17:X18) -> 0.2 | Y19: =+U19*$I$25 -> 301900 | Z19: =+X19*$D$25 -> 200000 | AA19: =+W19*$I$25 -> 116538.3 | AB19: =+X19*$D$25 -> 200000 | AC19: REITS, Commodities | AD19: Inflation hedge, asset diversification | AE19: 0 | AF19: 0.05 | AG19: 0.1 | AI19: REITS, Commodities | AJ19: VNQ ( Vanguard Real Estate ETF) or PDBC (Invesco Optimum Yield Diversified Commodity) | AK19: 0.1 | AL19: 0.05 | AM19: 0.05 | AO19: REITS, Commodities | AQ19: 0.1 | AR19: 0.05 | AS19: 0.05 | AV19: REITS, Commodities | AX19: 0.1 | AY19: 0.05 | AZ19: 0.05
C20: REITS, Commodities | D20: 0 | E20: =+X20*(E$23) -> 100000 | F20: =+E20-D20 -> 100000 | H20: =+C20 -> REITS, Commodities | I20: 0 | J20: =+W20*(J$23) -> 0 | K20: =+J20-I20 -> 0 | N20: =+L20+I20+M20 -> 0 | O20: =+N20/$N$25 -> 0 | P20: =+W20 -> 0 | R20: =+H20 -> REITS, Commodities | S20: =+I20/$I$25 -> 0 | T20: =+D20/$D$25 -> 0 | U20: =+AF19 -> 0.05 | V20: 0.1 | W20: 0 | X20: =+V20 -> 0.1 | Y20: =+U20*$I$25 -> 75475 | Z20: =+X20*$D$25 -> 100000 | AA20: =+W20*$I$25 -> 0 | AB20: =+X20*$D$25 -> 100000 | AC20: Bonds | AD20: Downside cushion, stability | AE20: 0.5 | AF20: 0.3 | AG20: 0 | AI20: Bonds | AJ20: iShares Core U.S. Aggregate Bond ETF | AK20: 0.2 | AL20: 0.05 | AM20: 0 | AO20: Bonds | AQ20: 0.2 | AR20: 0.05 | AS20: 0 | AV20: Bonds | AX20: 0.2 | AY20: 0.05 | AZ20: 0
C21: Bonds | D21: =+Charts!AB129 -> 61209.776 | E21: =+X21*(E$23) -> 0 | F21: =+E21-D21 -> -61209.776 | H21: =+C21 -> Bonds | I21: 0 | J21: =+W21*(J$23) -> 286774.53 | K21: =+J21-I21 -> 286774.53 | L21: =+-L10-L13 -> 86585.933 | M21: =+M23-M13 -> 82684.075 | N21: =+L21+I21+M21 -> 169270.01 | O21: =+N21/$N$25 -> 0.1012269 | P21: =+W21 -> 0.2 | R21: =+H21 -> Bonds | S21: =+I21/$I$25 -> 0 | T21: =+D21/$D$25 -> 0.061209776 | U21: =+AF20 -> 0.3 | V21: 0 | W21: 0.2 | X21: =+V21 -> 0 | Y21: =+U21*$I$25 -> 452850 | Z21: =+X21*$D$25 -> 0 | AA21: =+W21*$I$25 -> 301900 | AB21: =+X21*$D$25 -> 0 | AC21: Crypto | AD21: If add reduce another category | AE21: 0 | AF21: 0.05 | AG21: 0.05 | AI21: Crypto | AJ21: Bitwise 10 Crypto Index | AK21: 0 | AL21: 0.05 | AM21: 0.05 | AO21: Crypto | AP21: If add maybe reduce U.S. lareg cap growth | AQ21: 0 | AR21: 0.05 | AS21: 0.05 | AV21: Crypto (Optional) | AW21: If add maybe reduce U.S. lareg cap growth | AX21: 0 | AY21: 0.05 | AZ21: 0.05
C22: Crypto | D22: 0 | E22: =+X22*(E$23) -> 0 | F22: =+E22-D22 -> 0 | H22: =+C22 -> Crypto | I22: =+Charts!AC111 -> 9500 | J22: =+W22*(J$23) -> 9024.0411 | K22: =+J22-I22 -> -475.95887 | N22: =+L22+I22+M22 -> 9500 | O22: =+N22/$N$25 -> 0.0056811927 | P22: =+W22 -> 0.0062934747 | R22: =+H22 -> Crypto | S22: =+I22/$I$25 -> 0.0062934747 | T22: =+D22/$D$25 -> 0 | U22: 0 | V22: 0.05 | W22: =S22 -> 0.0062934747 | X22: 0 | Y22: =+U22*$I$25 -> 0 | Z22: =+X22*$D$25 -> 0 | AA22: =+W22*$I$25 -> 9500 | AB22: =+X22*$D$25 -> 0 | AC22: Total | AE22: =+AE15+AE18+AE19+AE20+AE21-AE21 -> 1 | AF22: =+AF15+AF18+AF19+AF20+AF21-AF21 -> 1 | AG22: =AG21+AG15+AG18+AG19+AG20-AG21 -> 1 | AI22: Total | AK22: =+AK15+AK18+AK19+AK20+AK21-AK21 -> 1 | AL22: =+AL15+AL18+AL19+AL20+AL21-AL21 -> 1 | AM22: =+AM15+AM18+AM19+AM20+AM21-AM21 -> 1 | AO22: Total | AQ22: =+AQ15+AQ18+AQ19+AQ20+AQ21-AQ21 -> 1 | AR22: =+AR15+AR18+AR19+AR20+AR21-AR21 -> 1 | AS22: =+AS15+AS18+AS19+AS20+AS21-AS21 -> 1 | AV22: Total | AX22: =+AX15+AX18+AX19+AX20+AX21-AX21 -> 1 | AY22: =+AY15+AY18+AY19+AY20+AY21-AY21 -> 1 | AZ22: =+AZ15+AZ18+AZ19+AZ20+AZ21-AZ21 -> 1
C23: Total | D23: =+D16+D19+D20+D21+D22+D10 -> 1000000 | E23: =+E25-E24 -> 1000000 | H23: Total | I23: =+I16+I19+I20+I21+I22+I10 -> 1271188.6 | J23: =+J25-J24 -> 1433872.6 | L23: =+L16+L19+L20+L21+L22+L10 -> 0 | M23: =I5+I6 -> 162684.07 | N23: =+N16+N19+N20+N21+N22+N10 -> 1433872.6 | O23: =+O16+O19+O20+O21+O22+O10 -> 0.85748493 | P23: =+P16+P19+P20+P21+P22+P10 -> 0.84212558 | R23: Subtotal | S23: =+S16+S19+S20+S21+S22+S10 -> 0.84212558 | T23: =+T16+T19+T20+T21+T22+T10 -> 1 | U23: =+U16+U19+U20+U21+U22+U10 -> 1 | V23: =+V16+V19+V20+V21+V22+V10 -> 1 | W23: =+W16+W19+W20+W21+W22+W10 -> 0.84212558 | X23: =+X16+X19+X20+X21+X22+X10 -> 1 | Y23: =+U23*$I$25 -> 1509500 | Z23: =+X23*$D$25 -> 1000000 | AA23: =+W23*$I$25 -> 1271188.6 | AB23: =+X23*$D$25 -> 1000000
C24: Other single stock holdings | D24: =+Charts!AB128 -> 0 | E24: =+D24 -> 0 | F24: =+E24-D24 -> 0 | H24: =+C24 -> Other single stock holdings | I24: =+Charts!AC110+Charts!AC109 -> 238311.43 | J24: =+I24 -> 238311.43 | K24: =+J24-I24 -> 0 | N24: =+L24+I24+M24 -> 238311.43 | O24: =+N24/$N$25 -> 0.14251507 | P24: =+W24 -> 0.15787442 | R24: =+H24 -> Other single stock holdings | S24: =+I24/$I$25 -> 0.15787442 | T24: =+D24/$D$25 -> 0 | U24: 0 | V24: 0 | W24: =S24 -> 0.15787442 | X24: 0 | Y24: =+U24*$I$25 -> 0 | Z24: =+X24*$D$25 -> 0 | AA24: =+W24*$I$25 -> 238311.43 | AB24: =+X24*$D$25 -> 0
C25: Total | D25: =+D24+D23 -> 1000000 | E25: =+D25+D6+D7 -> 1000000 | H25: Total | I25: =+I24+I23 -> 1509500 | J25: =+I25+I5+I6 -> 1672184.1 | N25: =+N24+N23 -> 1672184.1 | P25: =+W25 -> 1 | R25: Total | S25: =+S23+S24 -> 1 | T25: =+T23+T24 -> 1 | U25: =+U23+U24 -> 1 | V25: =+V23+V24 -> 1 | W25: =+W23+W24 -> 1 | X25: =+X23+X24 -> 1 | Y25: =+Y24+Y23 -> 1509500 | Z25: =+Z24+Z23 -> 1000000 | AA25: =+AA24+AA23 -> 1509500 | AB25: =+AB24+AB23 -> 1000000
I26: =+I25+D25 -> 2509500 | N26: =+N25/I25-1 -> 0.10777348
I27: =+I26=OPTIMIZER!E27 -> TRUE
H30: U.S. Large Cap (S&P 500) | I30: VOO (Vanguard S&P 500)
H31: U.S. Total Market | I31: VTI (Vanguard Total Stock Market)
H32: Large Cap Growth | I32: QQQ (Invesco QQQ Trust - Nasdaq 100) or VUG (Vanguard Growth ETF - Russell 1000)
H33: U.S. Dividend/Quality | I33: SCHD (Schwab U.S. Dividend Equity ETF) or DGRO (iShares Core Dividend Growth ETF)
H34: U.S. Small Cap | I34: VB (Vanguard Small Cap ETF) or IWM (iShares Russell 2000 ETF)
H35: Developed Markets | I35: VEA (Vanguard FTSE Deveoped Market ETF) or IEFA (iShares Core MSCI EAFE ETF)
H36: Emerging Markets | I36: VWO (Vanguard FTSE Emerging Markets ETF) or IEMG (iShares Core MSCI Emerging Markets ETF)
H37: REITS, Commodities | I37: VNQ ( Vanguard Real Estate ETF) or PDBC (Invesco Optimum Yield Diversified Commodity)
H38: Bonds | I38: Bloomberg Aggregate Bond Index
H39: Crypto | I39: Bitwise 10 Crypto Index

Sheet Long-Term Forecast
B1: =+'Cash Flow'!BE119 -> 2025 | C1: =+'Cash Flow'!BJ119 -> 2030 | D1: =+'Cash Flow'!BO119 -> 2035 | E1: =+'Cash Flow'!BP119 -> 2040 | G1: =+B1 -> 2025 | H1: =+C1 -> 2030 | I1: =+D1 -> 2035 | J1: =+E1 -> 2040
A2: Net Worth
A3: Go Alone | B3: =+'Cash Flow'!BE121 -> 4894245.7 | C3: =+'Cash Flow'!BJ121 -> 6449549.1 | D3: =+'Cash Flow'!BO121 -> 8548634.4 | E3: =+'Cash Flow'!BP121 -> 11420835 | G3: =+B3 -> 4894245.7 | H3: =+C3 -> 6449549.1 | I3: =+D3 -> 8548634.4 | J3: =+E3 -> 11420835
A4: With GURU | B4: =+'Cash Flow'!BE122 -> 4894245.7 | C4: =+'Cash Flow'!BJ122 -> 6449549.1 | D4: =+'Cash Flow'!BO122 -> 8548634.4 | E4: =+'Cash Flow'!BP122 -> 11420835 | G4: =+B4-G3 -> 0 | H4: =+C4-H3 -> 0 | I4: =+D4-I3 -> 0 | J4: =+E4-J3 -> 0
B5: =+B4-B3 -> 0 | C5: =+C4-C3 -> 0 | D5: =+D4-D3 -> 0 | E5: =+E4-E3 -> 0
A6: Investments
A7: Go Alone | B7: =+'Cash Flow'!BE128 -> 2690912 | C7: =+'Cash Flow'!BJ128 -> 3774143.2 | D7: =+'Cash Flow'!BO128 -> 5416397.3 | E7: =+'Cash Flow'!BP128 -> 7828573.3
A8: With GURU | B8: =+'Cash Flow'!BE129 -> 2690912 | C8: =+'Cash Flow'!BJ129 -> 3774143.2 | D8: =+'Cash Flow'!BO129 -> 5416397.3 | E8: =+'Cash Flow'!BP129 -> 7828573.3
B9: =+B8-B7 -> 0 | C9: =+C8-C7 -> 0 | D9: =+D8-D7 -> 0 | E9: =+E8-E7 -> 0
A10: Cash
A11: Go Alone | B11: =+'Cash Flow'!BE135 -> 571499.82 | C11: =+'Cash Flow'!BJ135 -> 941408.55 | D11: =+'Cash Flow'!BO135 -> 1323386.7 | E11: =+'Cash Flow'!BP135 -> 1752259.1
A12: With GURU | B12: =+'Cash Flow'!BE136 -> 571499.82 | C12: =+'Cash Flow'!BJ136 -> 941408.55 | D12: =+'Cash Flow'!BO136 -> 1323386.7 | E12: =+'Cash Flow'!BP136 -> 1752259.1

Sheet Dashboard Style
B4: Net Worth | O4: Projected Cumulative Cash Flow | X4: Cash Management Monitor | AM4: Net worth - fake data
B5: =+Charts!S9 -> 4648384 | O5: =+'MoneyBoard - Key Metrics'!C3 -> 66338.316 | X5: SUFFICIENT FUNDS FOR 12 MONTHS | AM5: 43466 | AN5: 3150000
H6: Assets | K6: Liabilities | X6: Cash required for next 12 months | AD6: =-'MoneyBoard - Key Metrics'!$C$6 -> 129384.79 | AM6: 43617 | AN6: =+AN5*(1+AO6) -> 3465000 | AO6: 0.1
X7: Funds to cover cash need | AD7: =+'MoneyBoard - Key Metrics'!C8 -> 372050 | AM7: 43831 | AN7: =+AN6*(1+AO7) -> 3672900 | AO7: 0.06
H8: Bank | J8: =+OPTIMIZER!AR24 -> 20939.42 | AM8: 43831 | AN8: =+AN7*(1+AO8) -> 3783087 | AO8: 0.03
H9: Money Market Fund | J9: =+OPTIMIZER!AR25 -> 129384.79 | AM9: 44197 | AN9: =+AN8*(1+AO9) -> 3896579.6 | AO9: 0.03
H10: Treasuries | J10: =+OPTIMIZER!AR26 -> 194041.71 | AM10: 44348 | AN10: =+AN9*(1+AO10) -> 3701750.6 | AO10: -0.05
H11: Investments | J11: =+'Model Portfolios'!N25 -> 1672184.1 | AM11: 44562 | AN11: =+AN10*(1+AO11) -> 3516663.1 | AO11: -0.05
H12: Real Estate | J12: =+Charts!Z10 -> 1815000 | AE12: =+'MoneyBoard - Balance Sheet'!C82 -> Chase Total Checking | AH12: =+'MoneyBoard - Balance Sheet'!D82 -> 25050 | AM12: 44713 | AN12: =+AN11*(1+AO12) -> 4044162.6 | AO12: 0.15
H13: Carry | J13: =+Charts!Z7 -> 835000 | AE13: =+'MoneyBoard - Balance Sheet'!C83 -> Citizens Private Banking Checking | AH13: =+'MoneyBoard - Balance Sheet'!D83 -> 107000 | AM13: 44927 | AN13: =+AN12*(1+AO13) -> 4246370.7 | AO13: 0.05
H14: Stock Comp | J14: =+Charts!Z8 -> 80000 | AE14: Total Immediate | AG14: =+'MoneyBoard - Balance Sheet'!D84 -> 132050 | AM14: 45078 | AN14: =+AN13*(1+AO14) -> 4331298.1 | AO14: 0.02
H15: Alternative Inv | J15: =+Charts!Z9 -> 250000 | AM15: 45292 | AN15: =+AN14*(1+AO15) -> 4374611.1 | AO15: 0.01
H16: Retirement Accounts | J16: =+Charts!Z6 -> 1000000 | AM16: 45444 | AN16: =+AN15*(1+AO16) -> 4593341.6 | AO16: 0.05
H17: Total | J17: =SUM(J8:K16) -> 5996550 | AM17: 45658 | AN17: =+Charts!S9 -> 4648384
AM20: Projected monthly cash flow
B21: Taxable Brokerage + Retirement Accounts | O21: Income vs. Expense Projection | AC21: Pre-approved Bank Offerings | AM21: 45658 | AN21: =+Charts!E43 -> -19347.3
B22: =+Charts!AB148 -> 2509500 | H22: 1 Year performance | K22: 0.0432 | AC22: HELOC | AE22: SOFR+200bps | AG22: 0.0618 | AM22: 45689 | AN22: =+Charts!F43 -> -1871.9829 | AP22: 45809 | AQ22: 45839 | AR22: 45870 | AS22: 45901 | AT22: 45931
B23: Current vs. Target Model Portfolio | H23: vs. Index | K23: 0.0384 | P23: 45658 | Q23: 45689 | R23: 45717 | S23: 45748 | T23: 45778 | U23: .. | X23: 45962 | Y23: 45992 | AP23: =+Charts!J28 -> 18910.164 | AQ23: =+Charts!K28 -> 18865.289 | AR23: =+Charts!L28 -> 18842.949 | AS23: =+Charts!M28 -> 18838.034 | AT23: =+Charts!N28 -> 18828.49
O24: Income | P24: =+Charts!E28 -> 19092.12 | Q24: =+Charts!F28 -> 19067.437 | R24: =+Charts!G28 -> 19010.765 | S24: =+Charts!H28 -> 18949.217 | T24: =+Charts!I28 -> 18938.666 | U24: .. | X24: =+Charts!O28 -> 18817.566 | Y24: =+Charts!P28 -> 241147.11 | AC24: Margin Loan | AE24: SOFR+100bps | AG24: 0.0518 | AM24: 45717 | AN24: =+Charts!G43 -> -1928.655 | AP24: =+Charts!J42 -> -21939.42 | AQ24: =+Charts!K42 -> -40439.42 | AR24: =+Charts!L42 -> -35939.42 | AS24: =+Charts!M42 -> -20939.42 | AT24: =+Charts!N42 -> -20939.42
O25: Expenses | P25: =+Charts!E42 -> -38439.42 | Q25: =+Charts!F42 -> -20939.42 | R25: =+Charts!G42 -> -20939.42 | S25: =+Charts!H42 -> -65939.42 | T25: =+Charts!I42 -> -24939.42 | U25: .. | X25: =+Charts!O42 -> -24939.42 | Y25: =+Charts!P42 -> -48392.38 | AM25: 45748 | AN25: =+Charts!H43 -> -46990.203 | AP25: =+SUM(AP23:AP24) -> -3029.2556 | AQ25: =+SUM(AQ23:AQ24) -> -21574.131 | AR25: =+SUM(AR23:AR24) -> -17096.471 | AS25: =+SUM(AS23:AS24) -> -2101.3859 | AT25: =+SUM(AT23:AT24) -> -2110.9303
O26: Net Cash Flow | P26: =+SUM(P24:P25) -> -19347.3 | Q26: =+SUM(Q24:Q25) -> -1871.9829 | R26: =+SUM(R24:R25) -> -1928.655 | S26: =+SUM(S24:S25) -> -46990.203 | T26: =+SUM(T24:T25) -> -6000.7541 | U26: … | X26: =+SUM(X24:X25) -> -6121.8545 | Y26: =+SUM(Y24:Y25) -> 192754.73 | AM26: 45778 | AN26: =+Charts!I43 -> -6000.7541
H27: =+Charts!AA139 -> US Total Market | K27: =+Charts!AB139 -> 779877.58 | AM27: 45809 | AN27: =+Charts!J43 -> -3029.2556
H28: =+Charts!AA140 -> US Large Cap | K28: =+Charts!AB140 -> 535000 | AM28: 45839 | AN28: =+Charts!K43 -> -21574.131
H29: =+Charts!AA141 -> US Small Cap | K29: =+Charts!AB141 -> 323582.23 | AM29: 45870 | AN29: =+Charts!L43 -> -17096.471
H30: =+Charts!AA142 -> US Dividend / Value | K30: =+Charts!AB142 -> 94368.991 | O30: GURU OPTIMIZER | AM30: 45901 | AN30: =+Charts!M43 -> -2101.3859
O31: Cash Optimizer | X31: Investments Optimizer | AM31: 45931 | AN31: =+Charts!N43 -> -2110.9303
O32: =+'MoneyBoard - Key Metrics'!A10 -> Cash Excess/Deficit Positon | T32: =+'MoneyBoard - Key Metrics'!C10 -> 162684.07 | X32: =+'MoneyBoard - Key Metrics'!A15 -> Total Cash You Should Invest Today (A+B): | AE32: =+'MoneyBoard - Key Metrics'!C15 -> 385649.51 | AM32: 45962 | AN32: =+Charts!O43 -> -6121.8545
O33: =+'MoneyBoard - Key Metrics'!A11 -> Identified Additional Cash Income / Year | T33: =+'MoneyBoard - Key Metrics'!C11 -> 7207.434 | AF33: =+'MoneyBoard - Key Metrics'!D15 -> 15% increase to investments | AM33: 45992 | AN33: =+Charts!P43 -> 192754.73
V34: =+'MoneyBoard - Key Metrics'!D11 -> 11% increase to your cash flow | X34: =+'MoneyBoard - Key Metrics'!A13 -> A: Cash in Investment Accounts to be Deployed | AE34: =+'MoneyBoard - Key Metrics'!C13 -> 222965.43
X35: =+'MoneyBoard - Key Metrics'!A14 -> B: Excess cash to be reallocate to investments | AE35: =+'MoneyBoard - Key Metrics'!C14 -> 162684.07
O36: Actions Here | X36: Actions Here | AM36: Projected cumulative cashflow
AM38: 45658 | AN38: =+Charts!E47 -> -19347.3
AM39: 45689 | AN39: =+Charts!F47 -> -21219.283
AM41: 45717 | AN41: =+Charts!G47 -> -23147.938
AM42: 45748 | AN42: =+Charts!H47 -> -70138.141
AC43: Tracking Medium-Term Goal | AM43: 45778 | AN43: =+Charts!I47 -> -76138.895
AC44: Current savings | AE44: =+OPTIMIZER!G26 -> 194041.71 | AG44: =+AE44/'Rent vs. Buy'!C17 -> 0.53917325 | AM44: 45809 | AN44: =+Charts!J47 -> -79168.151
AC45: Goal: | AF45: Purchase new primary residence (+$1-2million) | AM45: 45839 | AN45: =+Charts!K47 -> -100742.28
AM46: 45870 | AN46: =+Charts!L47 -> -117838.75
AC47: Target savings | AH47: =+'Rent vs. Buy'!C17 -> 359887.5 | AM47: 45901 | AN47: =+Charts!M47 -> -119940.14
AC48: Estimated date goal reached | AG48: 46753 | AM48: 45931 | AN48: =+Charts!N47 -> -122051.07
AM49: 45962 | AN49: =+Charts!O47 -> -128172.92
AM50: 45992 | AN50: =+Charts!P47 -> 66338.316
AM52: GURU Cash Management
AM53: Reserve | AN53: =+OPTIMIZER!G24 -> 20939.42
AM54: Flow | AN54: =+OPTIMIZER!G25 -> 129384.79
AM55: Build | AN55: =+OPTIMIZER!G26 -> 194041.71
AM56: Long-Term | AN56: =+OPTIMIZER!G27 -> 2672184.1
AM57: Long-Term Other | AN57: =+OPTIMIZER!G28 -> 2980000
B58: Projected Cash Flow | O58: Cash Management Monitor
B59: =+Charts!Q43 -> 66338.316 | F59: total cash flow in 12 months | O59: SUFFICIENT FUNDS | AM59: Taxable brokerage + retirement
O60: Cash required for next 12 months | T60: =-'MoneyBoard - Key Metrics'!$C$6 -> 129384.79 | AM60: =+Charts!AA137 -> Cash | AN60: =+Charts!AB137 -> 222965.43 | AO60: =+Charts!AL137 -> 0
O61: Liquid Accounts: | T61: =+T62+T66+T68+T70+T72 -> 344365.93 | AM61: =+Charts!AA138 -> International | AN61: =+Charts!AB138 -> 244684.55 | AO61: =+Charts!AL138 -> 316538.3
O62: On Hand | T62: =SUM(T63:T64) -> 150324.21 | AM62: US | AN62: =+Charts!AB159 -> 1732828.8 | AO62: =+Charts!AF159 -> 700000
O63: Bank | T63: =+J8 -> 20939.42 | AM63: =+Charts!AA143 -> Meta | AN63: =+Charts!AB143 -> 238311.43 | AO63: =+Charts!AL150 -> 238311.43
O64: Money Market Fund | T64: =+J9 -> 129384.79 | AM64: =+Charts!AA145 -> Crypto | AN64: =+Charts!AB145 -> 9500 | AO64: =+Charts!AL147 -> 9500
O65: 45717 | AM65: =+Charts!AA146 -> Bonds | AN65: =+Charts!AB146 -> 61209.776 | AO65: =+Charts!AL148 -> 301900
O66: T-Bill | T66: =+$J$10*0.3 -> 58212.513 | AM66: =+Charts!AA147 -> REITS, Commodities | AN66: =+Charts!AB147 -> 0 | AO66: =+Charts!AL149 -> 100000
O67: 45809 | AN67: =SUM(AN60:AN66) -> 2509500 | AO67: =SUM(AO60:AO66) -> 1666249.7
O68: T-Bill | T68: =+$J$10*0.4 -> 77616.684
O69: 45901
O70: T-Bill | T70: =+$J$10*0.15 -> 29106.257
O71: 45992
O72: T-Bill | T72: =+$J$10*0.15 -> 29106.257

Sheet Money Movement
B1: Immediate
E2: =+'Cash Flow'!BE75 -> January | F2: =+'Cash Flow'!BF75 -> February | G2: =+'Cash Flow'!BG75 -> March | H2: =+'Cash Flow'!BH75 -> April | I2: =+'Cash Flow'!BI75 -> May | J2: =+'Cash Flow'!BJ75 -> June | K2: =+'Cash Flow'!BK75 -> July | L2: =+'Cash Flow'!BL75 -> August | ... P2: =+'Cash Flow'!BP75 -> December
B3: Status Quo | E3: =+'Cash Flow'!BE77 -> 132050 | F3: =+'Cash Flow'!BF77 -> 132050 | G3: =+'Cash Flow'!BG77 -> 132050 | H3: =+'Cash Flow'!BH77 -> 132050 | I3: =+'Cash Flow'!BI77 -> 132050 | J3: =+'Cash Flow'!BJ77 -> 132050 | K3: =+'Cash Flow'!BK77 -> 132050 | L3: =+'Cash Flow'!BL77 -> 132050 | ... P3: =+'Cash Flow'!BP77 -> 179141.39
B4: GURU | E4: =+'Cash Flow'!BE78 -> 20939.42 | F4: =+'Cash Flow'!BF78 -> 20939.42 | G4: =+'Cash Flow'!BG78 -> 65939.42 | H4: =+'Cash Flow'!BH78 -> 24939.42 | I4: =+'Cash Flow'!BI78 -> 21939.42 | J4: =+'Cash Flow'!BJ78 -> 40439.42 | K4: =+'Cash Flow'!BK78 -> 35939.42 | L4: =+'Cash Flow'!BL78 -> 20939.42 | ... P4: =+'Cash Flow'!BP78 -> 38439.574
B6: Short Term Accounts
E7: =+'Cash Flow'!BE81 -> January | F7: =+'Cash Flow'!BF81 -> February | G7: =+'Cash Flow'!BG81 -> March | H7: =+'Cash Flow'!BH81 -> April | I7: =+'Cash Flow'!BI81 -> May | J7: =+'Cash Flow'!BJ81 -> June | K7: =+'Cash Flow'!BK81 -> July | L7: =+'Cash Flow'!BL81 -> August | ... P7: =+'Cash Flow'!BP81 -> December
B8: =+B3 -> Status Quo | E8: =+'Cash Flow'!BE83 -> 220374.11 | F8: =+'Cash Flow'!BF83 -> 218620.68 | G8: =+'Cash Flow'!BG83 -> 216850.28 | H8: =+'Cash Flow'!BH83 -> 170077.02 | I8: =+'Cash Flow'!BI83 -> 164264.54 | J8: =+'Cash Flow'!BJ83 -> 161409.55 | K8: =+'Cash Flow'!BK83 -> 140047.52 | L8: =+'Cash Flow'!BL83 -> 123165.92 | ... P8: =+'Cash Flow'!BP83 -> 253553.99
B9: GURU | E9: =+'Cash Flow'!BE84 -> 109758.9 | F9: =+'Cash Flow'!BF84 -> 107911.6 | G9: =+'Cash Flow'!BG84 -> 61039.621 | H9: =+'Cash Flow'!BH84 -> 55110.966 | I9: =+'Cash Flow'!BI84 -> 52120.762 | J9: =+'Cash Flow'!BJ84 -> 30620.008 | K9: =+'Cash Flow'!BK84 -> 13590.753 | L9: =+'Cash Flow'!BL84 -> 11516.622 | ... P9: =+'Cash Flow'!BP84 -> 129388.68
B11: Medium-Term Accounts
E12: =+'Cash Flow'!BE87 -> January | F12: =+'Cash Flow'!BF87 -> February | G12: =+'Cash Flow'!BG87 -> March | H12: =+'Cash Flow'!BH87 -> April | I12: =+'Cash Flow'!BI87 -> May | J12: =+'Cash Flow'!BJ87 -> June | K12: =+'Cash Flow'!BK87 -> July | L12: =+'Cash Flow'!BL87 -> August | ... P12: =+'Cash Flow'!BP87 -> December
B13: =+B8 -> Status Quo | E13: =+'Cash Flow'!BE89 -> 135000 | F13: =+'Cash Flow'!BF89 -> 135288.84 | G13: =+'Cash Flow'!BG89 -> 135578.31 | H13: =+'Cash Flow'!BH89 -> 135868.39 | I13: =+'Cash Flow'!BI89 -> 136159.09 | J13: =+'Cash Flow'!BJ89 -> 136450.41 | K13: =+'Cash Flow'!BK89 -> 136742.36 | L13: =+'Cash Flow'!BL89 -> 137034.93 | ... P13: =+'Cash Flow'!BP89 -> 138211.49
B14: GURU | E14: =+'Cash Flow'!BE90 -> 135000 | F14: =+'Cash Flow'!BF90 -> 135288.84 | G14: =+'Cash Flow'!BG90 -> 135578.31 | H14: =+'Cash Flow'!BH90 -> 135868.39 | I14: =+'Cash Flow'!BI90 -> 136159.09 | J14: =+'Cash Flow'!BJ90 -> 136450.41 | K14: =+'Cash Flow'!BK90 -> 136742.36 | L14: =+'Cash Flow'!BL90 -> 137034.93 | ... P14: =+'Cash Flow'!BP90 -> 138211.49
B16: Long-Term Accounts
E17: =+'Cash Flow'!BE93 -> January | F17: =+'Cash Flow'!BF93 -> February | G17: =+'Cash Flow'!BG93 -> March | H17: =+'Cash Flow'!BH93 -> April | I17: =+'Cash Flow'!BI93 -> May | J17: =+'Cash Flow'!BJ93 -> June | K17: =+'Cash Flow'!BK93 -> July | L17: =+'Cash Flow'!BL93 -> August | ... P17: =+'Cash Flow'!BP93 -> December
B18: =+B13 -> Status Quo | E18: =+'Cash Flow'!BE95 -> 2524138.8 | F18: =+'Cash Flow'!BF95 -> 2538862.9 | G18: =+'Cash Flow'!BG95 -> 2553672.9 | H18: =+'Cash Flow'!BH95 -> 2568569.4 | I18: =+'Cash Flow'!BI95 -> 2583552.7 | J18: =+'Cash Flow'!BJ95 -> 2598623.4 | K18: =+'Cash Flow'!BK95 -> 2613782 | L18: =+'Cash Flow'!BL95 -> 2629029.1 | ... P18: =+'Cash Flow'!BP95 -> 2690912
B19: GURU | E19: =+'Cash Flow'!BE96 -> 2524138.8 | F19: =+'Cash Flow'!BF96 -> 2538862.9 | G19: =+'Cash Flow'!BG96 -> 2553672.9 | H19: =+'Cash Flow'!BH96 -> 2568569.4 | I19: =+'Cash Flow'!BI96 -> 2583552.7 | J19: =+'Cash Flow'!BJ96 -> 2598623.4 | K19: =+'Cash Flow'!BK96 -> 2613782 | L19: =+'Cash Flow'!BL96 -> 2629029.1 | ... P19: =+'Cash Flow'!BP96 -> 2690912
B21: Net Worth
E22: =+'Cash Flow'!BE99 -> January | F22: =+'Cash Flow'!BF99 -> February | G22: =+'Cash Flow'!BG99 -> March | H22: =+'Cash Flow'!BH99 -> April | I22: =+'Cash Flow'!BI99 -> May | J22: =+'Cash Flow'!BJ99 -> June | K22: =+'Cash Flow'!BK99 -> July | L22: =+'Cash Flow'!BL99 -> August | ... P22: =+'Cash Flow'!BP99 -> December
B23: =+B18 -> Status Quo | E23: =+'Cash Flow'!BE101 -> 4643396.8 | F23: =+'Cash Flow'!BF101 -> 4656656.4 | G23: =+'Cash Flow'!BG101 -> 4669985.5 | H23: =+'Cash Flow'!BH101 -> 4638398.7 | I23: =+'Cash Flow'!BI101 -> 4647860.3 | J23: =+'Cash Flow'!BJ101 -> 4660367.3 | K23: =+'Cash Flow'!BK101 -> 4654455.9 | L23: =+'Cash Flow'!BL101 -> 4653113.9 | ... P23: =+'Cash Flow'!BP101 -> 4893652.8
B24: GURU | E24: =+'Cash Flow'!BE102 -> 4643396.8 | F24: =+'Cash Flow'!BF102 -> 4656656.4 | G24: =+'Cash Flow'!BG102 -> 4669985.5 | H24: =+'Cash Flow'!BH102 -> 4638398.7 | I24: =+'Cash Flow'!BI102 -> 4647860.3 | J24: =+'Cash Flow'!BJ102 -> 4660367.3 | K24: =+'Cash Flow'!BK102 -> 4654455.9 | L24: =+'Cash Flow'!BL102 -> 4653113.9 | ... P24: =+'Cash Flow'!BP102 -> 4893652.8
E32: =E2 -> January | F32: =F2 -> February | G32: =G2 -> March | H32: =H2 -> April | I32: =I2 -> May | J32: =J2 -> June | K32: =K2 -> July | L32: =L2 -> August | ... P32: =P2 -> December
B33: Plus: Income Allocation to Immediate | E33: =+'Cash Flow'!BE108 -> 18813.53 | F33: =+'Cash Flow'!BF108 -> 18813.53 | G33: =+'Cash Flow'!BG108 -> 18813.53 | H33: =+'Cash Flow'!BH108 -> 18813.53 | I33: =+'Cash Flow'!BI108 -> 18813.53 | J33: =+'Cash Flow'!BJ108 -> 18813.53 | K33: =+'Cash Flow'!BK108 -> 18813.53 | L33: =+'Cash Flow'!BL108 -> 18813.53 | ... P33: =+'Cash Flow'!BP108 -> 38439.42
B34: Less: Expenses | E34: =+'Cash Flow'!BE115 -> -38439.42 | F34: =+'Cash Flow'!BF115 -> -20939.42 | G34: =+'Cash Flow'!BG115 -> -20939.42 | H34: =+'Cash Flow'!BH115 -> -65939.42 | I34: =+'Cash Flow'!BI115 -> -24939.42 | J34: =+'Cash Flow'!BJ115 -> -21939.42 | K34: =+'Cash Flow'!BK115 -> -40439.42 | L34: =+'Cash Flow'!BL115 -> -35939.42 | ... P34: =+'Cash Flow'!BP115 -> -48392.38
B35: Plus: Cash Moved from Short-Term Into Immediate | E35: =+'Cash Flow'!BS78-E36 -> 19625.89 | F35: =+'Cash Flow'!BT78-F36 -> 2125.8026 | G35: =+'Cash Flow'!BU78-G36 -> 47125.803 | H35: =+'Cash Flow'!BV78-H36 -> 6125.7084 | I35: =+'Cash Flow'!BW78-I36 -> 3125.7 | J35: =+'Cash Flow'!BX78-J36 -> 21625.792 | K35: =+'Cash Flow'!BY78-K36 -> 17125.76 | L35: =+'Cash Flow'!BZ78-L36 -> 2125.7304 | ... P35: =+'Cash Flow'!CD78-P36 -> 0
B36: Plus: Cash Moved from Medium-Term Into Immediate | E36: =+'Cash Flow'!BS85 -> 0 | F36: =+'Cash Flow'!BT85 -> 0 | G36: =+'Cash Flow'!BU85 -> 0 | H36: =+'Cash Flow'!BV85 -> 0 | I36: =+'Cash Flow'!BW85 -> 0 | J36: =+'Cash Flow'!BX85 -> 0 | K36: =+'Cash Flow'!BY85 -> 0 | L36: =+'Cash Flow'!BZ85 -> 0 | ... P36: =+'Cash Flow'!CD85 -> 0
B37: Plus: After-Tax Interest Income | E37: 0 | F37: =+'Cash Flow'!BS103 -> 0.087719995 | G37: =+'Cash Flow'!BT103 -> 0.087720179 | H37: =+'Cash Flow'!BU103 -> 0.1819778 | I37: =+'Cash Flow'!BV103 -> 0.19035645 | J37: =+'Cash Flow'!BW103 -> 0.098193463 | K37: =+'Cash Flow'!BX103 -> 0.13065978 | L37: =+'Cash Flow'!BY103 -> 0.15998444 | M37: =+'Cash Flow'!BZ103 -> 0.11913954 | ... P37: =+'Cash Flow'!CC103 -> 0.153602
B38: Immediate | C38: =+OPTIMIZER!AV24 -> CIT Money Market Fund | D38: =+OPTIMIZER!G24 -> 20939.42 | E38: =+E4 -> 20939.42 | F38: =+F4 -> 20939.42 | G38: =+G4 -> 65939.42 | H38: =+H4 -> 24939.42 | I38: =+I4 -> 21939.42 | J38: =+J4 -> 40439.42 | K38: =+K4 -> 35939.42 | L38: =+L4 -> 20939.42 | ... P38: =+P4 -> 38439.574
B40: Plus: Income Allocation to Short-Term | E40: =+'Cash Flow'!BS91 -> 0 | F40: =+'Cash Flow'!BT91 -> 0 | G40: =+'Cash Flow'!BU91 -> 0 | H40: =+'Cash Flow'!BV91 -> 0 | I40: =+'Cash Flow'!BW91 -> 0 | J40: =+'Cash Flow'!BX91 -> 0 | K40: =+'Cash Flow'!BY91 -> 0 | L40: =+'Cash Flow'!BZ91 -> 0 | ... P40: =+'Cash Flow'!CD91 -> 129384.79
B41: Less: Cash Moved from Short-Term Into Immediate | E41: =-E35 -> -19625.89 | F41: =-F35 -> -2125.8026 | G41: =-G35 -> -47125.803 | H41: =-H35 -> -6125.7084 | I41: =-I35 -> -3125.7 | J41: =-J35 -> -21625.792 | K41: =-K35 -> -17125.76 | L41: =-L35 -> -2125.7304 | ... P41: =-P35 -> 0
B42: Plus: After-Tax Interest Income | E42: 0 | F42: =+'Cash Flow'!BS110 -> 278.50276 | G42: =+'Cash Flow'!BT110 -> 253.81978 | H42: =+'Cash Flow'!BU110 -> 197.05337 | I42: =+'Cash Flow'!BV110 -> 135.49652 | J42: =+'Cash Flow'!BW110 -> 125.03808 | K42: =+'Cash Flow'!BX110 -> 96.50414 | L42: =+'Cash Flow'!BY110 -> 51.599503 | M42: =+'Cash Flow'!BZ110 -> 29.299722 | ... P42: =+'Cash Flow'!CC110 -> 3.8822881
B43: Short-Term | C43: =+OPTIMIZER!AV25 -> JPMorgan 100% Treasuries Money Market Fund | D43: =+OPTIMIZER!G25 -> 129384.79 | E43: =+E9 -> 109758.9 | F43: =+F9 -> 107911.6 | G43: =+G9 -> 61039.621 | H43: =+H9 -> 55110.966 | I43: =+I9 -> 52120.762 | J43: =+J9 -> 30620.008 | K43: =+K9 -> 13590.753 | L43: =+L9 -> 11516.622 | ... P43: =+P9 -> 129388.68
B45: Plus: Income Allocation to Immediate | E45: =+'Cash Flow'!BS97 -> 0 | F45: =+'Cash Flow'!BT97 -> 0 | G45: =+'Cash Flow'!BU97 -> 0 | H45: =+'Cash Flow'!BV97 -> 0 | I45: =+'Cash Flow'!BW97 -> 0 | J45: =+'Cash Flow'!BX97 -> 0 | K45: =+'Cash Flow'!BY97 -> 0 | L45: =+'Cash Flow'!BZ97 -> 0 | ... P45: =+'Cash Flow'!CD97 -> 67629.96
B46: Less: Cash Moved from Medium-Term to Immediate | E46: =-E36 -> 0 | F46: =-F36 -> 0 | G46: =-G36 -> 0 | H46: =-H36 -> 0 | I46: =-I36 -> 0 | J46: =-J36 -> 0 | K46: =-K36 -> 0 | L46: =-L36 -> 0 | ... P46: =-P36 -> 0
B47: Plus: After-Tax Interest Income | E47: 0 | F47: =+'Cash Flow'!BS116 -> 288.84375 | G47: =+'Cash Flow'!BT116 -> 289.46176 | H47: =+'Cash Flow'!BU116 -> 290.08108 | I47: =+'Cash Flow'!BV116 -> 290.70174 | J47: =+'Cash Flow'!BW116 -> 291.32372 | K47: =+'Cash Flow'!BX116 -> 291.94703 | L47: =+'Cash Flow'!BY116 -> 292.57167 | M47: =+'Cash Flow'!BZ116 -> 293.19765 | ... P47: =+'Cash Flow'!CC116 -> 295.08365
B48: Medium-Term | C48: =+OPTIMIZER!AV26 -> 1 Year Treasuries + 2028 Muni Bonds | D48: =+OPTIMIZER!G26 -> 194041.71 | E48: =+E14 -> 135000 | F48: =+F14 -> 135288.84 | G48: =+G14 -> 135578.31 | H48: =+H14 -> 135868.39 | I48: =+I14 -> 136159.09 | J48: =+J14 -> 136450.41 | K48: =+K14 -> 136742.36 | L48: =+L14 -> 137034.93 | ... P48: =+P14 -> 138211.49
B50: Long-Term ( Brokerage & Retirement) | C50: =+OPTIMIZER!AV27 -> Growth equity market ETFs | D50: =+OPTIMIZER!G27 -> 2672184.1 | E50: =+E19 -> 2524138.8 | F50: =+F19 -> 2538862.9 | G50: =+G19 -> 2553672.9 | H50: =+H19 -> 2568569.4 | I50: =+I19 -> 2583552.7 | J50: =+J19 -> 2598623.4 | K50: =+K19 -> 2613782 | L50: =+L19 -> 2629029.1 | ... P50: =+P19 -> 2690912
B52: Total Net Worth | E52: =+E24 -> 4643396.8 | F52: =+F24 -> 4656656.4 | G52: =+G24 -> 4669985.5 | H52: =+H24 -> 4638398.7 | I52: =+I24 -> 4647860.3 | J52: =+J24 -> 4660367.3 | K52: =+K24 -> 4654455.9 | L52: =+L24 -> 4653113.9 | ... P52: =+P24 -> 4893652.8

Sheet Cash Flow Walk
B1: 4Q2024 | C1: 1Q2025 | D1: 2Q2025 | E1: 3Q2025 | F1: 4Q2025
B2: December | C2: =+'Cash Flow'!G5 -> March | D2: =+'Cash Flow'!J5 -> June | E2: =+'Cash Flow'!M5 -> September | F2: =+'Cash Flow'!P5 -> December
A3: Beginning | C3: =+B9 -> 193661.05 | D3: =+C9 -> 170513.11 | E3: =+D9 -> 114492.9 | F3: =+E9 -> 73720.909
A4: Income | C4: =SUM('Cash Flow'!$E$16:$G$16) -> 57170.322 | D4: =SUM('Cash Flow'!$H$16:$J$16) -> 56798.047 | E4: =SUM('Cash Flow'!$K$16:$M$16) -> 56546.272 | F4: =SUM('Cash Flow'!$N$16:$P$16) -> 279157.94
A5: Core Expenses | C5: =+C12-SUM(C6:C8) -> -62818.26 | D5: =+D12-SUM(D6:D8) -> -67818.26 | E5: =+E12-SUM(E6:E8) -> -64818.26 | F5: =+F12-SUM(F6:F8) -> -74574.62
A6: Property Taxes | C6: =SUM('Cash Flow'!$E$18:$G$18)+SUM('Cash Flow'!$E$27:$G$27) -> -17500 | D6: =SUM('Cash Flow'!$H$18:$J$18)+SUM('Cash Flow'!$H$27:$J$27) -> 0 | E6: =SUM('Cash Flow'!$K$18:$M$18)+SUM('Cash Flow'!$K$27:$M$27) -> -17500 | F6: =SUM('Cash Flow'!$N$18:$P$18)+SUM('Cash Flow'!$N$27:$P$27) -> -4696.6
A7: Tuition | C7: =SUM('Cash Flow'!$E$50:$G$50) -> 0 | D7: =SUM('Cash Flow'!$H$50:$J$50) -> -15000 | E7: =SUM('Cash Flow'!$K$50:$M$50) -> -15000 | F7: =SUM('Cash Flow'!$N$50:$P$50) -> -15000
A8: Taxes | C8: =SUM('Cash Flow'!$E$62:$G$62) -> 0 | D8: =SUM('Cash Flow'!$H$62:$J$62) -> -30000 | E8: =SUM('Cash Flow'!$K$62:$M$62) -> 0 | F8: =SUM('Cash Flow'!$N$62:$P$62) -> 0
A9: Ending | B9: =+'Cash Flow'!D67 -> 193661.05 | C9: =SUM(C3:C8) -> 170513.11 | D9: =SUM(D3:D8) -> 114492.9 | E9: =SUM(E3:E8) -> 73720.909 | F9: =SUM(F3:F8) -> 259999.36
A12: Total Expenses | C12: =SUM('Cash Flow'!$E$63:$G$63) -> -80318.26 | D12: =SUM('Cash Flow'!$H$63:$J$63) -> -112818.26 | E12: =SUM('Cash Flow'!$K$63:$M$63) -> -97318.26 | F12: =SUM('Cash Flow'!$N$63:$P$63) -> -94271.22 | U12: 1000
C14: =C1 -> 1Q2025 | G14: =D1 -> 2Q2025 | K14: =E1 -> 3Q2025 | O14: =+F1 -> 4Q2025
B15: Beginning | C15: Income | D15: Core Expenses | E15: One-Time Expenses | F15: 45747 | G15: Income | H15: Core Expenses | I15: One-Time Expenses | J15: 45838 | K15: Income | L15: Core Expenses | M15: One-Time Expenses | N15: 45930 | O15: Income | P15: Core Expenses | Q15: One-Time Expenses | R15: 46022 | T15: Beginning 1/1/25 | U15: Annual Income | V15: Core Expenses | W15: One-Time Expenses | X15: Ending Cash 12/31/2025
A16: Total | B16: =+B9 -> 193661.05 | C16: =+C3 -> 193661.05 | D16: =+C16+C17-D17 -> 188013.11 | E16: =D16-E17 -> 170513.11 | F16: =E16 -> 170513.11 | G16: =+D3 -> 170513.11 | H16: =+G16+G17-H17 -> 159492.9 | I16: =H16-I17 -> 114492.9 | J16: =I16 -> 114492.9 | K16: =+E3 -> 114492.9 | L16: =+K16+K17-L17 -> 106220.91 | M16: =L16-M17 -> 73720.909 | N16: =M16 -> 73720.909 | O16: =+F3 -> 73720.909 | P16: =+O16+O17-P17 -> 279695.96 | Q16: =P16-Q17 -> 259999.36 | R16: =Q16 -> 259999.36 | T16: =(+B16)/1000 -> 193.66105 | U16: =+T16 -> 193.66105 | V16: =+U16+U17-V17 -> 374.69596 | W16: =V16-W17 -> 259.99936 | X16: =W16 -> 259.99936
C17: =+C4 -> 57170.322 | D17: =-C5 -> 62818.26 | E17: =-C6-C7-C8 -> 17500 | G17: =+D4 -> 56798.047 | H17: =-D5 -> 67818.26 | I17: =-D6-D7-D8 -> 45000 | K17: =+E4 -> 56546.272 | L17: =-E5 -> 64818.26 | M17: =-E6-E7-E8 -> 32500 | O17: =+F4 -> 279157.94 | P17: =-F5 -> 74574.62 | Q17: =-F6-F7-F8 -> 19696.6 | U17: =(+C17+G17+K17+O17)/1000 -> 451.06432 | V17: =(+D17+H17+L17+P17)/1000 -> 270.0294 | W17: =(+E17+I17+M17+Q17)/1000 -> 114.6966
A19: Data Label | C19: =+C17 -> 57170.322 | D19: =-D17 -> -62818.26 | E19: =-E17 -> -17500 | G19: =+G17 -> 56798.047 | H19: =-H17 -> -67818.26 | I19: =-I17 -> -45000 | K19: =+K17 -> 56546.272 | L19: =-L17 -> -64818.26 | M19: =-M17 -> -32500 | O19: =+O17 -> 279157.94 | P19: =-P17 -> -74574.62 | Q19: =-Q17 -> -19696.6 | U19: =(+C19+G19+K19+O19)/1000 -> 451.06432 | V19: =-V17 -> -270.0294 | W19: =-W17 -> -114.6966

Sheet MoneyBoard - Balance Sheet
C1: SUMMARY NET WORTH / BALANCE SHEET
C3: Category | D3: Current Balance | H3: % of Total
A4: Highly liquid | C4: =+'Balance Sheet'!A14 -> Cash | D4: =+'Balance Sheet'!B14 -> 372050 | H4: =+D4/$D$11 -> 0.062044009
A5: Liquid (tax inefficent) | C5: Liquid Investments (Taxable Brokerage) | D5: =+'Balance Sheet'!B19 -> 1644500 | H5: =+D5/$D$11 -> 0.27424102
A6: Liquid (time to sell) | C6: =+'Balance Sheet'!A33 -> Real Estate | D6: =+'Balance Sheet'!B33 -> 1815000 | H6: =+D6/$D$11 -> 0.30267404
A7: Commited and includes penalties for liquidity | C7: =+'Balance Sheet'!A22 -> Alternative Assets | D7: =+'Balance Sheet'!B22 -> 250000 | H7: =+D7/$D$11 -> 0.041690639 | M7: Total Assets | N7: =+D11 -> 5996550
C8: =+'Balance Sheet'!A26 -> Carry | D8: =+'Balance Sheet'!B26 -> 835000 | H8: =+D8/$D$11 -> 0.13924673 | M8: Less: Total Liabilities | N8: =-D19 -> -1348166
C9: =+'Balance Sheet'!A28 -> Stock Compensation | D9: =+'Balance Sheet'!B28 -> 80000 | H9: =+D9/$D$11 -> 0.013341004 | M9: Your Net Worth: | N9: =SUM(N7:N8) -> 4648384
C10: =+'Balance Sheet'!A36 -> Retirement | D10: =+'Balance Sheet'!B36 -> 1000000 | H10: =+D10/$D$11 -> 0.16676256 | M10: (Assets - Liabilities)
C11: =+'Balance Sheet'!A37 -> Total Assets | D11: =+'Balance Sheet'!B37 -> 5996550 | E11: =+D11=SUM(D4:D10) -> TRUE | H11: =+D11/$D$11 -> 1
C13: Category | D13: Current Balance | H13: % of Total
C14: =+'Balance Sheet'!A43 -> Credit Cards / Lines of Credit | D14: =+'Balance Sheet'!B43 -> 11466.03 | H14: =+D14/$D$19 -> 0.0085049094
C15: =+'Balance Sheet'!A47 -> Student Loans | D15: =+'Balance Sheet'!B47 -> 69700 | H15: =+D15/$D$19 -> 0.051699864
C16: =+'Balance Sheet'!A50 -> Mortgages | D16: =+'Balance Sheet'!B50 -> 1092000 | H16: =+D16/$D$19 -> 0.80998926
C17: =+'Balance Sheet'!A51 -> Professional Loans (Private Equity) | D17: =+'Balance Sheet'!B51 -> 125000 | H17: =+D17/$D$19 -> 0.09271855
C18: =+'Balance Sheet'!A54 -> Remaining Capital Commitment | D18: =+'Balance Sheet'!B54 -> 50000 | H18: =+D18/$D$19 -> 0.03708742
C19: =+'Balance Sheet'!A55 -> Total Liabilities | D19: =+'Balance Sheet'!B55 -> 1348166 | E19: =SUM(D14:D18)=D19 -> TRUE | H19: =+D19/$D$19 -> 1
C25: DETAILED BALANCE SHEET
C27: Asset Category | D27: Current Balance | E27: Return | H27: Comments
C28: ='Balance Sheet'!A7 -> Chase Total Checking | D28: ='Balance Sheet'!B7 -> 25050 | E28: ='Balance Sheet'!E7 -> 0.0005 | H28: Main Account
C29: ='Balance Sheet'!A8 -> Citizens Private Banking Checking | D29: ='Balance Sheet'!B8 -> 107000 | E29: ='Balance Sheet'!E8 -> 0 | H29: Excess
C30: ='Balance Sheet'!A9 -> Checking Bank Accounts | D30: ='Balance Sheet'!B9 -> 132050 | E30: ='Balance Sheet'!E9 -> 9.4850435e-05
C31: ='Balance Sheet'!A10 -> Citizens Private Bank Money Market | D31: ='Balance Sheet'!B10 -> 225000 | E31: ='Balance Sheet'!E10 -> 0.0365 | H31: Excess
C32: ='Balance Sheet'!A11 -> CapitalOne 360 Perf Savings | D32: ='Balance Sheet'!B11 -> 15000 | E32: ='Balance Sheet'!E11 -> 0.0378
C33: ='Balance Sheet'!A12 -> [Savings 3 Placeholder] | D33: ='Balance Sheet'!B12 -> 0 | E33: ='Balance Sheet'!E12 -> 0
C34: ='Balance Sheet'!A13 -> Savings & Money Market Accounts | D34: ='Balance Sheet'!B13 -> 240000 | E34: ='Balance Sheet'!E13 -> 0.03658125
C35: ='Balance Sheet'!A14 -> Cash | D35: ='Balance Sheet'!B14 -> 372050 | E35: ='Balance Sheet'!E14 -> 0.0236313
C36: ='Balance Sheet'!A15 -> Treasuries | D36: ='Balance Sheet'!B15 -> 135000 | E36: ='Balance Sheet'!E15 -> 0.0395
C37: ='Balance Sheet'!A16 -> ETFs/ Mutual Funds | D37: ='Balance Sheet'!B16 -> 1201688.6 | E37: ='Balance Sheet'!E16 -> 0
C38: ='Balance Sheet'!A17 -> Crypto | D38: ='Balance Sheet'!B17 -> 9500 | E38: ='Balance Sheet'!E17 -> 0
C39: ='Balance Sheet'!A18 -> Single Stock | D39: ='Balance Sheet'!B18 -> 298311.43 | E39: [Return]
C40: ='Balance Sheet'!A19 -> Fidelity Taxable Brokerage | D40: ='Balance Sheet'!B19 -> 1644500 | E40: [Return]
C41: ='Balance Sheet'!A20 -> Private Equity Fund 1 | D41: ='Balance Sheet'!B20 -> 75000 | E41: [Return]
C42: ='Balance Sheet'!A21 -> Private Equity Fund 2 | D42: ='Balance Sheet'!B21 -> 175000 | E42: [Return]
C43: ='Balance Sheet'!A22 -> Alternative Assets | D43: ='Balance Sheet'!B22 -> 250000 | E43: [Return]
C44: ='Balance Sheet'!A23 -> Investments | D44: ='Balance Sheet'!B23 -> 1894500 | E44: [Return]
C45: ='Balance Sheet'!A24 -> Carry Private Equity Fund 1 | D45: ='Balance Sheet'!B24 -> 325000 | E45: [Return]
C46: ='Balance Sheet'!A25 -> Carry Private Equity Fund 2 | D46: ='Balance Sheet'!B25 -> 510000 | E46: [Return]
C47: ='Balance Sheet'!A26 -> Carry | D47: ='Balance Sheet'!B26 -> 835000 | E47: [Return]
C48: ='Balance Sheet'!A27 -> Goldman RSUs | D48: ='Balance Sheet'!B27 -> 80000 | E48: [Return]
C49: ='Balance Sheet'!A29 -> Carry and RSUs | D49: ='Balance Sheet'!B29 -> 915000 | E49: [Return]
C50: ='Balance Sheet'!A31 -> Tribeca (Primary) | D50: ='Balance Sheet'!B31 -> 1525000
C51: ='Balance Sheet'!A32 -> Sarasota (Investment) | D51: ='Balance Sheet'!B32 -> 290000 | E51: =+'Cash Flow'!R36 -> 0.03633972 | H51: Below 5%
C52: ='Balance Sheet'!A33 -> Real Estate | D52: ='Balance Sheet'!B33 -> 1815000 | E52: [Return]
C53: Asset Category (Continued) | D53: Current Balance | E53: Return | H53: Comments
C54: ='Balance Sheet'!A34 -> Fidelity 401(k) / IRA | D54: ='Balance Sheet'!B34 -> 620000 | E54: [Return]
C55: ='Balance Sheet'!A35 -> Fidelity Roth IRA | D55: ='Balance Sheet'!B35 -> 380000 | E55: [Return]
C56: ='Balance Sheet'!A36 -> Retirement | D56: ='Balance Sheet'!B36 -> 1000000 | E56: [Return]
C57: ='Balance Sheet'!A37 -> Total Assets | D57: ='Balance Sheet'!B37 -> 5996550 | E57: [Return]
C59: Liability Category | D59: Current Balance | E59: Cost | H59: Comments
C60: ='Balance Sheet'!A40 -> Chase Sapphire Preferred | D60: ='Balance Sheet'!B40 -> 3671.14 | E60: =+'Balance Sheet'!E40 -> 0 | H60: Need to review
C61: ='Balance Sheet'!A41 -> Amex Gold | D61: ='Balance Sheet'!B41 -> 5794.89 | E61: =+'Balance Sheet'!E41 -> 0
C62: ='Balance Sheet'!A42 -> Amazon Card | D62: ='Balance Sheet'!B42 -> 2000 | E62: =+'Balance Sheet'!E42 -> 0
C63: ='Balance Sheet'!#REF! -> #REF! | D63: ='Balance Sheet'!#REF! -> #REF! | E63: [Return]
C64: ='Balance Sheet'!A43 -> Credit Cards / Lines of Credit | D64: ='Balance Sheet'!B43 -> 11466.03 | E64: =+'Balance Sheet'!E44 -> 0
C65: ='Balance Sheet'!A45 -> Undergrad | D65: ='Balance Sheet'!B45 -> 11200 | E65: =+'Balance Sheet'!E45 -> 0.034
C66: ='Balance Sheet'!A46 -> Graduate | D66: ='Balance Sheet'!B46 -> 58500 | E66: =+'Balance Sheet'!E46 -> 0.045
C67: ='Balance Sheet'!A47 -> Student Loans | D67: ='Balance Sheet'!B47 -> 69700 | E67: =+'Balance Sheet'!I47 -> 0.043232425
C68: ='Balance Sheet'!A48 -> Tribeca (Primary) | D68: ='Balance Sheet'!B48 -> 945000 | E68: =+'Balance Sheet'!E48 -> 0.0315 | H68: Floating in 3 mo
C69: ='Balance Sheet'!A49 -> Sarasota (Investment) | D69: ='Balance Sheet'!B49 -> 147000 | E69: =+'Balance Sheet'!E49 -> 0.0255
C70: ='Balance Sheet'!A50 -> Mortgages | D70: ='Balance Sheet'!B50 -> 1092000 | E70: =+'Balance Sheet'!E50 -> 0.030692308
C71: ='Balance Sheet'!A51 -> Professional Loans (Private Equity) | D71: ='Balance Sheet'!B51 -> 125000 | E71: =+'Balance Sheet'!E51 -> 0.065
C72: ='Balance Sheet'!A52 -> Private Equity Fund 1 | D72: ='Balance Sheet'!B52 -> 0 | E72: =+'Balance Sheet'!E52 -> 0
C73: ='Balance Sheet'!A53 -> Private Equity Fund 2 | D73: ='Balance Sheet'!B53 -> 50000 | E73: =+'Balance Sheet'!E53 -> 0
C74: ='Balance Sheet'!A54 -> Remaining Capital Commitment | D74: ='Balance Sheet'!B54 -> 50000 | E74: =+'Balance Sheet'!E54 -> 0
C75: ='Balance Sheet'!A55 -> Total Liabilities | D75: ='Balance Sheet'!B55 -> 1348166 | E75: =+'Balance Sheet'!E55 -> 0.02709555
C77: ='Balance Sheet'!A56 -> Net Worth | D77: ='Balance Sheet'!B56 -> 4648384
C79: GURU METHOD
C81: Category | D81: Current Balance | E81: Current % | H81: Return
C82: =+C28 -> Chase Total Checking | D82: =+D28 -> 25050 | E82: =D82/$D$105 -> 0.004177402 | H82: =+E28 -> 0.0005
C83: =+C29 -> Citizens Private Banking Checking | D83: =+D29 -> 107000 | E83: =D83/$D$105 -> 0.017843593 | H83: =+E29 -> 0
C84: Immediate | D84: =SUM(D82:D83) -> 132050 | E84: =D84/$D$105 -> 0.022020995 | H84: =SUMPRODUCT(H82:H83,D82:D83)/D84 -> 9.4850435e-05
C85: =+C31 -> Citizens Private Bank Money Market | D85: =+D31 -> 225000 | E85: =D85/$D$105 -> 0.037521575 | H85: =+E31 -> 0.0365
C86: =+C32 -> CapitalOne 360 Perf Savings | D86: =+D32 -> 15000 | E86: =D86/$D$105 -> 0.0025014383 | H86: =+E32 -> 0.0378
C87: Short-Term | D87: =SUM(D85:D86) -> 240000 | E87: =D87/$D$105 -> 0.040023013 | H87: =SUMPRODUCT(H85:H86,D85:D86)/D87 -> 0.03658125
C88: =+C40&" "&C36 -> Fidelity Taxable Brokerage Treasuries | D88: =+D36 -> 135000 | E88: =D88/$D$105 -> 0.022512945 | F88: Brokerage | G88: Retirement | H88: =+'Balance Sheet'!E15 -> 0.0395
C89: Medium-Term | D89: =+D88 -> 135000 | E89: =D89/$D$105 -> 0.022512945 | F89: =F98+F97+F90+F99 -> 1509500 | G89: =G98+G97+G90+G99 -> 1000000
C90: Cash | D90: =+SUM(F90:G90) -> 222965.43 | E90: =D90/$D$105 -> 0.037182285 | F90: =SUMIF(Charts!$AB$103:$AB$112,'MoneyBoard - Balance Sheet'!C90,Charts!$AC$103:$AC$112) -> 186585.93 | G90: =SUMIF(Charts!$AA$124:$AA$131,'MoneyBoard - Balance Sheet'!C90,Charts!$AB$124:$AB$131) -> 36379.5
C91: =+Charts!AB104 -> International | D91: =+SUM(F91:G91) -> 244684.55 | E91: =D91/$D$105 -> 0.040804221 | F91: =SUMIF(Charts!$AB$103:$AB$112,'MoneyBoard - Balance Sheet'!C91,Charts!$AC$103:$AC$112) -> 116538.3 | G91: =SUMIF(Charts!$AA$124:$AA$131,'MoneyBoard - Balance Sheet'!C91,Charts!$AB$124:$AB$131) -> 128146.25
C92: =+Charts!AB105 -> US Total Market | D92: =+SUM(F92:G92) -> 779877.58 | E92: =D92/$D$105 -> 0.13005438 | F92: =SUMIF(Charts!$AB$103:$AB$112,'MoneyBoard - Balance Sheet'!C92,Charts!$AC$103:$AC$112) -> 379877.58 | G92: =SUMIF(Charts!$AA$124:$AA$131,'MoneyBoard - Balance Sheet'!C92,Charts!$AB$124:$AB$131) -> 400000
C93: =+Charts!AB106 -> US Large Cap | D93: =+SUM(F93:G93) -> 535000 | E93: =D93/$D$105 -> 0.089217967 | F93: =SUMIF(Charts!$AB$103:$AB$112,'MoneyBoard - Balance Sheet'!C93,Charts!$AC$103:$AC$112) -> 435000 | G93: =SUMIF(Charts!$AA$124:$AA$131,'MoneyBoard - Balance Sheet'!C93,Charts!$AB$124:$AB$131) -> 100000
C94: =+Charts!AB107 -> US Small Cap | D94: =+SUM(F94:G94) -> 323582.23 | E94: =D94/$D$105 -> 0.0539614 | F94: =SUMIF(Charts!$AB$103:$AB$112,'MoneyBoard - Balance Sheet'!C94,Charts!$AC$103:$AC$112) -> 49317.756 | G94: =SUMIF(Charts!$AA$124:$AA$131,'MoneyBoard - Balance Sheet'!C94,Charts!$AB$124:$AB$131) -> 274264.47
C95: =+Charts!AB108 -> US Dividend / Value | D95: =+SUM(F95:G95) -> 94368.991 | E95: =D95/$D$105 -> 0.015737214 | F95: =SUMIF(Charts!$AB$103:$AB$112,'MoneyBoard - Balance Sheet'!C95,Charts!$AC$103:$AC$112) -> 94368.991 | G95: =SUMIF(Charts!$AA$124:$AA$131,'MoneyBoard - Balance Sheet'!C95,Charts!$AB$124:$AB$131) -> 0
C96: Single Stock | D96: =+SUM(F96:G96) -> 238311.43 | E96: =D96/$D$105 -> 0.039741424 | F96: =SUM(D107:D108) -> 238311.43 | G96: =SUM(F107:F108) -> 0
C97: Equities | D97: =+SUM(F97:G97) -> 2215824.8 | E97: =D97/$D$105 -> 0.3695166 | F97: =SUM(F91:F96) -> 1313414.1 | G97: =SUM(G91:G96) -> 902410.72
C98: Bonds | D98: =+SUM(F98:G98) -> 61209.776 | E98: =D98/$D$105 -> 0.010207499 | F98: =SUMIF(Charts!$AB$103:$AB$112,'MoneyBoard - Balance Sheet'!C98,Charts!$AC$103:$AC$112) -> 0 | G98: =SUMIF(Charts!$AA$124:$AA$131,'MoneyBoard - Balance Sheet'!C98,Charts!$AB$124:$AB$131) -> 61209.776
C99: =+Charts!AB111 -> Crypto | D99: =+SUM(F99:G99) -> 9500 | E99: =D99/$D$105 -> 0.0015842443 | F99: =SUMIF(Charts!$AB$103:$AB$112,'MoneyBoard - Balance Sheet'!C99,Charts!$AC$103:$AC$112) -> 9500 | G99: =SUMIF(Charts!$AA$124:$AA$131,'MoneyBoard - Balance Sheet'!C99,Charts!$AB$124:$AB$131) -> 0
C100: Long-Term | D100: =D90+D97+D98+D99 -> 2509500 | E100: =D100/$D$105 -> 0.41849063 | F100: =F90+F97+F98+F99 -> 1509500 | G100: =G90+G97+G98+G99 -> 1000000 | H100: [Return]
C101: Memo:
C102: Long-Term Liquid | D102: =F100 -> 1509500 | E102: =D102/$D$105 -> 0.25172808
C103: Long-Term Retirement | D103: =G100 -> 1000000 | E103: =D103/$D$105 -> 0.16676256
C104: Long-Term Other | D104: =+D52+D49+D43 -> 2980000 | E104: =D104/$D$105 -> 0.49695241
C105: Total | D105: =+D104+D100+D89+D87+D84 -> 5996550
C107: =+Charts!AB109 -> Meta | D107: =SUMIF(Charts!$AB$103:$AB$112,'MoneyBoard - Balance Sheet'!C107,Charts!$AC$103:$AC$112) -> 238311.43 | F107: =SUMIF(Charts!$AA$124:$AA$131,'MoneyBoard - Balance Sheet'!C107,Charts!$AB$124:$AB$131) -> 0
C108: =+Charts!AB110 -> Other Single Stock | D108: =SUMIF(Charts!$AB$103:$AB$112,'MoneyBoard - Balance Sheet'!C108,Charts!$AC$103:$AC$112) -> 0 | F108: =SUMIF(Charts!$AA$124:$AA$131,'MoneyBoard - Balance Sheet'!C108,Charts!$AB$124:$AB$131) -> 0

Sheet Charts
A2: DASHBOARD OUTPUT [WORK IN PROGRESS]
A3: Assets | L3: Liabilities
V4: THESE COLUMNS HAVE DATA FOR THE CHARTS TO THE LEFT
V5: =A3 -> Assets
V6: Retirement Assets | Z6: =(('Balance Sheet'!B36)/1000)*1000 -> 1000000 | AE6: =L3 -> Liabilities
V7: Private Equity Carry | Z7: =+'Balance Sheet'!B24+'Balance Sheet'!B25 -> 835000 | AE7: Credit Cards / Line of Credits | AG7: =(('Balance Sheet'!B43)/1000)*1000 -> 11466.03
S8: Net Worth | V8: Stock Compensation | Z8: =+'Balance Sheet'!B28 -> 80000 | AE8: Student Debt | AG8: =('Balance Sheet'!B47) -> 69700
S9: ='Balance Sheet'!B56 -> 4648384 | V9: Alternative Asset Investments | Z9: =+'Balance Sheet'!B22 -> 250000 | AE9: Mortgages | AG9: =(('Balance Sheet'!B50)/1000)*1000 -> 1092000
V10: Real Estate | Z10: =(('Balance Sheet'!B33)/1000)*1000 -> 1815000 | AE10: Professional / PE Loans | AG10: =+'Balance Sheet'!B51 -> 125000
V11: Liquid Investments | Z11: =+'Balance Sheet'!B15+'Balance Sheet'!B16+'Balance Sheet'!B17+'Balance Sheet'!B18 -> 1644500 | AE11: Remaining Capital Commitment | AG11: =+'Balance Sheet'!B54 -> 50000
V12: Cash | Z12: =(('Balance Sheet'!B14)/1000)*1000 -> 372050 | AE12: Total | AG12: =(SUM(AG7:AG11)) -> 1348166
V13: Total | Z13: =SUM(Z6:Z12) -> 5996550 | AA13: =+AA6+SUM(Z6:Z12) -> 5996550 | AG13: =+AG12='Balance Sheet'!B55 -> TRUE
V14: Check | Z14: =+Z13='Balance Sheet'!B37 -> TRUE
V17: Cash_Treasuries | Z17: =+'Balance Sheet'!B14+'Balance Sheet'!B15 -> 507050
B19: Return / Yield: | C19: [TBD] | E19: [TBD] | F19: [TBD] | G19: [TBD] | H19: [TBD] | I19: [TBD] | K19: Cost: | M19: [TBD] | N19: [TBD] | O19: [TBD] | Q19: [TBD]
A22: Cash Flow Prediction Model
D24: Actual | E24: Forecast | Q24: Next 12
D25: =+'Cash Flow'!D5 -> December | E25: =+'Cash Flow'!E5 -> January | F25: =+'Cash Flow'!F5 -> February | G25: =+'Cash Flow'!G5 -> March | H25: =+'Cash Flow'!H5 -> April | I25: =+'Cash Flow'!I5 -> May | J25: =+'Cash Flow'!J5 -> June | K25: =+'Cash Flow'!K5 -> July | ... P25: =+'Cash Flow'!P5 -> December | Q25: Months
A26: =+'Cash Flow'!A10 -> Compensation | D26: =+SUMIF('Cash Flow'!$A$6:$A$67,$A26,'Cash Flow'!D$6:D$67) -> 235454.17 | E26: =+SUMIF('Cash Flow'!$A$6:$A$67,$A26,'Cash Flow'!E$6:E$67) -> 18813.53 | F26: =+SUMIF('Cash Flow'!$A$6:$A$67,$A26,'Cash Flow'!F$6:F$67) -> 18813.53 | G26: =+SUMIF('Cash Flow'!$A$6:$A$67,$A26,'Cash Flow'!G$6:G$67) -> 18813.53 | H26: =+SUMIF('Cash Flow'!$A$6:$A$67,$A26,'Cash Flow'!H$6:H$67) -> 18813.53 | I26: =+SUMIF('Cash Flow'!$A$6:$A$67,$A26,'Cash Flow'!I$6:I$67) -> 18813.53 | J26: =+SUMIF('Cash Flow'!$A$6:$A$67,$A26,'Cash Flow'!J$6:J$67) -> 18813.53 | K26: =+SUMIF('Cash Flow'!$A$6:$A$67,$A26,'Cash Flow'!K$6:K$67) -> 18813.53 | ... P26: =+SUMIF('Cash Flow'!$A$6:$A$67,$A26,'Cash Flow'!P$6:P$67) -> 235454.17 | Q26: =SUM(E26:P26) -> 442403
A27: =+'Cash Flow'!A15 -> Interest From Bank Accounts | D27: =+SUMIF('Cash Flow'!$A$6:$A$67,$A27,'Cash Flow'!D$6:D$67) -> 388.31444 | E27: =+SUMIF('Cash Flow'!$A$6:$A$67,$A27,'Cash Flow'!E$6:E$67) -> 278.59048 | F27: =+SUMIF('Cash Flow'!$A$6:$A$67,$A27,'Cash Flow'!F$6:F$67) -> 253.9075 | G27: =+SUMIF('Cash Flow'!$A$6:$A$67,$A27,'Cash Flow'!G$6:G$67) -> 197.23535 | H27: =+SUMIF('Cash Flow'!$A$6:$A$67,$A27,'Cash Flow'!H$6:H$67) -> 135.68688 | I27: =+SUMIF('Cash Flow'!$A$6:$A$67,$A27,'Cash Flow'!I$6:I$67) -> 125.13627 | J27: =+SUMIF('Cash Flow'!$A$6:$A$67,$A27,'Cash Flow'!J$6:J$67) -> 96.6348 | K27: =+SUMIF('Cash Flow'!$A$6:$A$67,$A27,'Cash Flow'!K$6:K$67) -> 51.759487 | ... P27: =+SUMIF('Cash Flow'!$A$6:$A$67,$A27,'Cash Flow'!P$6:P$67) -> 5692.9393 | Q27: =SUM(E27:P27) -> 8661.3155
A28: =+'Cash Flow'!A16 -> Cash Income | D28: =+SUMIF('Cash Flow'!$A$6:$A$67,$A28,'Cash Flow'!D$6:D$67) -> 235842.49 | E28: =+SUMIF('Cash Flow'!$A$6:$A$67,$A28,'Cash Flow'!E$6:E$67) -> 19092.12 | F28: =+SUMIF('Cash Flow'!$A$6:$A$67,$A28,'Cash Flow'!F$6:F$67) -> 19067.437 | G28: =+SUMIF('Cash Flow'!$A$6:$A$67,$A28,'Cash Flow'!G$6:G$67) -> 19010.765 | H28: =+SUMIF('Cash Flow'!$A$6:$A$67,$A28,'Cash Flow'!H$6:H$67) -> 18949.217 | I28: =+SUMIF('Cash Flow'!$A$6:$A$67,$A28,'Cash Flow'!I$6:I$67) -> 18938.666 | J28: =+SUMIF('Cash Flow'!$A$6:$A$67,$A28,'Cash Flow'!J$6:J$67) -> 18910.164 | K28: =+SUMIF('Cash Flow'!$A$6:$A$67,$A28,'Cash Flow'!K$6:K$67) -> 18865.289 | ... P28: =+SUMIF('Cash Flow'!$A$6:$A$67,$A28,'Cash Flow'!P$6:P$67) -> 241147.11 | Q28: =SUM(E28:P28) -> 451064.32
A29: =+'Cash Flow'!A17 -> Rent on Primary Residence | D29: =+SUMIF('Cash Flow'!$A$6:$A$67,$A29,'Cash Flow'!D$6:D$67) -> 0 | E29: =+SUMIF('Cash Flow'!$A$6:$A$67,$A29,'Cash Flow'!E$6:E$67) -> 0 | F29: =+SUMIF('Cash Flow'!$A$6:$A$67,$A29,'Cash Flow'!F$6:F$67) -> 0 | G29: =+SUMIF('Cash Flow'!$A$6:$A$67,$A29,'Cash Flow'!G$6:G$67) -> 0 | H29: =+SUMIF('Cash Flow'!$A$6:$A$67,$A29,'Cash Flow'!H$6:H$67) -> 0 | I29: =+SUMIF('Cash Flow'!$A$6:$A$67,$A29,'Cash Flow'!I$6:I$67) -> 0 | J29: =+SUMIF('Cash Flow'!$A$6:$A$67,$A29,'Cash Flow'!J$6:J$67) -> 0 | K29: =+SUMIF('Cash Flow'!$A$6:$A$67,$A29,'Cash Flow'!K$6:K$67) -> 0 | ... P29: =+SUMIF('Cash Flow'!$A$6:$A$67,$A29,'Cash Flow'!P$6:P$67) -> 0 | Q29: =SUM(E29:P29) -> 0
A30: =+'Cash Flow'!A26 -> Manhattan Apartment | D30: =+SUMIF('Cash Flow'!$A$6:$A$67,$A30,'Cash Flow'!D$6:D$67) -> -4523.8817 | E30: =+SUMIF('Cash Flow'!$A$6:$A$67,$A30,'Cash Flow'!E$6:E$67) -> -22023.882 | F30: =+SUMIF('Cash Flow'!$A$6:$A$67,$A30,'Cash Flow'!F$6:F$67) -> -4523.8817 | G30: =+SUMIF('Cash Flow'!$A$6:$A$67,$A30,'Cash Flow'!G$6:G$67) -> -4523.8817 | H30: =+SUMIF('Cash Flow'!$A$6:$A$67,$A30,'Cash Flow'!H$6:H$67) -> -4523.8817 | I30: =+SUMIF('Cash Flow'!$A$6:$A$67,$A30,'Cash Flow'!I$6:I$67) -> -4523.8817 | J30: =+SUMIF('Cash Flow'!$A$6:$A$67,$A30,'Cash Flow'!J$6:J$67) -> -4523.8817 | K30: =+SUMIF('Cash Flow'!$A$6:$A$67,$A30,'Cash Flow'!K$6:K$67) -> -22023.882 | ... P30: =+SUMIF('Cash Flow'!$A$6:$A$67,$A30,'Cash Flow'!P$6:P$67) -> -4523.8817 | Q30: =SUM(E30:P30) -> -89286.58
A31: =+'Cash Flow'!A36 -> Florida Investment Property | D31: =+SUMIF('Cash Flow'!$A$6:$A$67,$A31,'Cash Flow'!D$6:D$67) -> -5075.73 | E31: =+SUMIF('Cash Flow'!$A$6:$A$67,$A31,'Cash Flow'!E$6:E$67) -> 1166.29 | F31: =+SUMIF('Cash Flow'!$A$6:$A$67,$A31,'Cash Flow'!F$6:F$67) -> 1166.29 | G31: =+SUMIF('Cash Flow'!$A$6:$A$67,$A31,'Cash Flow'!G$6:G$67) -> 1166.29 | H31: =+SUMIF('Cash Flow'!$A$6:$A$67,$A31,'Cash Flow'!H$6:H$67) -> 1166.29 | I31: =+SUMIF('Cash Flow'!$A$6:$A$67,$A31,'Cash Flow'!I$6:I$67) -> 1166.29 | J31: =+SUMIF('Cash Flow'!$A$6:$A$67,$A31,'Cash Flow'!J$6:J$67) -> 1166.29 | K31: =+SUMIF('Cash Flow'!$A$6:$A$67,$A31,'Cash Flow'!K$6:K$67) -> 1166.29 | ... P31: =+SUMIF('Cash Flow'!$A$6:$A$67,$A31,'Cash Flow'!P$6:P$67) -> -7632.61 | Q31: =SUM(E31:P31) -> 5196.58
A32: =+'Cash Flow'!A39 -> Alternative Investments | D32: =+SUMIF('Cash Flow'!$A$6:$A$67,$A32,'Cash Flow'!D$6:D$67) -> -677.08333 | E32: =+SUMIF('Cash Flow'!$A$6:$A$67,$A32,'Cash Flow'!E$6:E$67) -> -677.08333 | F32: =+SUMIF('Cash Flow'!$A$6:$A$67,$A32,'Cash Flow'!F$6:F$67) -> -677.08333 | G32: =+SUMIF('Cash Flow'!$A$6:$A$67,$A32,'Cash Flow'!G$6:G$67) -> -677.08333 | H32: =+SUMIF('Cash Flow'!$A$6:$A$67,$A32,'Cash Flow'!H$6:H$67) -> -677.08333 | I32: =+SUMIF('Cash Flow'!$A$6:$A$67,$A32,'Cash Flow'!I$6:I$67) -> -677.08333 | J32: =+SUMIF('Cash Flow'!$A$6:$A$67,$A32,'Cash Flow'!J$6:J$67) -> -677.08333 | K32: =+SUMIF('Cash Flow'!$A$6:$A$67,$A32,'Cash Flow'!K$6:K$67) -> -677.08333 | ... P32: =+SUMIF('Cash Flow'!$A$6:$A$67,$A32,'Cash Flow'!P$6:P$67) -> -677.08333 | Q32: =SUM(E32:P32) -> -8125
A33: =+'Cash Flow'!A42 -> Student Debt | D33: =+SUMIF('Cash Flow'!$A$6:$A$67,$A33,'Cash Flow'!D$6:D$67) -> -759.44167 | E33: =+SUMIF('Cash Flow'!$A$6:$A$67,$A33,'Cash Flow'!E$6:E$67) -> -759.44167 | F33: =+SUMIF('Cash Flow'!$A$6:$A$67,$A33,'Cash Flow'!F$6:F$67) -> -759.44167 | G33: =+SUMIF('Cash Flow'!$A$6:$A$67,$A33,'Cash Flow'!G$6:G$67) -> -759.44167 | H33: =+SUMIF('Cash Flow'!$A$6:$A$67,$A33,'Cash Flow'!H$6:H$67) -> -759.44167 | I33: =+SUMIF('Cash Flow'!$A$6:$A$67,$A33,'Cash Flow'!I$6:I$67) -> -759.44167 | J33: =+SUMIF('Cash Flow'!$A$6:$A$67,$A33,'Cash Flow'!J$6:J$67) -> -759.44167 | K33: =+SUMIF('Cash Flow'!$A$6:$A$67,$A33,'Cash Flow'!K$6:K$67) -> -759.44167 | ... P33: =+SUMIF('Cash Flow'!$A$6:$A$67,$A33,'Cash Flow'!P$6:P$67) -> -759.44167 | Q33: =SUM(E33:P33) -> -9113.3
A34: =+'Cash Flow'!A46 -> Cars | D34: =+SUMIF('Cash Flow'!$A$6:$A$67,$A34,'Cash Flow'!D$6:D$67) -> 0 | E34: =+SUMIF('Cash Flow'!$A$6:$A$67,$A34,'Cash Flow'!E$6:E$67) -> 0 | F34: =+SUMIF('Cash Flow'!$A$6:$A$67,$A34,'Cash Flow'!F$6:F$67) -> 0 | G34: =+SUMIF('Cash Flow'!$A$6:$A$67,$A34,'Cash Flow'!G$6:G$67) -> 0 | H34: =+SUMIF('Cash Flow'!$A$6:$A$67,$A34,'Cash Flow'!H$6:H$67) -> 0 | I34: =+SUMIF('Cash Flow'!$A$6:$A$67,$A34,'Cash Flow'!I$6:I$67) -> 0 | J34: =+SUMIF('Cash Flow'!$A$6:$A$67,$A34,'Cash Flow'!J$6:J$67) -> 0 | K34: =+SUMIF('Cash Flow'!$A$6:$A$67,$A34,'Cash Flow'!K$6:K$67) -> 0 | ... P34: =+SUMIF('Cash Flow'!$A$6:$A$67,$A34,'Cash Flow'!P$6:P$67) -> 0 | Q34: =SUM(E34:P34) -> 0
A35: =+'Cash Flow'!A49 -> Credit Cards | D35: =+SUMIF('Cash Flow'!$A$6:$A$67,$A35,'Cash Flow'!D$6:D$67) -> -11466.03 | E35: =+SUMIF('Cash Flow'!$A$6:$A$67,$A35,'Cash Flow'!E$6:E$67) -> -11466.03 | F35: =+SUMIF('Cash Flow'!$A$6:$A$67,$A35,'Cash Flow'!F$6:F$67) -> -11466.03 | G35: =+SUMIF('Cash Flow'!$A$6:$A$67,$A35,'Cash Flow'!G$6:G$67) -> -11466.03 | H35: =+SUMIF('Cash Flow'!$A$6:$A$67,$A35,'Cash Flow'!H$6:H$67) -> -11466.03 | I35: =+SUMIF('Cash Flow'!$A$6:$A$67,$A35,'Cash Flow'!I$6:I$67) -> -11466.03 | J35: =+SUMIF('Cash Flow'!$A$6:$A$67,$A35,'Cash Flow'!J$6:J$67) -> -11466.03 | K35: =+SUMIF('Cash Flow'!$A$6:$A$67,$A35,'Cash Flow'!K$6:K$67) -> -11466.03 | ... P35: =+SUMIF('Cash Flow'!$A$6:$A$67,$A35,'Cash Flow'!P$6:P$67) -> -11466.03 | Q35: =SUM(E35:P35) -> -137592.36
A36: =+'Cash Flow'!A48 -> Personal Insurance | D36: =+SUMIF('Cash Flow'!$A$6:$A$67,$A36,'Cash Flow'!D$6:D$67) -> 0 | E36: =+SUMIF('Cash Flow'!$A$6:$A$67,$A36,'Cash Flow'!E$6:E$67) -> 0 | F36: =+SUMIF('Cash Flow'!$A$6:$A$67,$A36,'Cash Flow'!F$6:F$67) -> 0 | G36: =+SUMIF('Cash Flow'!$A$6:$A$67,$A36,'Cash Flow'!G$6:G$67) -> 0 | H36: =+SUMIF('Cash Flow'!$A$6:$A$67,$A36,'Cash Flow'!H$6:H$67) -> 0 | I36: =+SUMIF('Cash Flow'!$A$6:$A$67,$A36,'Cash Flow'!I$6:I$67) -> 0 | J36: =+SUMIF('Cash Flow'!$A$6:$A$67,$A36,'Cash Flow'!J$6:J$67) -> 0 | K36: =+SUMIF('Cash Flow'!$A$6:$A$67,$A36,'Cash Flow'!K$6:K$67) -> 0 | ... P36: =+SUMIF('Cash Flow'!$A$6:$A$67,$A36,'Cash Flow'!P$6:P$67) -> 0 | Q36: =SUM(D36:O36) -> 0
A37: =+'Cash Flow'!A53 -> Dependent Care | D37: =+SUMIF('Cash Flow'!$A$6:$A$67,$A37,'Cash Flow'!D$6:D$67) -> -19333.333 | E37: =+SUMIF('Cash Flow'!$A$6:$A$67,$A37,'Cash Flow'!E$6:E$67) -> -4333.3333 | F37: =+SUMIF('Cash Flow'!$A$6:$A$67,$A37,'Cash Flow'!F$6:F$67) -> -4333.3333 | G37: =+SUMIF('Cash Flow'!$A$6:$A$67,$A37,'Cash Flow'!G$6:G$67) -> -4333.3333 | H37: =+SUMIF('Cash Flow'!$A$6:$A$67,$A37,'Cash Flow'!H$6:H$67) -> -19333.333 | I37: =+SUMIF('Cash Flow'!$A$6:$A$67,$A37,'Cash Flow'!I$6:I$67) -> -4333.3333 | J37: =+SUMIF('Cash Flow'!$A$6:$A$67,$A37,'Cash Flow'!J$6:J$67) -> -4333.3333 | K37: =+SUMIF('Cash Flow'!$A$6:$A$67,$A37,'Cash Flow'!K$6:K$67) -> -4333.3333 | ... P37: =+SUMIF('Cash Flow'!$A$6:$A$67,$A37,'Cash Flow'!P$6:P$67) -> -19333.333 | Q37: =SUM(D37:O37) -> -97000
A38: =+'Cash Flow'!A55 -> Club Memberships | D38: =+SUMIF('Cash Flow'!$A$6:$A$67,$A38,'Cash Flow'!D$6:D$67) -> 0 | E38: =+SUMIF('Cash Flow'!$A$6:$A$67,$A38,'Cash Flow'!E$6:E$67) -> 0 | F38: =+SUMIF('Cash Flow'!$A$6:$A$67,$A38,'Cash Flow'!F$6:F$67) -> 0 | G38: =+SUMIF('Cash Flow'!$A$6:$A$67,$A38,'Cash Flow'!G$6:G$67) -> 0 | H38: =+SUMIF('Cash Flow'!$A$6:$A$67,$A38,'Cash Flow'!H$6:H$67) -> 0 | I38: =+SUMIF('Cash Flow'!$A$6:$A$67,$A38,'Cash Flow'!I$6:I$67) -> 0 | J38: =+SUMIF('Cash Flow'!$A$6:$A$67,$A38,'Cash Flow'!J$6:J$67) -> 0 | K38: =+SUMIF('Cash Flow'!$A$6:$A$67,$A38,'Cash Flow'!K$6:K$67) -> 0 | ... P38: =+SUMIF('Cash Flow'!$A$6:$A$67,$A38,'Cash Flow'!P$6:P$67) -> 0 | Q38: =SUM(D38:O38) -> 0
A39: =+'Cash Flow'!A59 -> Phone / Utilities | D39: =+SUMIF('Cash Flow'!$A$6:$A$67,$A39,'Cash Flow'!D$6:D$67) -> -345.94 | E39: =+SUMIF('Cash Flow'!$A$6:$A$67,$A39,'Cash Flow'!E$6:E$67) -> -345.94 | F39: =+SUMIF('Cash Flow'!$A$6:$A$67,$A39,'Cash Flow'!F$6:F$67) -> -345.94 | G39: =+SUMIF('Cash Flow'!$A$6:$A$67,$A39,'Cash Flow'!G$6:G$67) -> -345.94 | H39: =+SUMIF('Cash Flow'!$A$6:$A$67,$A39,'Cash Flow'!H$6:H$67) -> -345.94 | I39: =+SUMIF('Cash Flow'!$A$6:$A$67,$A39,'Cash Flow'!I$6:I$67) -> -345.94 | J39: =+SUMIF('Cash Flow'!$A$6:$A$67,$A39,'Cash Flow'!J$6:J$67) -> -345.94 | K39: =+SUMIF('Cash Flow'!$A$6:$A$67,$A39,'Cash Flow'!K$6:K$67) -> -345.94 | ... P39: =+SUMIF('Cash Flow'!$A$6:$A$67,$A39,'Cash Flow'!P$6:P$67) -> 0 | Q39: =SUM(D39:O39) -> -4151.28
A40: =+'Cash Flow'!A61 -> Travel (not on credit card) | D40: =+SUMIF('Cash Flow'!$A$6:$A$67,$A40,'Cash Flow'!D$6:D$67) -> 0 | E40: =+SUMIF('Cash Flow'!$A$6:$A$67,$A40,'Cash Flow'!E$6:E$67) -> 0 | F40: =+SUMIF('Cash Flow'!$A$6:$A$67,$A40,'Cash Flow'!F$6:F$67) -> 0 | G40: =+SUMIF('Cash Flow'!$A$6:$A$67,$A40,'Cash Flow'!G$6:G$67) -> 0 | H40: =+SUMIF('Cash Flow'!$A$6:$A$67,$A40,'Cash Flow'!H$6:H$67) -> 0 | I40: =+SUMIF('Cash Flow'!$A$6:$A$67,$A40,'Cash Flow'!I$6:I$67) -> -4000 | J40: =+SUMIF('Cash Flow'!$A$6:$A$67,$A40,'Cash Flow'!J$6:J$67) -> -1000 | K40: =+SUMIF('Cash Flow'!$A$6:$A$67,$A40,'Cash Flow'!K$6:K$67) -> -2000 | ... P40: =+SUMIF('Cash Flow'!$A$6:$A$67,$A40,'Cash Flow'!P$6:P$67) -> -4000 | Q40: =SUM(D40:O40) -> -11000
A41: =+'Cash Flow'!A62 -> Taxes (TBD) | D41: =+SUMIF('Cash Flow'!$A$6:$A$67,$A41,'Cash Flow'!D$6:D$67) -> 0 | E41: =+SUMIF('Cash Flow'!$A$6:$A$67,$A41,'Cash Flow'!E$6:E$67) -> 0 | F41: =+SUMIF('Cash Flow'!$A$6:$A$67,$A41,'Cash Flow'!F$6:F$67) -> 0 | G41: =+SUMIF('Cash Flow'!$A$6:$A$67,$A41,'Cash Flow'!G$6:G$67) -> 0 | H41: =+SUMIF('Cash Flow'!$A$6:$A$67,$A41,'Cash Flow'!H$6:H$67) -> -30000 | I41: =+SUMIF('Cash Flow'!$A$6:$A$67,$A41,'Cash Flow'!I$6:I$67) -> 0 | J41: =+SUMIF('Cash Flow'!$A$6:$A$67,$A41,'Cash Flow'!J$6:J$67) -> 0 | K41: =+SUMIF('Cash Flow'!$A$6:$A$67,$A41,'Cash Flow'!K$6:K$67) -> 0 | ... P41: =+SUMIF('Cash Flow'!$A$6:$A$67,$A41,'Cash Flow'!P$6:P$67) -> 0 | Q41: =SUM(D41:O41) -> -30000 | R41: Max | S41: Min | T41: Median | U41: Average
A42: =+'Cash Flow'!A63 -> Cash Expenses | D42: =+SUMIF('Cash Flow'!$A$6:$A$67,$A42,'Cash Flow'!D$6:D$67) -> -42181.44 | E42: =+SUMIF('Cash Flow'!$A$6:$A$67,$A42,'Cash Flow'!E$6:E$67) -> -38439.42 | F42: =+SUMIF('Cash Flow'!$A$6:$A$67,$A42,'Cash Flow'!F$6:F$67) -> -20939.42 | G42: =+SUMIF('Cash Flow'!$A$6:$A$67,$A42,'Cash Flow'!G$6:G$67) -> -20939.42 | H42: =+SUMIF('Cash Flow'!$A$6:$A$67,$A42,'Cash Flow'!H$6:H$67) -> -65939.42 | I42: =+SUMIF('Cash Flow'!$A$6:$A$67,$A42,'Cash Flow'!I$6:I$67) -> -24939.42 | J42: =+SUMIF('Cash Flow'!$A$6:$A$67,$A42,'Cash Flow'!J$6:J$67) -> -21939.42 | K42: =+SUMIF('Cash Flow'!$A$6:$A$67,$A42,'Cash Flow'!K$6:K$67) -> -40439.42 | ... P42: =+SUMIF('Cash Flow'!$A$6:$A$67,$A42,'Cash Flow'!P$6:P$67) -> -48392.38 | Q42: =SUM(E42:P42) -> -384726 | R42: =MAX(E42:P42) -> -20939.42 | S42: =MIN(E42:P42) -> -65939.42 | T42: =MEDIAN(E42:P42) -> -24939.42 | U42: =AVERAGE(E42:P42) -> -32060.5
A43: =+'Cash Flow'!A67 -> Net Cash Flow | D43: =+SUMIF('Cash Flow'!$A$6:$A$67,$A43,'Cash Flow'!D$6:D$67) -> 193661.05 | E43: =+SUMIF('Cash Flow'!$A$6:$A$67,$A43,'Cash Flow'!E$6:E$67) -> -19347.3 | F43: =+SUMIF('Cash Flow'!$A$6:$A$67,$A43,'Cash Flow'!F$6:F$67) -> -1871.9829 | G43: =+SUMIF('Cash Flow'!$A$6:$A$67,$A43,'Cash Flow'!G$6:G$67) -> -1928.655 | H43: =+SUMIF('Cash Flow'!$A$6:$A$67,$A43,'Cash Flow'!H$6:H$67) -> -46990.203 | I43: =+SUMIF('Cash Flow'!$A$6:$A$67,$A43,'Cash Flow'!I$6:I$67) -> -6000.7541 | J43: =+SUMIF('Cash Flow'!$A$6:$A$67,$A43,'Cash Flow'!J$6:J$67) -> -3029.2556 | K43: =+SUMIF('Cash Flow'!$A$6:$A$67,$A43,'Cash Flow'!K$6:K$67) -> -21574.131 | ... P43: =+SUMIF('Cash Flow'!$A$6:$A$67,$A43,'Cash Flow'!P$6:P$67) -> 192754.73 | Q43: =SUM(E43:P43) -> 66338.316 | R43: =MAX(E43:P43) -> 192754.73 | S43: =MIN(E43:P43) -> -46812.479 | T43: =MEDIAN(E43:P43) -> -4358.5094 | U43: =AVERAGE(E43:P43) -> 5528.193 | V43: =Q43/Q28 -> 0.14707064
A44: =+'Cash Flow'!A68 -> Net cash flow excluding interet income | D44: =+SUMIF('Cash Flow'!$A$6:$A$68,$A44,'Cash Flow'!D$6:D$68) -> 193272.73 | E44: =+SUMIF('Cash Flow'!$A$6:$A$68,$A44,'Cash Flow'!E$6:E$68) -> -19625.89 | F44: =+SUMIF('Cash Flow'!$A$6:$A$68,$A44,'Cash Flow'!F$6:F$68) -> -2125.8904 | G44: =+SUMIF('Cash Flow'!$A$6:$A$68,$A44,'Cash Flow'!G$6:G$68) -> -2125.8904 | H44: =+SUMIF('Cash Flow'!$A$6:$A$68,$A44,'Cash Flow'!H$6:H$68) -> -47125.89 | I44: =+SUMIF('Cash Flow'!$A$6:$A$68,$A44,'Cash Flow'!I$6:I$68) -> -6125.8904 | J44: =+SUMIF('Cash Flow'!$A$6:$A$68,$A44,'Cash Flow'!J$6:J$68) -> -3125.8904 | K44: =+SUMIF('Cash Flow'!$A$6:$A$68,$A44,'Cash Flow'!K$6:K$68) -> -21625.89 | ... P44: =+SUMIF('Cash Flow'!$A$6:$A$68,$A44,'Cash Flow'!P$6:P$68) -> 187061.79 | Q44: =SUM(E44:P44) -> 57677
F45: =+ROUND(D43,4)=ROUND(D28+D42,4) -> TRUE | G45: =+ROUND(E43,4)=ROUND(E28+E42,4) -> TRUE | H45: =+ROUND(F43,4)=ROUND(F28+F42,4) -> TRUE | I45: =+ROUND(G43,4)=ROUND(G28+G42,4) -> TRUE | J45: =+ROUND(H43,4)=ROUND(H28+H42,4) -> TRUE | K45: =+ROUND(I43,4)=ROUND(I28+I42,4) -> TRUE | L45: =+ROUND(J43,4)=ROUND(J28+J42,4) -> TRUE | M45: =+ROUND(K43,4)=ROUND(K28+K42,4) -> TRUE | ... Q45: =+ROUND(O43,4)=ROUND(O28+O42,4) -> TRUE
A47: Cumulative Net Cash Flow* | E47: =+SUM($E$43:E43) -> -19347.3 | F47: =+SUM($E$43:F43) -> -21219.283 | G47: =+SUM($E$43:G43) -> -23147.938 | H47: =+SUM($E$43:H43) -> -70138.141 | I47: =+SUM($E$43:I43) -> -76138.895 | J47: =+SUM($E$43:J43) -> -79168.151 | K47: =+SUM($E$43:K43) -> -100742.28 | L47: =+SUM($E$43:L43) -> -117838.75 | ... P47: =+SUM($E$43:P43) -> 66338.316 | Q47: =+Q43 -> 66338.316
A48: Months of expenses in cash In bank account | E48: =IF($Z$17+SUM($E42:E$42)>0,1,0) -> 1 | F48: =IF($Z$17+SUM($E42:F$42)>0,1,0) -> 1 | G48: =IF($Z$17+SUM($E42:G$42)>0,1,0) -> 1 | H48: =IF($Z$17+SUM($E42:H$42)>0,1,0) -> 1 | I48: =IF($Z$17+SUM($E42:I$42)>0,1,0) -> 1 | J48: =IF($Z$17+SUM($E42:J$42)>0,1,0) -> 1 | K48: =IF($Z$17+SUM($E42:K$42)>0,1,0) -> 1 | L48: =IF($Z$17+SUM($E42:L$42)>0,1,0) -> 1 | ... P48: =IF($Z$17+SUM($E42:P$42)>0,1,0) -> 1 | Q48: =IF(P48=1,-Z17/AVERAGE(E42:P42),SUM(E48:P48)) -> 15.815411
A49: Months of cash outflow in cash In bank account | E49: =IF($Z$12+SUM($E$43:E43)>0,1,0) -> 1 | F49: =IF($Z$12+SUM($E$43:F43)>0,1,0) -> 1 | G49: =IF($Z$12+SUM($E$43:G43)>0,1,0) -> 1 | H49: =IF($Z$12+SUM($E$43:H43)>0,1,0) -> 1 | I49: =IF($Z$12+SUM($E$43:I43)>0,1,0) -> 1 | J49: =IF($Z$12+SUM($E$43:J43)>0,1,0) -> 1 | K49: =IF($Z$12+SUM($E$43:K43)>0,1,0) -> 1 | L49: =IF($Z$12+SUM($E$43:L43)>0,1,0) -> 1 | ... P49: =IF($Z$12+SUM($E$43:P43)>0,1,0) -> 1 | Q49: =IF(Z12+Q43>0,"More cash than necessary",SUM(E49:P49)) -> More cash than necessary
X65: `
A73: Asset Allocation | AH73: TEXT FOR BOX (NEED TO MANUALLY LINK TO BOX)
E74: Cash Flow | K74: Cash Flow | L74: If Income | V74: Excess / (Deficit) | Y74: Move From | AC74: Move to | AH74: Move From | AL74: Move to
A75: GURU Suggestion | E75: Need | H75: Customer Selected Parameters | K75: Need | L75: Goes to Zero | M75: Current | N75: Rate | O75: Cash Management Action to Take | U75: formulas for L | V75: =M79-K79 -> 384998.93 | W75: =IF(V75<0,"total deficit","total excess") -> total excess | Y75: Checking | Z75: Money Market | AA75: Treasuries | AB75: Stock | AC75: Checking | AD75: Money Market | AE75: Treasuries | AF75: Stock | AH75: Checking | AI75: Money Market | AJ75: Treasuries | AK75: Stock | AL75: Checking | AM75: Money Market | AN75: Treasuries | AO75: Stock
A76: 2 | B76: Months in checking | E76: =MAX(-(+$E$43+$F$43),0) -> 21219.283 | H76: 1 | I76: Months in checking | K76: =MAX(-SUM($E$43),0) -> 19347.3 | L76: 1400 | M76: =+'Balance Sheet'!B9 -> 132050 | N76: =+Y80 -> 0.0005 | O76: =AI76 -> 0 | U76: =+V76 -> 130650 | V76: =M76-L76 -> 130650 | X76: Checking | Z76: =IF(V76<0,IF(V77<0,0,MIN(V77,-V76)),0) -> 0 | AA76: =IF(V76<0,IF(V78<0,0,MIN(V78,-V76-Z76)),0) -> 0 | AB76: =IF(V76<0,MAX(-V76-SUM(Z76:AA76),0),0) -> 0 | AD76: =IF(V76>0,IF(V77>0,0,MIN(-V77,V76)),0) -> 0 | AE76: =IF(V76>0,IF(V78>0,0,MIN(-V78,V76-AD76)),0) -> 0 | AF76: =IF(V76>0,MAX(V76-SUM(AD76:AE76),0),0) -> 130650 | AH76: =IF(Y76>0,"Move "&TEXT(Y76,"$00,000")&" From "&Y$75&" To "&$X76,0) -> 0 | AI76: =IF(Z76>0,"Move "&TEXT(Z76,"$##,#00")&" From "&Z$75&" To "&$X76,0) -> 0 | AJ76: =IF(AA76>0,"Move "&TEXT(AA76,"$00,000")&" From "&AA$75&" To "&$X76,0) -> 0 | AK76: =IF(AB76>0,"Move "&TEXT(AB76,"$00,000")&" From "&AB$75&" To "&$X76,0) -> 0 | AL76: =IF(AC76>0,"Move "&TEXT(AC76,"$00,000")&" From "&$X76&" To "&AC$75,0) -> 0 | AM76: =IF(AD76>0,"Move "&TEXT(AD76,"$00,000")&" From "&$X76&" To "&AD$75,0) -> 0 | AN76: =IF(AE76>0,"Move "&TEXT(AE76,"$00,000")&" From "&$X76&" To "&AE$75,0) -> 0 | AO76: =IF(AF76>0,"Move "&TEXT(AF76,"$00,000")&" From "&$X76&" To "&AF$75,0) -> Move $130,650 From Checking To Stock
A77: 2 | B77: Months in Money Market | E77: =MAX(-SUM($G$43:$H$43),0) -> 48918.858 | H77: 11 | I77: Months in Money Market | K77: =MAX(-SUM($F$43:$J$43),0) -> 59820.851 | L77: 60000 | M77: =+'Balance Sheet'!B13 -> 240000 | N77: =+Z80 -> 0.0365 | O77: =AO77 -> Move $180,000 From Money Market To Stock | U77: =MAX(-SUM($F$42:$P$42),0) -> 346286.58 | V77: =M77-L77 -> 180000 | X77: Money Market | Y77: =IF(V77<0,IF(V76<0,0,MIN(V76-Y76,-V77)),0) -> 0 | AA77: =IF(V77<0,IF(V78<0,0,MIN(V78-AA76,-V77-Y77)),0) -> 0 | AB77: =IF(V77<0,MAX(-V77-SUM(Y77:AA77),0),0) -> 0 | AC77: =IF(V77>0,IF(V76>0,0,MIN(-V76-AC76,V77)),0) -> 0 | AE77: =IF(V77>0,IF(V78>0,0,MIN(-V78-AE76,V77-AC77)),0) -> 0 | AF77: =IF(V77>0,MAX(V77-SUM(AC77:AE77),0),0) -> 180000 | AH77: =IF(Y77>0,"Move "&TEXT(Y77,"$00,000")&" From "&Y$75&" To "&$X77,0) -> 0 | AI77: =IF(Z77>0,"Move "&TEXT(Z77,"$00,000")&" From "&Z$75&" To "&$X77,0) -> 0 | AJ77: =IF(AA77>0,"Move "&TEXT(AA77,"$00,000")&" From "&AA$75&" To "&$X77,0) -> 0 | AK77: =IF(AB77>0,"Move "&TEXT(AB77,"$00,000")&" From "&AB$75&" To "&$X77,0) -> 0 | AL77: =IF(AC77>0,"Move "&TEXT(AC77,"$00,000")&" From "&$X77&" To "&AC$75,0) -> 0 | AM77: =IF(AD77>0,"Move "&TEXT(AD77,"$00,000")&" From "&$X77&" To "&AD$75,0) -> 0 | AN77: =IF(AE77>0,"Move "&TEXT(AE77,"$00,000")&" From "&$X77&" To "&AE$75,0) -> 0 | AO77: =IF(AF77>0,"Move "&TEXT(AF77,"$00,000")&" From "&$X77&" To "&AF$75,0) -> Move $180,000 From Money Market To Stock
A78: 2 | B78: Months in Treasuries | E78: =MAX(-(I43+$J$43),0) -> 9030.0096 | H78: 0 | I78: Months in Treasuries | K78: =MAX(-SUM(K43:N43),0) -> 42882.919 | L78: 60000 | M78: =+'Balance Sheet'!B15 -> 135000 | N78: =+AA80 -> 0.0475 | U78: 0 | V78: =M78-L78 -> 75000 | X78: Treasuries | Y78: =IF(V78<0,IF(V76<0,0,MIN(V76-SUM(Y76:Y77),-V78)),0) -> 0 | Z78: =IF(V78<0,IF(V77<0,0,MIN(V77-SUM(Z76:Z77),-V78-Y78)),0) -> 0 | AB78: =IF(V78<0,MAX(-V78-SUM(Y78:AA78),0),0) -> 0 | AC78: =IF(V78>0,IF(V76>0,0,MIN(-V76-SUM(AC76:AC77),V78)),0) -> 0 | AD78: =IF(V78>0,IF(V77>0,0,MIN(-V77-SUM(AD76:AD77),V78-AC78)),0) -> 0 | AF78: =IF(V78>0,MAX(V78-SUM(AC78:AE78),0),0) -> 75000 | AH78: =IF(Y78>0,"Move "&TEXT(Y78,"$00,000")&" From "&Y$75&" To "&$X78,0) -> 0 | AI78: =IF(Z78>0,"Move "&TEXT(Z78,"$00,000")&" From "&Z$75&" To "&$X78,0) -> 0 | AJ78: =IF(AA78>0,"Move "&TEXT(AA78,"$00,000")&" From "&AA$75&" To "&$X78,0) -> 0 | AK78: =IF(AB78>0,"Move "&TEXT(AB78,"$00,000")&" From "&AB$75&" To "&$X78,0) -> 0 | AL78: =IF(AC78>0,"Move "&TEXT(AC78,"$00,000")&" From "&$X78&" To "&AC$75,0) -> 0 | AM78: =IF(AD78>0,"Move "&TEXT(AD78,"$00,000")&" From "&$X78&" To "&AD$75,0) -> 0 | AN78: =IF(AE78>0,"Move "&TEXT(AE78,"$00,000")&" From "&$X78&" To "&AE$75,0) -> 0 | AO78: =IF(AF78>0,"Move "&TEXT(AF78,"$00,000")&" From "&$X78&" To "&AF$75,0) -> Move $75,000 From Treasuries To Stock
A79: =+A77+A76+A78 -> 6 | B79: Months Total | E79: =SUM(E76:E78) -> 79168.151 | H79: =+H77+H76+H78 -> 12 | I79: Months Total | K79: =SUM(K76:K78) -> 122051.07 | L79: =SUM(L76:L78) -> 121400 | M79: =SUM(M76:M78) -> 507050 | N79: =+AB80 -> 0.1 | Y79: =IF(SUM(Y76:Y78)>MAX(V76,0),"error","ok") -> ok | Z79: =IF(SUM(Z76:Z78)>MAX(V77,0),"error","ok") -> ok | AA79: =IF(SUM(AA76:AA78)>MAX(V78,0),"error","ok") -> ok
M80: =+M79-L79 -> 385650 | Y80: ='Balance Sheet'!E7 -> 0.0005 | Z80: =+'Balance Sheet'!E10 -> 0.0365 | AA80: 0.0475 | AB80: 0.1
O81: By Optimizing Your Cash We Calculate an Increase of | Y81: Current | AC81: After Optimization
O82: =TEXT(AC82-Y82,"$##,000")&"!!" -> $28,367!! | X82: Yield on Liquid cash | Y82: =(M76*Y80+M77*Z80+M78*AA80) -> 15238.525 | AC82: =L76*Y80+L77*Z80+L78*AA80+SUM(AF76:AF78)*AB80 -> 43605.7
O83: in Annual Income
A86: [PIE CHART OF SHORT, MEDIUM, LONG TERM CASH NEEDS BASED ON MODEL]
A87: [SUGGESTED ALLOCATION OF ASSETS VS. CURRENT]
A90: Asset Allocation
U93: Cash | W93: =+Z12 -> 372050
U94: Treasuries | W94: =+'Balance Sheet'!B15 -> 135000 | X94: Immediate | Z94: =+OPTIMIZER!E24 -> 132050
U95: Liquid Brokerage Investments | W95: =+'Balance Sheet'!B16+'Balance Sheet'!B17+'Balance Sheet'!B18 -> 1509500 | X95: Short-Term | Z95: =+OPTIMIZER!E25 -> 240000
U96: Retirement Accounts | W96: =+Z6 -> 1000000 | X96: Medium-Term | Z96: =+OPTIMIZER!E26 -> 135000
U97: Alternative Assets | W97: =+Z9 -> 250000 | X97: Long-Term Liquid | Z97: =+AC112 -> 1509500
U98: Real Estate | W98: =+Z10 -> 1815000 | X98: Long-Term Retirement | Z98: =+AB131 -> 1000000
U99: Private Equity Carry | W99: =+Z7 -> 835000 | X99: Long-Term Other (RE, Alts, Stock Comp) | Z99: =+'Balance Sheet'!B33+'Balance Sheet'!B29+'Balance Sheet'!B22 -> 2980000
U100: Stock Compensation | W100: =+Z8 -> 80000 | X100: Total | Z100: =SUM(Z94:Z99) -> 5996550 | AA100: =+Z100='Balance Sheet'!B37 -> TRUE
A101: Stock Allocation | U101: Total | W101: =SUM(W93:W100) -> 5996550 | AB101: Taxable Brokerage
A102: [TOP 5 BEST AND WORST PERFORMERS ]
A103: [TOTAL FEES / COMMISSIONS PAID] | AB103: =+'Investment Breakdown'!A35 -> Cash | AC103: =SUMIF('Investment Breakdown'!$A$35:$A$44,Charts!AB103,'Investment Breakdown'!$B$35:$B$43) -> 186585.93
AB104: =+'Investment Breakdown'!A36 -> International | AC104: =SUMIF('Investment Breakdown'!$A$35:$A$44,Charts!AB104,'Investment Breakdown'!$B$35:$B$43) -> 116538.3
AB105: =+'Investment Breakdown'!A37 -> US Total Market | AC105: =SUMIF('Investment Breakdown'!$A$35:$A$44,Charts!AB105,'Investment Breakdown'!$B$35:$B$43) -> 379877.58
AB106: =+'Investment Breakdown'!A38 -> US Large Cap | AC106: =SUMIF('Investment Breakdown'!$A$35:$A$44,Charts!AB106,'Investment Breakdown'!$B$35:$B$43) -> 435000
A107: Brokerage Account | AB107: =+'Investment Breakdown'!A39 -> US Small Cap | AC107: =SUMIF('Investment Breakdown'!$A$35:$A$44,Charts!AB107,'Investment Breakdown'!$B$35:$B$43) -> 49317.756
AB108: =+'Investment Breakdown'!A40 -> US Dividend / Value | AC108: =SUMIF('Investment Breakdown'!$A$35:$A$44,Charts!AB108,'Investment Breakdown'!$B$35:$B$43) -> 94368.991
AB109: =+'Investment Breakdown'!A41 -> Meta | AC109: =SUMIF('Investment Breakdown'!$A$35:$A$44,Charts!AB109,'Investment Breakdown'!$B$35:$B$43) -> 238311.43
AB110: =+'Investment Breakdown'!A42 -> Other Single Stock | AC110: =SUMIF('Investment Breakdown'!$A$35:$A$44,Charts!AB110,'Investment Breakdown'!$B$35:$B$43) -> 0
AB111: =+'Investment Breakdown'!A43 -> Crypto | AC111: =SUMIF('Investment Breakdown'!$A$35:$A$44,Charts!AB111,'Investment Breakdown'!$B$35:$B$43) -> 9500
AB112: =+'Investment Breakdown'!A44 -> Total | AC112: =SUMIF('Investment Breakdown'!$A$35:$A$44,Charts!AB112,'Investment Breakdown'!$B$35:$B$43) -> 1509500
AC113: =+AC112=SUM(AC103:AC111) -> TRUE
AB114: US small /mid cap | AC114: =+AC105*$AC$158+AC107 -> 144287.15
A122: Retirement Accounts
X123: =+'Investment Breakdown'!A46 -> Retirement by Taxable | AA123: =+'Investment Breakdown'!A51 -> Retirement by Category
X124: =+'Investment Breakdown'!A47 -> Pre-Tax | Y124: =+'Investment Breakdown'!B47 -> 620000 | AA124: =+'Investment Breakdown'!A52 -> International | AB124: =SUMIF('Investment Breakdown'!$A$52:$A$58,Charts!AA124,'Investment Breakdown'!$B$52:$B$58) -> 128146.25
X125: =+'Investment Breakdown'!A48 -> After- Tax | Y125: =+'Investment Breakdown'!B48 -> 380000 | AA125: =+'Investment Breakdown'!A53 -> US Total Market | AB125: =SUMIF('Investment Breakdown'!$A$52:$A$58,Charts!AA125,'Investment Breakdown'!$B$52:$B$58) -> 400000
X126: =+'Investment Breakdown'!A49 -> Total | Y126: =+'Investment Breakdown'!B49 -> 1000000 | AA126: =+'Investment Breakdown'!A54 -> US Large Cap | AB126: =SUMIF('Investment Breakdown'!$A$52:$A$58,Charts!AA126,'Investment Breakdown'!$B$52:$B$58) -> 100000
Y127: =+Y126=AB131 -> TRUE | AA127: =+'Investment Breakdown'!A55 -> US Small Cap | AB127: =SUMIF('Investment Breakdown'!$A$52:$A$58,Charts!AA127,'Investment Breakdown'!$B$52:$B$58) -> 274264.47
AA128: =+'Investment Breakdown'!A57 -> Other Single Stock | AB128: =SUMIF('Investment Breakdown'!$A$52:$A$58,Charts!AA128,'Investment Breakdown'!$B$52:$B$58) -> 0
AA129: =+'Investment Breakdown'!A56 -> Bonds | AB129: =SUMIF('Investment Breakdown'!$A$52:$A$58,Charts!AA129,'Investment Breakdown'!$B$52:$B$58) -> 61209.776
AA130: =+'Investment Breakdown'!A58 -> Cash | AB130: =SUMIF('Investment Breakdown'!$A$52:$A$58,Charts!AA130,'Investment Breakdown'!$B$52:$B$58) -> 36379.5
AA131: =+'Investment Breakdown'!A59 -> Total | AB131: =SUMIF('Investment Breakdown'!$A$52:$A$59,Charts!AA131,'Investment Breakdown'!$B$52:$B$59) -> 1000000 | AF131: =AF138/AF151 -> 0.2 | AG131: =AG138/AG151 -> 0.2
AB132: =AB131=SUM(AB124:AB130) -> TRUE
AA134: US small /mid cap | AB134: =+AB125*$AC$158+AB127 -> 374264.47
AF135: GURU | AJ135: Customer selected | AN135: Current | AQ135: GURU - current
AA136: Brokeragte + Retirement | AD136: Model Portfolio | AF136: Retirement | AG136: Taxable Brokerage | AH136: Total | AJ136: Retirement | AK136: Taxable Brokerage | AL136: Total | AN136: Retirement | AO136: Taxable Brokerage | AQ136: Retirement | AR136: Taxable Brokerage
A137: Brokerage + Retirement | AA137: Cash | AB137: =SUMIF('Investment Breakdown'!$A$35:$A$58,Charts!AA137,'Investment Breakdown'!$B$35:$B$43) -> 222965.43 | AC137: =AB137/$AB$148 -> 0.088848549 | AD137: Cash | AF137: =SUMIF('Model Portfolios'!$R$10:$R$25,Charts!AD137,'Model Portfolios'!$Z$10:$Z$25) -> 0 | AG137: =SUMIF('Model Portfolios'!$R$10:$R$25,Charts!AD137,'Model Portfolios'!$Y$10:$Y$25) -> 0 | AH137: =+AG137+AF137 -> 0 | AJ137: =SUMIF('Model Portfolios'!$R$10:$R$25,Charts!AD137,'Model Portfolios'!$AB$10:$AB$25) -> 0 | AK137: =SUMIF('Model Portfolios'!$R$10:$R$25,Charts!AD137,'Model Portfolios'!$AA$10:$AA$25) -> 0 | AL137: =+AJ137+AK137 -> 0 | AN137: =SUMIF($AA$124:$AA$130,AD137,$AB$124:$AB$130) -> 36379.5 | AO137: =SUMIF($AB$103:$AB$111,AD137,$AC$103:$AC$111) -> 186585.93 | AQ137: =+AJ137-AN137 -> -36379.5 | AR137: =+AK137-AO137 -> -186585.93
A138: Current | J138: Model Portfolio | AA138: International | AB138: =SUMIF('Investment Breakdown'!$A$35:$A$58,Charts!AA138,'Investment Breakdown'!$B$35:$B$43) -> 244684.55 | AC138: =AB138/$AB$148 -> 0.097503308 | AD138: International | AF138: =+SUM(AF154:AF155) -> 200000 | AG138: =+SUM(AG154:AG155) -> 301900 | AH138: =+AG138+AF138 -> 501900 | AJ138: =+SUM(AJ154:AJ155) -> 200000 | AK138: =+SUM(AK154:AK155) -> 116538.3 | AL138: =+AK138+AJ138 -> 316538.3 | AN138: =SUMIF($AA$124:$AA$130,AD138,$AB$124:$AB$130) -> 128146.25 | AO138: =SUMIF($AB$103:$AB$111,AD138,$AC$103:$AC$111) -> 116538.3 | AQ138: =+AJ138-AN138 -> 71853.75 | AR138: =+AK138-AO138 -> 0
AA139: US Total Market | AB139: =SUMIF('Investment Breakdown'!$A$35:$A$58,Charts!AA139,'Investment Breakdown'!$B$35:$B$43) -> 779877.58 | AC139: =AB139/$AB$148 -> 0.31077011 | AN139: =SUMIF($AA$124:$AA$130,AD139,$AB$124:$AB$130) -> 0 | AQ139: =+AJ139-AN139 -> 0 | AR139: =+AK139-AO139 -> 0
AA140: US Large Cap | AB140: =SUMIF('Investment Breakdown'!$A$35:$A$58,Charts!AA140,'Investment Breakdown'!$B$35:$B$43) -> 535000 | AC140: =AB140/$AB$148 -> 0.21318988 | AD140: US Total Market | AF140: =SUMIF('Model Portfolios'!$R$10:$R$25,Charts!AD140,'Model Portfolios'!$Z$10:$Z$25) -> 150000 | AG140: =SUMIF('Model Portfolios'!$R$10:$R$25,Charts!AD140,'Model Portfolios'!$Y$10:$Y$25) -> 75475 | AH140: =+AG140+AF140 -> 225475 | AJ140: =SUMIF('Model Portfolios'!$R$10:$R$25,Charts!AD140,'Model Portfolios'!$AB$10:$AB$25) -> 150000 | AK140: =SUMIF('Model Portfolios'!$R$10:$R$25,Charts!AD140,'Model Portfolios'!$AA$10:$AA$25) -> 150950 | AL140: =+AJ140+AK140 -> 300950 | AN140: =SUMIF($AA$124:$AA$130,AD140,$AB$124:$AB$130) -> 400000 | AO140: =SUMIF($AB$103:$AB$111,AD140,$AC$103:$AC$111) -> 379877.58 | AQ140: =+AJ140-AN140 -> -250000 | AR140: =+AK140-AO140 -> -228927.58
AA141: US Small Cap | AB141: =SUMIF('Investment Breakdown'!$A$35:$A$58,Charts!AA141,'Investment Breakdown'!$B$35:$B$43) -> 323582.23 | AC141: =AB141/$AB$148 -> 0.12894291 | AD141: US Large Cap | AF141: =SUMIF('Model Portfolios'!$R$10:$R$25,Charts!AD141,'Model Portfolios'!$Z$10:$Z$25) -> 250000 | AG141: =SUMIF('Model Portfolios'!$R$10:$R$25,Charts!AD141,'Model Portfolios'!$Y$10:$Y$25) -> 226425 | AH141: =+AG141+AF141 -> 476425 | AJ141: =SUMIF('Model Portfolios'!$R$10:$R$25,Charts!AD141,'Model Portfolios'!$AB$10:$AB$25) -> 250000 | AK141: =SUMIF('Model Portfolios'!$R$10:$R$25,Charts!AD141,'Model Portfolios'!$AA$10:$AA$25) -> 377375 | AL141: =+AJ141+AK141 -> 627375 | AN141: =SUMIF($AA$124:$AA$130,AD141,$AB$124:$AB$130) -> 100000 | AO141: =SUMIF($AB$103:$AB$111,AD141,$AC$103:$AC$111) -> 435000 | AQ141: =+AJ141-AN141 -> 150000 | AR141: =+AK141-AO141 -> -57625
AA142: US Dividend / Value | AB142: =SUMIF('Investment Breakdown'!$A$35:$A$58,Charts!AA142,'Investment Breakdown'!$B$35:$B$43) -> 94368.991 | AC142: =AB142/$AB$148 -> 0.037604699 | AD142: US Large Cap Growth | AF142: =SUMIF('Model Portfolios'!$R$10:$R$25,Charts!AD142,'Model Portfolios'!$Z$10:$Z$25) -> 150000 | AG142: =SUMIF('Model Portfolios'!$R$10:$R$25,Charts!AD142,'Model Portfolios'!$Y$10:$Y$25) -> 150950 | AH142: =+AG142+AF142 -> 300950 | AJ142: =SUMIF('Model Portfolios'!$R$10:$R$25,Charts!AD142,'Model Portfolios'!$AB$10:$AB$25) -> 150000 | AK142: =SUMIF('Model Portfolios'!$R$10:$R$25,Charts!AD142,'Model Portfolios'!$AA$10:$AA$25) -> 150950 | AL142: =+AJ142+AK142 -> 300950 | AN142: =SUMIF($AA$124:$AA$130,AD142,$AB$124:$AB$130) -> 0 | AO142: =SUMIF($AB$103:$AB$111,AD142,$AC$103:$AC$111) -> 0 | AQ142: =+AJ142-AN142 -> 150000 | AR142: =+AK142-AO142 -> 150950
AA143: Meta | AB143: =SUMIF('Investment Breakdown'!$A$35:$A$58,Charts!AA143,'Investment Breakdown'!$B$35:$B$43) -> 238311.43 | AC143: =AB143/$AB$148 -> 0.094963711 | AD143: US Small Cap | AF143: =SUMIF('Model Portfolios'!$R$10:$R$25,Charts!AD143,'Model Portfolios'!$Z$10:$Z$25) -> 100000 | AG143: =SUMIF('Model Portfolios'!$R$10:$R$25,Charts!AD143,'Model Portfolios'!$Y$10:$Y$25) -> 150950 | AH143: =+AG143+AF143 -> 250950 | AJ143: =SUMIF('Model Portfolios'!$R$10:$R$25,Charts!AD143,'Model Portfolios'!$AB$10:$AB$25) -> 100000 | AK143: =SUMIF('Model Portfolios'!$R$10:$R$25,Charts!AD143,'Model Portfolios'!$AA$10:$AA$25) -> 88500.265 | AL143: =+AJ143+AK143 -> 188500.27 | AN143: =SUMIF($AA$124:$AA$130,AD143,$AB$124:$AB$130) -> 274264.47 | AO143: =SUMIF($AB$103:$AB$111,AD143,$AC$103:$AC$111) -> 49317.756 | AQ143: =+AJ143-AN143 -> -174264.47 | AR143: =+AK143-AO143 -> 39182.509
AA144: Other Single Stock | AB144: =SUMIF('Investment Breakdown'!$A$35:$A$58,Charts!AA144,'Investment Breakdown'!$B$35:$B$43) -> 0 | AC144: =AB144/$AB$148 -> 0 | AD144: US Dividend / Value | AF144: =SUMIF('Model Portfolios'!$R$10:$R$25,Charts!AD144,'Model Portfolios'!$Z$10:$Z$25) -> 50000 | AG144: =SUMIF('Model Portfolios'!$R$10:$R$25,Charts!AD144,'Model Portfolios'!$Y$10:$Y$25) -> 75475 | AH144: =+AG144+AF144 -> 125475 | AJ144: =SUMIF('Model Portfolios'!$R$10:$R$25,Charts!AD144,'Model Portfolios'!$AB$10:$AB$25) -> 50000 | AK144: =SUMIF('Model Portfolios'!$R$10:$R$25,Charts!AD144,'Model Portfolios'!$AA$10:$AA$25) -> 75475 | AL144: =+AJ144+AK144 -> 125475 | AN144: =SUMIF($AA$124:$AA$130,AD144,$AB$124:$AB$130) -> 0 | AO144: =SUMIF($AB$103:$AB$111,AD144,$AC$103:$AC$111) -> 94368.991 | AQ144: =+AJ144-AN144 -> 50000 | AR144: =+AK144-AO144 -> -18893.991
...

Sheet DATA AND MODELS-->
G14: MODEL BACKUPS ---->

Sheet Balance Sheet
A2: BALANCE SHEET MODEL
A3: Today | B3: =TODAY() -> 46070 | C3: Need to be filled out
A5: Assets | B5: Balance
D6: Source | E6: Rate | H6: Notes | K6: Type of Account
A7: Chase Total Checking | B7: 25050 | E7: 0.0005
A8: Citizens Private Banking Checking | B8: 107000 | D8: Redacted ZIP | E8: 0 | G8: Per Sarah | H8: Checking - used only to access ATMs | K8: ADV PLUS SAVINGS
A9: Checking Bank Accounts | B9: =SUM(B7:B8) -> 132050 | E9: =SUMPRODUCT(E7:E8,B7:B8)/B9 -> 9.4850435e-05
A10: Citizens Private Bank Money Market | B10: 225000 | E10: 0.0365 | F10: 45735 | G10: Statement | H10: Main account - payroll, credit card payments | K10: PLATINUM SAVINGS | M10: Need to adjust for $7K IRA contribution
A11: CapitalOne 360 Perf Savings | B11: 15000 | E11: 0.0378 | F11: 45735 | G11: Statement | H11: no activity | K11: SAVINGS
A12: [Savings 3 Placeholder] | F12: 45735 | G12: Statement | H12: no activity | K12: ONLINE SAVINGS
A13: Savings & Money Market Accounts | B13: =SUM(B10:B12) -> 240000 | E13: =SUMPRODUCT(E10:E12,B10:B12)/B13 -> 0.03658125
A14: Cash | B14: =+B13+B9 -> 372050 | E14: =+(B9*E9+B13*E13)/B14 -> 0.0236313
A15: Treasuries | B15: 135000 | D15: None | E15: 0.0395
A16: ETFs/ Mutual Funds | B16: =+SUM('Investment Breakdown'!B6:B11) -> 1201688.6 | D16: See "Investment Breakdown"
A17: Crypto | B17: =+'Investment Breakdown'!B15 -> 9500 | D17: See "Investment Breakdown"
A18: Single Stock | B18: =SUM('Investment Breakdown'!B12:B13) -> 298311.43 | D18: See "Investment Breakdown"
A19: Fidelity Taxable Brokerage | B19: =SUM(B15:B18) -> 1644500
A20: Private Equity Fund 1 | B20: 75000
A21: Private Equity Fund 2 | B21: =250000-B20 -> 175000
A22: Alternative Assets | B22: =SUM(B20:B21) -> 250000
A23: Investments | B23: =B19+B22 -> 1894500
A24: Carry Private Equity Fund 1 | B24: 325000
A25: Carry Private Equity Fund 2 | B25: 510000
A26: Carry | B26: =SUM(B24:B25) -> 835000
A27: Goldman RSUs | B27: 80000 | F27: shares | H27: Trade Date
A28: Stock Compensation | B28: =+B27 -> 80000
A29: Carry and RSUs | B29: =+B26+B28 -> 915000 | E29: Fair Market Value Estimate | H29: Rent
E30: Purch Price | F30: Value Chg | G30: Amount gain/loss | H30: Do you rent? | I30: Actual Annual Rent | J30: Monthly Rent Estimate | M30: Maintenance | N30: Property Taxes | O30: Implied Cap Rate
A31: Tribeca (Primary) | B31: 1525000 | E31: 1350000 | F31: =+B31/E31-1 -> 0.12962963 | G31: =B31-E31 -> 175000 | H31: No | I31: 0 | J31: 0 | O31: =J31*12/B31 -> 0
A32: Sarasota (Investment) | B32: 290000 | E32: 210000 | F32: =+B32/E32-1 -> 0.38095238 | G32: =B32-E32 -> 80000 | H32: Yes | I32: =2100*12 -> 25200 | J32: =+I32/12 -> 2100 | O32: =J32*12/B32 -> 0.086896552
A33: Real Estate | B33: =SUM(B31:B32) -> 1815000 | E33: =SUM(E31:E32) -> 1560000 | F33: =E33/B33-1 -> -0.14049587 | G33: =SUM(G31:G32) -> 255000 | J33: =SUM(J31:J32) -> 2100 | O33: =J33*12/E33 -> 0.016153846
A34: Fidelity 401(k) / IRA | B34: =+'Investment Breakdown'!B22 -> 620000 | D34: See "Investment Breakdown"
A35: Fidelity Roth IRA | B35: =+'Investment Breakdown'!B30 -> 380000 | D35: See "Investment Breakdown"
A36: Retirement | B36: =SUM(B34:B35) -> 1000000
A37: Total Assets | B37: =B14+B23+B33+B29+B36 -> 5996550
A39: Liabilities | B39: Last statement Balance | E39: Rate | F39: Current Balance
A40: Chase Sapphire Preferred | B40: 3671.14 | E40: 0 | F40: =3783-2500-190 -> 1093
A41: Amex Gold | B41: 5794.89 | E41: 0 | F41: =2163-1537 -> 626
A42: Amazon Card | B42: 2000 | E42: 0 | F42: 133
A43: Credit Cards / Lines of Credit | B43: =SUM(B40:B42) -> 11466.03 | E43: =SUMPRODUCT(E40:E42,B40:B42)/B43 -> 0 | F43: =SUM(F40:F42) -> 1852
I44: Rate | J44: Term | K44: Principal Payment Monthly | L44: Interest
A45: Undergrad | B45: =32000-K45*12*13 -> 11200 | E45: 0.034 | J45: 2032 | K45: 133.33333 | L45: =+B45*E45/12 -> 31.733333
A46: Graduate | B46: =90000-K46*12*7 -> 58500 | E46: 0.045 | J46: 2038 | K46: 375 | L46: =+B46*E46/12 -> 219.375
A47: Student Loans | B47: =+SUM(B45:B46) -> 69700 | E47: =SUMPRODUCT(E45:E46,B45:B46)/B47 -> 0.043232425 | I47: =+SUMPRODUCT(E45:E46,B45:B46)/B47 -> 0.043232425
A48: =A31 -> Tribeca (Primary) | B48: =+E31*70% -> 945000 | C48: 45712 | D48: Statement | E48: 0.0315 | F48: 45712 | G48: Statement | H48: 54179 | I48: =B48/B31 -> 0.61967213
A49: =A32 -> Sarasota (Investment) | B49: =+E32*70% -> 147000 | C49: 45712 | D49: Statement | E49: 0.0255 | F49: 45712 | G49: Statement | H49: 55185 | I49: =B49/B32 -> 0.50689655
A50: Mortgages | B50: =SUM(B48:B49) -> 1092000 | E50: =SUMPRODUCT(B48:B49,E48:E49)/B50 -> 0.030692308
A51: Professional Loans (Private Equity) | B51: =+SUM(B20:B21)*50% -> 125000 | E51: 0.065
A52: =+A20 -> Private Equity Fund 1 | B52: 0 | E52: 0
A53: =+A21 -> Private Equity Fund 2 | B53: 50000 | E53: 0
A54: Remaining Capital Commitment | B54: =SUM(B52:B53) -> 50000 | E54: =SUMPRODUCT(E52:E53,B52:B53)/B54 -> 0
A55: Total Liabilities | B55: =B50+B43+B51+B47+B54 -> 1348166 | E55: =+(B43*E43+B47*E47+B50*E50+B54*E54)/B55 -> 0.02709555
A56: Net Worth | B56: =B37-B55 -> 4648384

Sheet Cash Flow
A2: CASH FLOW MODEL
D3: December | E3: Next Twelve Months
B4: Subcategory | D4: 2024 | E4: 2025 | S4: 1 | T4: =+S4+T5-S5 -> 2 | U4: =+T4+U5-T5 -> 3 | V4: =+U4+V5-U5 -> 4 | W4: =+V4+W5-V5 -> 5 | X4: =+W4+X5-W5 -> 6 | Y4: =+X4+Y5-X5 -> 7 | Z4: =+Y4+Z5-Y5 -> 8 | AA4: =+Z4+AA5-Z5 -> 9 | ... AV4: =+AU4+AV5-AU5 -> 30
B5: 1 | C5: 2 | D5: December | E5: January | F5: February | G5: March | H5: April | I5: May | J5: June | K5: July | L5: August | M5: September | N5: October | O5: November | P5: December | Q5: Next Twelve Months | S5: 2026 | T5: =+S5+1 -> 2027 | U5: =+T5+1 -> 2028 | V5: =+U5+1 -> 2029 | W5: =+V5+1 -> 2030 | X5: =+W5+1 -> 2031 | Y5: =+X5+1 -> 2032 | Z5: =+Y5+1 -> 2033 | AA5: =+Z5+1 -> 2034 | ... AV5: =+AU5+1 -> 2055 | AX5: Annual Income | BB5: Deductions
A6: Partner1 Income | D6: =+AX6/12*(1-$BB$14) -> 13302.496 | E6: =+D6 -> 13302.496 | F6: =+E6 -> 13302.496 | G6: =+F6 -> 13302.496 | H6: =+G6 -> 13302.496 | I6: =+H6 -> 13302.496 | J6: =+I6 -> 13302.496 | K6: =+J6 -> 13302.496 | L6: =+K6 -> 13302.496 | ... P6: =+O6 -> 13302.496 | Q6: =SUM(E6:P6) -> 159629.95 | AX6: 350000 | AY6: Director/Junior MD Private Equity - Salary | BB6: 0.04 | BC6: City Tax
A7: Partner1 Bonus | D7: =+AX7*(1-$BB$14) -> 191555.94 | P7: =+D7 -> 191555.94 | Q7: =SUM(E7:P7) -> 191555.94 | S7: =+Q7*(1+$S$11) -> 201133.74 | T7: =+S7*(1+$T$11) -> 211190.42 | U7: =+T7*(1+$T$11) -> 221749.94 | V7: =+U7*(1+$T$11) -> 232837.44 | W7: =+V7*(1+$T$11) -> 244479.31 | X7: =+W7*(1+$T$11) -> 256703.28 | Y7: =+X7*(1+$T$11) -> 269538.44 | Z7: =+Y7*(1+$T$11) -> 283015.36 | AA7: =+Z7*(1+$T$11) -> 297166.13 | ... AL7: =+AK7*(1+$T$11) -> 508254.93 | AX7: =+AX6*1.2 -> 420000 | AY7: Director/Junior MD Private Equity - Bonus | BB7: 0.08 | BC7: State Tax
A8: Partner2 Income | D8: =+AX8/12*(1-$BB$14) -> 5511.0339 | E8: =+D8 -> 5511.0339 | F8: =+E8 -> 5511.0339 | G8: =+F8 -> 5511.0339 | H8: =+G8 -> 5511.0339 | I8: =+H8 -> 5511.0339 | J8: =+I8 -> 5511.0339 | K8: =+J8 -> 5511.0339 | L8: =+K8 -> 5511.0339 | ... P8: =+O8 -> 5511.0339 | Q8: =SUM(E8:P8) -> 66132.407 | AX8: 145000 | AY8: Marketing Prof - Salary | BB8: 0.35 | BC8: Federal Tax | BF8: 0.0435 | BG8: =+BF8*(1-BB9) -> 0.023055
A9: Partner2 Bonus | D9: =+AX9*(1-$BB$14) -> 25084.706 | P9: =+D9 -> 25084.706 | Q9: =SUM(E9:P9) -> 25084.706 | S9: =+Q9*(1+$S$11) -> 26338.941 | T9: =+S9*(1+$T$11) -> 27655.889 | U9: =+T9*(1+$T$11) -> 29038.683 | V9: =+U9*(1+$T$11) -> 30490.617 | W9: =+V9*(1+$T$11) -> 32015.148 | X9: =+W9*(1+$T$11) -> 33615.905 | Y9: =+X9*(1+$T$11) -> 35296.701 | Z9: =+Y9*(1+$T$11) -> 37061.536 | AA9: =+Z9*(1+$T$11) -> 38914.612 | ... AL9: =+AK9*(1+$T$11) -> 66557.193 | AX9: 55000 | AY9: Marketing Prof - Bonus | BB9: =SUM(BB6:BB8) -> 0.47 | BC9: Consolidated Tax | BF9: 0.0411 | BG9: =BF9*(1-BB8) -> 0.026715
A10: Compensation | D10: =+SUM(D6:D9) -> 235454.17 | E10: =+SUM(E6:E9) -> 18813.53 | F10: =+SUM(F6:F9) -> 18813.53 | G10: =+SUM(G6:G9) -> 18813.53 | H10: =+SUM(H6:H9) -> 18813.53 | I10: =+SUM(I6:I9) -> 18813.53 | J10: =+SUM(J6:J9) -> 18813.53 | K10: =+SUM(K6:K9) -> 18813.53 | ... P10: =+SUM(P6:P9) -> 235454.17 | Q10: =SUM(E10:P10) -> 442403 | S10: =+Q10*(1+S11) -> 464523.15 | T10: =+S10*(1+T11) -> 487749.31 | U10: =+T10*(1+U11) -> 512136.77 | V10: =+U10*(1+V11) -> 537743.61 | W10: =+V10*(1+W11) -> 564630.79 | X10: =+W10*(1+X11) -> 592862.33 | Y10: =+X10*(1+Y11) -> 622505.45 | Z10: =+Y10*(1+Z11) -> 653630.72 | AA10: =+Z10*(1+AA11) -> 686312.26 | ... AL10: =+AK10*(1+AL11) -> 1173826.9 | AX10: =SUM(AX6:AX9) -> 970000 | AY10: Total Salary and Bonus | BB10: =9932/AX10 -> 0.010239175 | BC10: Social security ($9.9K)
A11: Immediate | D11: =+'Balance Sheet'!B9*'Balance Sheet'!E9/12*(1-BB9) -> 0.5531875 | E11: =E86 -> 0.087719995 | F11: =F86 -> 0.087720179 | G11: =G86 -> 0.1819778 | H11: =H86 -> 0.19035645 | I11: =I86 -> 0.098193463 | J11: =J86 -> 0.13065978 | K11: =K86 -> 0.15998444 | L11: =L86 -> 0.11913954 | ... P11: =P86 -> 0.18187973 | Q11: =SUM(E11:P11) -> 1.5750523 | S11: 0.05 | T11: 0.05 | U11: 0.05 | V11: 0.05 | W11: 0.05 | X11: 0.05 | Y11: 0.05 | Z11: 0.05 | AA11: 0.05 | AB11: 0.05 | AC11: 0.05 | AD11: 0.05 | AE11: 0.05 | AF11: 0.05 | AG11: 0.05 | AH11: 0.05 | AI11: 0.05 | AJ11: 0.05 | AK11: 0.05 | AL11: 0.05 | BB11: 0.0245 | BC11: Medicare
A12: Short | D12: =+'Balance Sheet'!B13*'Balance Sheet'!E13/12*(1-BB9) -> 387.76125 | E12: =+E98 -> 278.50276 | F12: =+F98 -> 253.81978 | G12: =+G98 -> 197.05337 | H12: =+H98 -> 135.49652 | I12: =+I98 -> 125.03808 | J12: =+J98 -> 96.50414 | K12: =+K98 -> 51.599503 | L12: =+L98 -> 29.299722 | ... P12: =+P98 -> 150.68842 | Q12: =SUM(E12:P12) -> 1361.1653 | S12: =+S98 -> 3434.0333 | T12: =+T98 -> 3652.1898 | U12: =+U98 -> 3884.2052 | V12: =+V98 -> 4130.9602 | W12: =+W98 -> 4393.3909 | X12: =+X98 -> 4672.4932 | Y12: =+Y98 -> 4969.3263 | Z12: =+Z98 -> 5285.0165 | ... AL12: =+AL98 -> 11067.063 | BB12: =15000/AX10 -> 0.015463918 | BC12: Health Insurane ($15K)
A13: Medium - Usually Zero unless transaction account | D13: 0 | E13: =+E106 -> 0 | F13: =+F106 -> 0 | G13: =+G106 -> 0 | H13: =+H106 -> 0 | I13: =+I106 -> 0 | J13: =+J106 -> 0 | K13: =+K106 -> 0 | L13: =+L106 -> 0 | ... P13: =+P106 -> 5395.701 | Q13: =SUM(E13:P13) -> 5395.701 | S13: =+S106 -> 5951.0267 | T13: =+T106 -> 7096.8396 | U13: =+U106 -> 8314.708 | V13: =+V106 -> 9608.1693 | W13: =+W106 -> 10980.908 | X13: =+X106 -> 12436.76 | Y13: =+Y106 -> 13777.315 | Z13: =+Z106 -> 14552.927 | ... AL13: =+AL106 -> 19720.644 | BB13: =23000/AX10 -> 0.02371134 | BC13: 401K ($23K max)
A14: [Placeholder] | D14: =+E14 -> 0 | Q14: =SUM(E14:P14) -> 0 | BB14: =SUM(BB9:BB13) -> 0.54391443 | BC14: Total Deductions
A15: Interest From Bank Accounts | D15: =SUM(D11:D14) -> 388.31444 | E15: =SUM(E11:E14) -> 278.59048 | F15: =SUM(F11:F14) -> 253.9075 | G15: =SUM(G11:G14) -> 197.23535 | H15: =SUM(H11:H14) -> 135.68688 | I15: =SUM(I11:I14) -> 125.13627 | J15: =SUM(J11:J14) -> 96.6348 | K15: =SUM(K11:K14) -> 51.759487 | ... P15: =SUM(P11:P14) -> 5692.9393 | Q15: =SUM(E15:P15) -> 8661.3155 | S15: =SUM(S11:S14) -> 9385.11 | T15: =SUM(T11:T14) -> 10749.079 | U15: =SUM(U11:U14) -> 12198.963 | V15: =SUM(V11:V14) -> 13739.179 | W15: =SUM(W11:W14) -> 15374.349 | X15: =SUM(X11:X14) -> 17109.303 | Y15: =SUM(Y11:Y14) -> 18746.691 | Z15: =SUM(Z11:Z14) -> 19837.994 | ... AL15: =SUM(AL11:AL14) -> 30787.757 | BB15: 0.2 | BC15: Capital Gains
A16: Cash Income | D16: =+D10+D15 -> 235842.49 | E16: =+E10+E15 -> 19092.12 | F16: =+F10+F15 -> 19067.437 | G16: =+G10+G15 -> 19010.765 | H16: =+H10+H15 -> 18949.217 | I16: =+I10+I15 -> 18938.666 | J16: =+J10+J15 -> 18910.164 | K16: =+K10+K15 -> 18865.289 | ... P16: =+P10+P15 -> 241147.11 | Q16: =SUM(E16:P16) -> 451064.32 | R16: Income | S16: =+S10+S15 -> 473908.26 | T16: =+T10+T15 -> 498498.39 | U16: =+U10+U15 -> 524335.74 | V16: =+V10+V15 -> 551482.79 | W16: =+W10+W15 -> 580005.14 | X16: =+X10+X15 -> 609971.63 | Y16: =+Y10+Y15 -> 641252.14 | Z16: =+Z10+Z15 -> 673468.71 | ... AL16: =+AL10+AL15 -> 1204614.6
A17: Rent on Primary Residence | D17: 0 | E17: 0 | F17: =+E17 -> 0 | G17: =+F17 -> 0 | H17: =+G17 -> 0 | I17: =+H17 -> 0 | J17: =+I17 -> 0 | K17: =+J17 -> 0 | L17: =+K17 -> 0 | M17: =+L17 -> 0 | ... P17: =+O17 -> 0 | Q17: =SUM(E17:P17) -> 0 | R17: Growth | S17: =+S16/Q16-1 -> 0.050644539 | T17: =+T16/S16-1 -> 0.051887947 | U17: =+U16/T16-1 -> 0.051830357 | V17: =+V16/U16-1 -> 0.051774184 | W17: =+W16/V16-1 -> 0.051719383 | X17: =+X16/W16-1 -> 0.051665911 | Y17: =+Y16/X16-1 -> 0.051281901 | Z17: =+Z16/Y16-1 -> 0.050240105 | AA17: =+AA16/Z16-1 -> 0.049579895 | ... AL17: =+AL16/AK16-1 -> 0.049714616
A18: Property Taxes | B18: Real Estate | C18: Taxes | D18: 0 | E18: =-35000/2 -> -17500 | K18: =-35000/2 -> -17500 | Q18: =SUM(E18:P18) -> -35000
A19: Maintenance / HOA Fees | B19: Real Estate | D19: =-2458.43/3 -> -819.47667 | E19: =+D19 -> -819.47667 | F19: =+E19 -> -819.47667 | G19: =+F19 -> -819.47667 | H19: =+G19 -> -819.47667 | I19: =+H19 -> -819.47667 | J19: =+I19 -> -819.47667 | K19: =+J19 -> -819.47667 | L19: =+K19 -> -819.47667 | ... P19: =+O19 -> -819.47667 | Q19: =SUM(E19:P19) -> -9833.72
A20: Rent | D20: 0 | E20: =+D20 -> 0 | F20: =+E20 -> 0 | G20: =+F20 -> 0 | H20: =+G20 -> 0 | I20: =+H20 -> 0 | J20: =+I20 -> 0 | K20: =+J20 -> 0 | L20: =+K20 -> 0 | ... P20: =+O20 -> 0 | Q20: =SUM(E20:P20) -> 0
A21: Property Management | B21: Real Estate | D21: 0 | E21: =+D21 -> 0 | F21: =+E21 -> 0 | G21: =+F21 -> 0 | H21: =+G21 -> 0 | I21: =+H21 -> 0 | J21: =+I21 -> 0 | K21: =+J21 -> 0 | L21: =+K21 -> 0 | ... P21: =+O21 -> 0 | Q21: =SUM(E21:P21) -> 0
A22: Mortgage | B22: Real Estate | C22: Debt Interest | D22: =-'Balance Sheet'!B48*'Balance Sheet'!E48/12 -> -2480.625 | E22: =+D22 -> -2480.625 | F22: =+E22 -> -2480.625 | G22: =+F22 -> -2480.625 | H22: =+G22 -> -2480.625 | I22: =+H22 -> -2480.625 | J22: =+I22 -> -2480.625 | K22: =+J22 -> -2480.625 | L22: =+K22 -> -2480.625 | ... P22: =+O22 -> -2480.625 | Q22: =SUM(E22:P22) -> -29767.5
A23: Cable | C23: Cable | D23: -106.33 | E23: =+D23 -> -106.33 | F23: =+E23 -> -106.33 | G23: =+F23 -> -106.33 | H23: =+G23 -> -106.33 | I23: =+H23 -> -106.33 | J23: =+I23 -> -106.33 | K23: =+J23 -> -106.33 | L23: =+K23 -> -106.33 | ... P23: =+O23 -> -106.33 | Q23: =SUM(E23:P23) -> -1275.96
A24: Utilities | C24: Utilities | D24: -287.45 | E24: =+D24 -> -287.45 | F24: =+E24 -> -287.45 | G24: =+F24 -> -287.45 | H24: =+G24 -> -287.45 | I24: =+H24 -> -287.45 | J24: =+I24 -> -287.45 | K24: =+J24 -> -287.45 | L24: =+K24 -> -287.45 | ... P24: =+O24 -> -287.45 | Q24: =SUM(E24:P24) -> -3449.4
A25: Insurance | D25: -830 | E25: =+D25 -> -830 | F25: =+E25 -> -830 | G25: =+F25 -> -830 | H25: =+G25 -> -830 | I25: =+H25 -> -830 | J25: =+I25 -> -830 | K25: =+J25 -> -830 | L25: =+K25 -> -830 | ... P25: =+O25 -> -830 | Q25: =SUM(E25:P25) -> -9960
A26: Manhattan Apartment | D26: =+SUM(D18:D25) -> -4523.8817 | E26: =+SUM(E18:E25) -> -22023.882 | F26: =+SUM(F18:F25) -> -4523.8817 | G26: =+SUM(G18:G25) -> -4523.8817 | H26: =+SUM(H18:H25) -> -4523.8817 | I26: =+SUM(I18:I25) -> -4523.8817 | J26: =+SUM(J18:J25) -> -4523.8817 | K26: =+SUM(K18:K25) -> -22023.882 | ... P26: =+SUM(P18:P25) -> -4523.8817 | Q26: =SUM(E26:P26) -> -89286.58 | R26: =+IF(Q20=0,"NA",Q26/('Balance Sheet'!B31-'Balance Sheet'!B48)) -> NA | AX26: Return
A27: Property Taxes | B27: Real Estate | C27: Taxes | P27: =-9393.2/2 -> -4696.6 | Q27: =SUM(E27:P27) -> -4696.6
A28: Maintenance / HOA Fees | B28: Real Estate | D28: =-486.67/2 -> -243.335 | E28: =+D28 -> -243.335 | F28: =+E28 -> -243.335 | G28: =+F28 -> -243.335 | H28: =+G28 -> -243.335 | I28: =+H28 -> -243.335 | J28: =+I28 -> -243.335 | K28: =+J28 -> -243.335 | L28: =+K28 -> -243.335 | ... P28: =+O28 -> -243.335 | Q28: =SUM(E28:P28) -> -2920.02
A29: Golf dues | D29: =-8204.6/2 -> -4102.3 | P29: =-8204.6/2 -> -4102.3 | Q29: =SUM(E29:P29) -> -4102.3
A30: Rent | D30: =+'Balance Sheet'!J32 -> 2100 | E30: =+D30 -> 2100 | F30: =+E30 -> 2100 | G30: =+F30 -> 2100 | H30: =+G30 -> 2100 | I30: =+H30 -> 2100 | J30: =+I30 -> 2100 | K30: =+J30 -> 2100 | L30: =+K30 -> 2100 | ... P30: =+O30 -> 2100 | Q30: =SUM(E30:P30) -> 25200
A31: Property Management | B31: Real Estate | D31: =-D30*18% -> -378 | E31: =+D31 -> -378 | F31: =+E31 -> -378 | G31: =+F31 -> -378 | H31: =+G31 -> -378 | I31: =+H31 -> -378 | J31: =+I31 -> -378 | K31: =+J31 -> -378 | L31: =+K31 -> -378 | ... P31: =+O31 -> -378 | Q31: =SUM(E31:P31) -> -4536
A32: Mortgage | B32: Real Estate | C32: Debt Interest | D32: =('Balance Sheet'!B49*'Balance Sheet'!E49/12)*-1 -> -312.375 | E32: =+D32 -> -312.375 | F32: =+E32 -> -312.375 | G32: =+F32 -> -312.375 | H32: =+G32 -> -312.375 | I32: =+H32 -> -312.375 | J32: =+I32 -> -312.375 | K32: =+J32 -> -312.375 | L32: =+K32 -> -312.375 | ... P32: =+O32 -> -312.375 | Q32: =SUM(E32:P32) -> -3748.5
A33: Cable | C33: Cable | Q33: =SUM(E33:P33) -> 0
A34: Utilities | C34: Utilities | Q34: =SUM(E34:P34) -> 0
A35: Insurance | D35: =-3242*66% -> -2139.72 | Q35: =SUM(E35:P35) -> 0
A36: Florida Investment Property | D36: =+SUM(D27:D35) -> -5075.73 | E36: =+SUM(E27:E35) -> 1166.29 | F36: =+SUM(F27:F35) -> 1166.29 | G36: =+SUM(G27:G35) -> 1166.29 | H36: =+SUM(H27:H35) -> 1166.29 | I36: =+SUM(I27:I35) -> 1166.29 | J36: =+SUM(J27:J35) -> 1166.29 | K36: =+SUM(K27:K35) -> 1166.29 | ... P36: =+SUM(P27:P35) -> -7632.61 | Q36: =SUM(E36:P36) -> 5196.58 | R36: =+Q36/('Balance Sheet'!B32-'Balance Sheet'!B49) -> 0.03633972 | AX36: Return
A37: Capital Calls | B37: Investments | Q37: =SUM(E37:P37) -> 0
A38: Professional Loan (Private Equity) | B38: Investments | C38: Debt Interest | D38: =-'Balance Sheet'!B51*'Balance Sheet'!E51/12 -> -677.08333 | E38: =+D38 -> -677.08333 | F38: =+E38 -> -677.08333 | G38: =+F38 -> -677.08333 | H38: =+G38 -> -677.08333 | I38: =+H38 -> -677.08333 | J38: =+I38 -> -677.08333 | K38: =+J38 -> -677.08333 | L38: =+K38 -> -677.08333 | ... P38: =+O38 -> -677.08333 | Q38: =SUM(E38:P38) -> -8125
A39: Alternative Investments | D39: =+SUM(D37:D38) -> -677.08333 | E39: =+SUM(E37:E38) -> -677.08333 | F39: =+SUM(F37:F38) -> -677.08333 | G39: =+SUM(G37:G38) -> -677.08333 | H39: =+SUM(H37:H38) -> -677.08333 | I39: =+SUM(I37:I38) -> -677.08333 | J39: =+SUM(J37:J38) -> -677.08333 | K39: =+SUM(K37:K38) -> -677.08333 | ... P39: =+SUM(P37:P38) -> -677.08333 | Q39: =SUM(E39:P39) -> -8125
A40: Undergrad | C40: Debt Interest | D40: =-'Balance Sheet'!K45-'Balance Sheet'!L45 -> -165.06667 | E40: =+D40 -> -165.06667 | F40: =+E40 -> -165.06667 | G40: =+F40 -> -165.06667 | H40: =+G40 -> -165.06667 | I40: =+H40 -> -165.06667 | J40: =+I40 -> -165.06667 | K40: =+J40 -> -165.06667 | L40: =+K40 -> -165.06667 | ... P40: =+O40 -> -165.06667 | Q40: =SUM(E40:P40) -> -1980.8
A41: Graduate | C41: Debt Interest | D41: =-'Balance Sheet'!K46-'Balance Sheet'!L46 -> -594.375 | E41: =+D41 -> -594.375 | F41: =+E41 -> -594.375 | G41: =+F41 -> -594.375 | H41: =+G41 -> -594.375 | I41: =+H41 -> -594.375 | J41: =+I41 -> -594.375 | K41: =+J41 -> -594.375 | L41: =+K41 -> -594.375 | ... P41: =+O41 -> -594.375 | Q41: =SUM(E41:P41) -> -7132.5
A42: Student Debt | D42: =+SUM(D40:D41) -> -759.44167 | E42: =+SUM(E40:E41) -> -759.44167 | F42: =+SUM(F40:F41) -> -759.44167 | G42: =+SUM(G40:G41) -> -759.44167 | H42: =+SUM(H40:H41) -> -759.44167 | I42: =+SUM(I40:I41) -> -759.44167 | J42: =+SUM(J40:J41) -> -759.44167 | K42: =+SUM(K40:K41) -> -759.44167 | ... P42: =+SUM(P40:P41) -> -759.44167 | Q42: =SUM(E42:P42) -> -9113.3
A43: Insurance | D43: 0 | E43: =+D43 -> 0 | F43: =+E43 -> 0 | G43: =+F43 -> 0 | H43: =+G43 -> 0 | I43: =+H43 -> 0 | J43: =+I43 -> 0 | K43: =+J43 -> 0 | L43: =+K43 -> 0 | ... P43: =+O43 -> 0 | Q43: =SUM(E43:P43) -> 0
A44: Parking | D44: 0 | E44: =+D44 -> 0 | F44: =+E44 -> 0 | G44: =+F44 -> 0 | H44: =+G44 -> 0 | I44: =+H44 -> 0 | J44: =+I44 -> 0 | K44: =+J44 -> 0 | L44: =+K44 -> 0 | ... P44: =+O44 -> 0 | Q44: =SUM(E44:P44) -> 0
A45: Maintenance | Q45: =SUM(E45:P45) -> 0
A46: Cars | D46: =SUM(D43:D45) -> 0 | E46: =SUM(E43:E45) -> 0 | F46: =SUM(F43:F45) -> 0 | G46: =SUM(G43:G45) -> 0 | H46: =SUM(H43:H45) -> 0 | I46: =SUM(I43:I45) -> 0 | J46: =SUM(J43:J45) -> 0 | K46: =SUM(K43:K45) -> 0 | ... P46: =SUM(P43:P45) -> 0 | Q46: =SUM(E46:P46) -> 0
A47: Umbrella insurance | Q47: =SUM(E47:P47) -> 0
A48: Personal Insurance | D48: =+D47 -> 0 | E48: =+E47 -> 0 | F48: =+F47 -> 0 | G48: =+G47 -> 0 | H48: =+H47 -> 0 | I48: =+I47 -> 0 | J48: =+J47 -> 0 | K48: =+K47 -> 0 | ... P48: =+P47 -> 0 | Q48: =SUM(E48:P48) -> 0
A49: Credit Cards | D49: =-'Balance Sheet'!B43 -> -11466.03 | E49: =+D49 -> -11466.03 | F49: =+E49 -> -11466.03 | G49: =+F49 -> -11466.03 | H49: =+G49 -> -11466.03 | I49: =+H49 -> -11466.03 | J49: =+I49 -> -11466.03 | K49: =+J49 -> -11466.03 | L49: =+K49 -> -11466.03 | ... P49: =+O49 -> -11466.03 | Q49: =SUM(E49:P49) -> -137592.36
A50: Tuition | B50: =+$A$53 -> Dependent Care | D50: -15000 | H50: -15000 | L50: -15000 | P50: -15000 | Q50: =SUM(E50:P50) -> -45000
A51: Babysitter | B51: =+$A$53 -> Dependent Care | D51: =-25*40*4.33333333333333 -> -4333.3333 | E51: =+D51 -> -4333.3333 | F51: =+E51 -> -4333.3333 | G51: =+F51 -> -4333.3333 | H51: =+G51 -> -4333.3333 | I51: =+H51 -> -4333.3333 | J51: =+I51 -> -4333.3333 | K51: =+J51 -> -4333.3333 | L51: =+K51 -> -4333.3333 | ... P51: =+O51 -> -4333.3333 | Q51: =SUM(E51:P51) -> -52000
A52: Babysitter Bonus | B52: =+$A$53 -> Dependent Care | Q52: =SUM(E52:P52) -> 0
A53: Dependent Care | D53: =+SUM(D50:D52) -> -19333.333 | E53: =+SUM(E50:E52) -> -4333.3333 | F53: =+SUM(F50:F52) -> -4333.3333 | G53: =+SUM(G50:G52) -> -4333.3333 | H53: =+SUM(H50:H52) -> -19333.333 | I53: =+SUM(I50:I52) -> -4333.3333 | J53: =+SUM(J50:J52) -> -4333.3333 | K53: =+SUM(K50:K52) -> -4333.3333 | ... P53: =+SUM(P50:P52) -> -19333.333 | Q53: =SUM(E53:P53) -> -97000
Q54: =SUM(E54:P54) -> 0
A55: Club Memberships | D55: =+SUM(D54:D54) -> 0 | E55: =+SUM(E54:E54) -> 0 | F55: =+SUM(F54:F54) -> 0 | G55: =+SUM(G54:G54) -> 0 | H55: =+SUM(H54:H54) -> 0 | I55: =+SUM(I54:I54) -> 0 | J55: =+SUM(J54:J54) -> 0 | K55: =+SUM(K54:K54) -> 0 | ... P55: =+SUM(P54:P54) -> 0 | Q55: =SUM(E55:P55) -> 0
A56: Phone | D56: -345.94 | E56: =+D56 -> -345.94 | F56: =+E56 -> -345.94 | G56: =+F56 -> -345.94 | H56: =+G56 -> -345.94 | I56: =+H56 -> -345.94 | J56: =+I56 -> -345.94 | K56: =+J56 -> -345.94 | L56: =+K56 -> -345.94 | ... O56: =+N56 -> -345.94 | P56: 0 | Q56: =SUM(E56:P56) -> -3805.34
A57: Electricity
A58: Water
A59: Phone / Utilities | D59: =+SUM(D56:D56) -> -345.94 | E59: =+SUM(E56:E56) -> -345.94 | F59: =+SUM(F56:F56) -> -345.94 | G59: =+SUM(G56:G56) -> -345.94 | H59: =+SUM(H56:H56) -> -345.94 | I59: =+SUM(I56:I56) -> -345.94 | J59: =+SUM(J56:J56) -> -345.94 | K59: =+SUM(K56:K56) -> -345.94 | ... P59: =+SUM(P56:P56) -> 0 | Q59: =SUM(E59:P59) -> -3805.34
A60: Travel / Holiday | I60: -4000 | J60: -1000 | K60: -2000 | O60: -4000 | P60: -4000 | Q60: =SUM(E60:P60) -> -15000
A61: Travel (not on credit card) | D61: =+SUM(D60:D60) -> 0 | E61: =+SUM(E60:E60) -> 0 | F61: =+SUM(F60:F60) -> 0 | G61: =+SUM(G60:G60) -> 0 | H61: =+SUM(H60:H60) -> 0 | I61: =+SUM(I60:I60) -> -4000 | J61: =+SUM(J60:J60) -> -1000 | K61: =+SUM(K60:K60) -> -2000 | ... P61: =+SUM(P60:P60) -> -4000 | Q61: =SUM(E61:P61) -> -15000
A62: Taxes (TBD) | H62: -30000
A63: Cash Expenses | D63: =+D61+D59+D55+D53+D49+D39+D36+D17+D46+D48+D42+D62+D26 -> -42181.44 | E63: =+E61+E59+E55+E53+E49+E39+E36+E17+E46+E48+E42+E62+E26 -> -38439.42 | F63: =+F61+F59+F55+F53+F49+F39+F36+F17+F46+F48+F42+F62+F26 -> -20939.42 | G63: =+G61+G59+G55+G53+G49+G39+G36+G17+G46+G48+G42+G62+G26 -> -20939.42 | H63: =+H61+H59+H55+H53+H49+H39+H36+H17+H46+H48+H42+H62+H26 -> -65939.42 | I63: =+I61+I59+I55+I53+I49+I39+I36+I17+I46+I48+I42+I62+I26 -> -24939.42 | J63: =+J61+J59+J55+J53+J49+J39+J36+J17+J46+J48+J42+J62+J26 -> -21939.42 | K63: =+K61+K59+K55+K53+K49+K39+K36+K17+K46+K48+K42+K62+K26 -> -40439.42 | ... P63: =+P61+P59+P55+P53+P49+P39+P36+P17+P46+P48+P42+P62+P26 -> -48392.38 | Q63: =SUM(E63:P63) -> -384726 | S63: =+Q63*(1+S64) -> -403962.3 | T63: =+S63*(1+T64) -> -424160.41 | U63: =+T63*(1+U64) -> -445368.44 | V63: =+U63*(1+V64) -> -467636.86 | W63: =+V63*(1+W64) -> -491018.7 | X63: =+W63*(1+X64) -> -515569.64 | Y63: =+X63*(1+Y64) -> -541348.12 | Z63: =+Y63*(1+Z64) -> -568415.52 | AA63: =+Z63*(1+AA64) -> -596836.3 | ... AL63: =+AK63*(1+AL64) -> -1020792.6
A64: Debt Interest | D64: =SUMIF($C$17:$C$63,"Debt Interest",D17:D63) -> -4229.525 | E64: =SUMIF($C$17:$C$63,"Debt Interest",E17:E63) -> -4229.525 | F64: =SUMIF($C$17:$C$63,"Debt Interest",F17:F63) -> -4229.525 | G64: =SUMIF($C$17:$C$63,"Debt Interest",G17:G63) -> -4229.525 | H64: =SUMIF($C$17:$C$63,"Debt Interest",H17:H63) -> -4229.525 | I64: =SUMIF($C$17:$C$63,"Debt Interest",I17:I63) -> -4229.525 | J64: =SUMIF($C$17:$C$63,"Debt Interest",J17:J63) -> -4229.525 | K64: =SUMIF($C$17:$C$63,"Debt Interest",K17:K63) -> -4229.525 | ... Q64: =SUMIF($C$17:$C$63,"Debt Interest",Q17:Q63) -> -50754.3 | R64: Growth | S64: 0.05 | T64: =+S64 -> 0.05 | U64: =+T64 -> 0.05 | V64: =+U64 -> 0.05 | W64: =+V64 -> 0.05 | X64: =+W64 -> 0.05 | Y64: =+X64 -> 0.05 | Z64: =+Y64 -> 0.05 | AA64: =+Z64 -> 0.05 | ... AL64: =+AK64 -> 0.05
A65: Total ex Debt Interest | D65: =+D63-D64 -> -37951.915 | E65: =+E63-E64 -> -34209.895 | F65: =+F63-F64 -> -16709.895 | G65: =+G63-G64 -> -16709.895 | H65: =+H63-H64 -> -61709.895 | I65: =+I63-I64 -> -20709.895 | J65: =+J63-J64 -> -17709.895 | K65: =+K63-K64 -> -36209.895 | ... Q65: =+Q63-Q64 -> -333971.7
A67: Net Cash Flow | D67: =+D16+D63 -> 193661.05 | E67: =+E16+E63 -> -19347.3 | F67: =+F16+F63 -> -1871.9829 | G67: =+G16+G63 -> -1928.655 | H67: =+H16+H63 -> -46990.203 | I67: =+I16+I63 -> -6000.7541 | J67: =+J16+J63 -> -3029.2556 | K67: =+K16+K63 -> -21574.131 | ... Q67: =+Q16+Q63 -> 66338.316 | R67: =12100/Q67 -> 0.18239836 | S67: =+S16+S63 -> 69945.96 | T67: =+T16+T63 -> 74337.972 | U67: =+U16+U63 -> 78967.3 | V67: =+V16+V63 -> 83845.933 | W67: =+W16+W63 -> 88986.44 | X67: =+X16+X63 -> 94401.999 | Y67: =+Y16+Y63 -> 99904.022 | Z67: =+Z16+Z63 -> 105053.19 | ... AL67: =+AL16+AL63 -> 183822.01
A68: Net cash flow excluding interet income | D68: =+D10+D63 -> 193272.73 | E68: =+E10+E63 -> -19625.89 | F68: =+F10+F63 -> -2125.8904 | G68: =+G10+G63 -> -2125.8904 | H68: =+H10+H63 -> -47125.89 | I68: =+I10+I63 -> -6125.8904 | J68: =+J10+J63 -> -3125.8904 | K68: =+K10+K63 -> -21625.89 | ... P68: =+P10+P63 -> 187061.79
Q69: =Q10+Q63 -> 57677
A70: Interest Income Calculation
A71: GURU optimizer | C71: 1
A72: ONLY BANK AND BROKERAGE ACCOUNTS | AX72: Sensitivities
A73: MONEY MOVEMENT PROJECTION
B74: Yield on cash | D74: Balance | BE74: =+A83 -> Immediate - Ending | BS74: =A82 -> Move cash from Short-Term to Immediate
AZ75: Optimizer | BE75: =+E5 -> January | BF75: =+F5 -> February | BG75: =+G5 -> March | BH75: =+H5 -> April | BI75: =+I5 -> May | BJ75: =+J5 -> June | BK75: =+K5 -> July | BL75: =+L5 -> August | ... BP75: =+P5 -> December | BS75: =BE75 -> January | BT75: =BF75 -> February | BU75: =BG75 -> March | BV75: =BH75 -> April | BW75: =BI75 -> May | BX75: =BJ75 -> June | BY75: =BK75 -> July | BZ75: =BL75 -> August | ... CD75: =BP75 -> December
A76: Immediate - Beginning (Assumes Interest Accrued End of Month) | E76: =D83 -> 20939.42 | F76: =E83+E86 -> 20939.508 | G76: =F83+F86 -> 20939.508 | H76: =G83+G86 -> 65939.602 | I76: =H83+H86 -> 24939.61 | J76: =I83+I86 -> 21939.518 | K76: =J83+J86 -> 40439.551 | L76: =K83+K86 -> 35939.58 | M76: =L83+L86 -> 20939.539 | ... P76: =O83+O86 -> 48392.534 | Q76: =D83 -> 20939.42 | S76: =P83+P86 -> 38439.755 | T76: =S83+S86 -> 202376.46 | U76: =T83+T86 -> 226773.21 | V76: =U83+U86 -> 252390.42 | W76: =V83+V86 -> 279289.11 | X76: =W83+W86 -> 307533.36 | Y76: =X83+X86 -> 337190.43 | Z76: =Y83+Y86 -> 368330.98 | AA76: =Z83+Z86 -> 401029.17 | ... AL76: =AK83+AK86 -> 888840.68 | AX76: Ending Balance | AZ76: 0 | BA76: 1 | BD76: Optimizer | BE76: =+E83 -> 20939.42 | BF76: =+F83 -> 20939.42 | BG76: =+G83 -> 65939.42 | BH76: =+H83 -> 24939.42 | BI76: =+I83 -> 21939.42 | BJ76: =+J83 -> 40439.42 | BK76: =+K83 -> 35939.42 | BL76: =+L83 -> 20939.42 | ... BP76: =+P83 -> 38439.574 | BR76: Optimizer | BS76: =+E82 -> 19625.89 | BT76: =+F82 -> 2125.8026 | BU76: =+G82 -> 47125.803 | BV76: =+H82 -> 6125.7084 | BW76: =+I82 -> 3125.7 | BX76: =+J82 -> 21625.792 | BY76: =+K82 -> 17125.76 | BZ76: =+L82 -> 2125.7304 | ... CD76: =+P82 -> 0
A77: Paycheck allocation | E77: =IF($C$71=1,OPTIMIZER!$X$24,100%) -> 1 | F77: =IF($C$71=1,OPTIMIZER!$X$24,100%) -> 1 | G77: =IF($C$71=1,OPTIMIZER!$X$24,100%) -> 1 | H77: =IF($C$71=1,OPTIMIZER!$X$24,100%) -> 1 | I77: =IF($C$71=1,OPTIMIZER!$X$24,100%) -> 1 | J77: =IF($C$71=1,OPTIMIZER!$X$24,100%) -> 1 | K77: =IF($C$71=1,OPTIMIZER!$X$24,100%) -> 1 | L77: =IF($C$71=1,OPTIMIZER!$X$24,100%) -> 1 | ... O77: =IF($C$71=1,OPTIMIZER!$X$24,100%) -> 1 | P77: =IF($C$71=1,OPTIMIZER!R24,-P79/P10+20%) -> 0.16325648 | Q77: =+Q78/$Q$16 -> 0.67048541 | S77: =IF($C$71=1,Q77,MIN(-S79/S10+5%,100%)) -> 0.91962792 | T77: =IF($C$71=1,R77,MIN(-T79/T10+5%,100%)) -> 0 | U77: =IF($C$71=1,S77,MIN(-U79/U10+5%,100%)) -> 0.91962792 | V77: =IF($C$71=1,T77,MIN(-V79/V10+5%,100%)) -> 0 | W77: =IF($C$71=1,U77,MIN(-W79/W10+5%,100%)) -> 0.91962792 | X77: =IF($C$71=1,V77,MIN(-X79/X10+5%,100%)) -> 0 | Y77: =IF($C$71=1,W77,MIN(-Y79/Y10+5%,100%)) -> 0.91962792 | Z77: =IF($C$71=1,X77,MIN(-Z79/Z10+5%,100%)) -> 0 | ... AL77: =IF($C$71=1,AJ77,MIN(-AL79/AL10+5%,100%)) -> 0 | AX77: Immediate | AY77: =+Q83 -> 38439.755 | AZ77: 179142.04 | BA77: 38439.755 | BD77: 0 | BE77: 132050 | BF77: 132050 | BG77: 132050 | BH77: 132050 | BI77: 132050 | BJ77: 132050 | BK77: 132050 | BL77: 132050 | BM77: 132050 | BN77: 132050 | BO77: 132050 | BP77: 179141.39 | BR77: 0 | BS77: 19625.89 | BT77: 2125.3372 | BU77: 2125.3372 | BV77: 47125.337 | BW77: 6125.3372 | BX77: 3125.3372 | BY77: 21625.337 | BZ77: 17125.337 | CA77: 2125.3372 | CB77: 2125.3372 | CC77: 6125.3372 | CD77: 0
A78: Income allocation to Immediate | E78: =E77*E$10 -> 18813.53 | F78: =F77*F$10 -> 18813.53 | G78: =G77*G$10 -> 18813.53 | H78: =H77*H$10 -> 18813.53 | I78: =I77*I$10 -> 18813.53 | J78: =J77*J$10 -> 18813.53 | K78: =K77*K$10 -> 18813.53 | L78: =L77*L$10 -> 18813.53 | ... P78: =P77*P$10 -> 38439.42 | Q78: =SUM(E78:P78) -> 245388.25 | S78: =S77*S$10 -> 427188.46 | T78: =T77*T$10 -> 0 | U78: =U77*U$10 -> 470975.27 | V78: =V77*V$10 -> 0 | W78: =W77*W$10 -> 519250.24 | X78: =X77*X$10 -> 0 | Y78: =Y77*Y$10 -> 572473.39 | Z78: =Z77*Z$10 -> 0 | ... AL78: =AL77*AL$10 -> 0 | AX78: Short | AY78: =+Q95 -> 129539.36 | AZ78: 253850.57 | BA78: 129539.36 | BD78: 1 | BE78: 20939.42 | BF78: 20939.42 | BG78: 65939.42 | BH78: 24939.42 | BI78: 21939.42 | BJ78: 40439.42 | BK78: 35939.42 | BL78: 20939.42 | BM78: 20939.42 | BN78: 24939.42 | BO78: 48392.38 | BP78: 38439.574 | BR78: 1 | BS78: 19625.89 | BT78: 2125.8026 | BU78: 47125.803 | BV78: 6125.7084 | BW78: 3125.7 | BX78: 21625.792 | BY78: 17125.76 | BZ78: 2125.7304 | CA78: 2125.7712 | CB78: 6125.8026 | CC78: 29578.754 | CD78: 0
A79: Expenses (100% through immediate) | E79: =E63 -> -38439.42 | F79: =F63 -> -20939.42 | G79: =G63 -> -20939.42 | H79: =H63 -> -65939.42 | I79: =I63 -> -24939.42 | J79: =J63 -> -21939.42 | K79: =K63 -> -40439.42 | L79: =L63 -> -35939.42 | ... P79: =P63 -> -48392.38 | Q79: =SUM(E79:P79) -> -384726 | S79: =S63 -> -403962.3 | T79: =T63 -> -424160.41 | U79: =U63 -> -445368.44 | V79: =V63 -> -467636.86 | W79: =W63 -> -491018.7 | X79: =X63 -> -515569.64 | Y79: =Y63 -> -541348.12 | Z79: =Z63 -> -568415.52 | ... AL79: =AL63 -> -1020792.6 | AX79: Medium | AY79: =+Q104 -> 138507.21 | AZ79: 138507.21 | BA79: 138507.21
A80: Subtotal Cash: After Tax Income and Expenses | C80: optimizer on | D80: 5000 | E80: =+E76+E78+E79 -> 1313.5296 | F80: =+F76+F78+F79 -> 18813.617 | G80: =+G76+G78+G79 -> 18813.617 | H80: =+H76+H78+H79 -> 18813.712 | I80: =+I76+I78+I79 -> 18813.72 | J80: =+J76+J78+J79 -> 18813.628 | K80: =+K76+K78+K79 -> 18813.66 | L80: =+L76+L78+L79 -> 18813.69 | ... Q80: =+Q76+Q78+Q79 -> -118398.33 | S80: =+S76+S78+S79 -> 202368.2 | T80: =+T76+T78+T79 -> 226763.92 | U80: =+U76+U78+U79 -> 252380.05 | V80: =+V76+V78+V79 -> 279277.6 | W80: =+W76+W78+W79 -> 307520.65 | X80: =+X76+X78+X79 -> 337176.47 | Y80: =+Y76+Y78+Y79 -> 368315.7 | Z80: =+Z76+Z78+Z79 -> 401012.51 | ... AL80: =+AL76+AL78+AL79 -> 947532.02 | BE80: =A95 -> Short - Ending
A81: Minimum Threshold for Ending Balance | C81: optimizer off | D81: =D83 -> 20939.42 | E81: =IF($C$71=1,-SUM(F63),$D$81) -> 20939.42 | F81: =IF($C$71=1,-SUM(G63),$D$81) -> 20939.42 | G81: =IF($C$71=1,-SUM(H63),$D$81) -> 65939.42 | H81: =IF($C$71=1,-SUM(I63),$D$81) -> 24939.42 | I81: =IF($C$71=1,-SUM(J63),$D$81) -> 21939.42 | J81: =IF($C$71=1,-SUM(K63),$D$81) -> 40439.42 | K81: =IF($C$71=1,-SUM(L63),$D$81) -> 35939.42 | L81: =IF($C$71=1,-SUM(M63),$D$81) -> 20939.42 | ... O81: =IF($C$71=1,-SUM(P63),$D$81) -> 48392.38 | P81: =IF($C$71=1,-SUM(E63),$D$81) -> 38439.42 | S81: =S76 -> 38439.755 | T81: =T76 -> 202376.46 | U81: =U76 -> 226773.21 | V81: =V76 -> 252390.42 | W81: =W76 -> 279289.11 | X81: =X76 -> 307533.36 | Y81: =Y76 -> 337190.43 | Z81: =Z76 -> 368330.98 | ... AL81: =AL76 -> 888840.68 | AZ81: Optimizer | BE81: =+BE75 -> January | BF81: =+BF75 -> February | BG81: =+BG75 -> March | BH81: =+BH75 -> April | BI81: =+BI75 -> May | BJ81: =+BJ75 -> June | BK81: =+BK75 -> July | BL81: =+BL75 -> August | ... BP81: =+BP75 -> December | BS81: =A94 -> Move cash from Medium-Term to Short-Term
A82: Move cash from Short-Term to Immediate | E82: =IF(E80>E81,0,-(E80-E81)) -> 19625.89 | F82: =IF(F80>F81,0,-(F80-F81)) -> 2125.8026 | G82: =IF(G80>G81,0,-(G80-G81)) -> 47125.803 | H82: =IF(H80>H81,0,-(H80-H81)) -> 6125.7084 | I82: =IF(I80>I81,0,-(I80-I81)) -> 3125.7 | J82: =IF(J80>J81,0,-(J80-J81)) -> 21625.792 | K82: =IF(K80>K81,0,-(K80-K81)) -> 17125.76 | L82: =IF(L80>L81,0,-(L80-L81)) -> 2125.7304 | ... P82: =IF(P80>P81,0,-(P80-P81)) -> 0 | Q82: =SUM(E82:P82) -> 156836.51 | S82: =IF(S80>S81,0,-(S80-S81)) -> 0 | T82: =IF(T80>T81,0,-(T80-T81)) -> 0 | U82: =IF(U80>U81,0,-(U80-U81)) -> 0 | V82: =IF(V80>V81,0,-(V80-V81)) -> 0 | W82: =IF(W80>W81,0,-(W80-W81)) -> 0 | X82: =IF(X80>X81,0,-(X80-X81)) -> 0 | Y82: =IF(Y80>Y81,0,-(Y80-Y81)) -> 0 | Z82: =IF(Z80>Z81,0,-(Z80-Z81)) -> 0 | ... AL82: =IF(AL80>AL81,0,-(AL80-AL81)) -> 0 | AX82: Annual Pre-Tax Income | AZ82: 0 | BA82: 1 | BD82: Optimizer | BE82: =+E95 -> 109758.9 | BF82: =+F95 -> 107911.6 | BG82: =+G95 -> 61039.621 | BH82: =+H95 -> 55110.966 | BI82: =+I95 -> 52120.762 | BJ82: =+J95 -> 30620.008 | BK82: =+K95 -> 13590.753 | BL82: =+L95 -> 11516.622 | ... BP82: =+P95 -> 129388.68 | BS82: =BE75 -> January | BT82: =BF75 -> February | BU82: =BG75 -> March | BV82: =BH75 -> April | BW82: =BI75 -> May | BX82: =BJ75 -> June | BY82: =BK75 -> July | BZ82: =BL75 -> August | ... CD82: =BP75 -> December
A83: Immediate - Ending | D83: =IF($C$71=1,OPTIMIZER!AR24,'Balance Sheet'!$B$9) -> 20939.42 | E83: =+E80+E82 -> 20939.42 | F83: =+F80+F82 -> 20939.42 | G83: =+G80+G82 -> 65939.42 | H83: =+H80+H82 -> 24939.42 | I83: =+I80+I82 -> 21939.42 | J83: =+J80+J82 -> 40439.42 | K83: =+K80+K82 -> 35939.42 | L83: =+L80+L82 -> 20939.42 | ... P83: =+P80+P82 -> 38439.574 | Q83: =+Q80+Q82+SUM(E86:P86) -> 38439.755 | R83: =ROUND(Q83,3)=ROUND(P83+P86,3) -> TRUE | S83: =+S80+S82 -> 202368.2 | T83: =+T80+T82 -> 226763.92 | U83: =+U80+U82 -> 252380.05 | V83: =+V80+V82 -> 279277.6 | W83: =+W80+W82 -> 307520.65 | X83: =+X80+X82 -> 337176.47 | Y83: =+Y80+Y82 -> 368315.7 | Z83: =+Z80+Z82 -> 401012.51 | ... AL83: =+AL80+AL82 -> 947532.02 | AX83: Immediate | AY83: =+Q85 -> 2.9717967 | AZ83: 12.711134 | BA83: 2.9717967 | BD83: 0 | BE83: 220374.11 | BF83: 218620.68 | BG83: 216850.28 | BH83: 170077.02 | BI83: 164264.54 | BJ83: 161409.55 | BK83: 140047.52 | BL83: 123165.92 | BM83: 121253.42 | BN83: 119325.7 | BO83: 113394.87 | BP83: 253553.99 | BR83: Optimizer | BS83: =+E94 -> 0 | BT83: =+F94 -> 0 | BU83: =+G94 -> 0 | BV83: =+H94 -> 0 | BW83: =+I94 -> 0 | BX83: =+J94 -> 0 | BY83: =+K94 -> 0 | BZ83: =+L94 -> 0 | ... CD83: =+P94 -> 0
A84: Yield | D84: ='Balance Sheet'!E9 -> 9.4850435e-05 | E84: =+D84 -> 9.4850435e-05 | F84: =+E84 -> 9.4850435e-05 | G84: =+F84 -> 9.4850435e-05 | H84: =+G84 -> 9.4850435e-05 | I84: =+H84 -> 9.4850435e-05 | J84: =+I84 -> 9.4850435e-05 | K84: =+J84 -> 9.4850435e-05 | L84: =+K84 -> 9.4850435e-05 | ... P84: =+O84 -> 9.4850435e-05 | Q84: =+Q85/AVERAGE(Q76,Q83) -> 0.00010009559 | S84: =+Q84 -> 0.00010009559 | T84: =+S84 -> 0.00010009559 | U84: =+T84 -> 0.00010009559 | V84: =+U84 -> 0.00010009559 | W84: =+V84 -> 0.00010009559 | X84: =+W84 -> 0.00010009559 | Y84: =+X84 -> 0.00010009559 | Z84: =+Y84 -> 0.00010009559 | AA84: =+Z84 -> 0.00010009559 | ... AL84: =+AK84 -> 0.00010009559 | AX84: Short | AY84: =Q97 -> 2094.1005 | AZ84: 6148.8257 | BA84: 2094.1005 | BD84: 1 | BE84: 109758.9 | BF84: 107911.6 | BG84: 61039.621 | BH84: 55110.966 | BI84: 52120.762 | BJ84: 30620.008 | BK84: 13590.753 | BL84: 11516.622 | BM84: 9420.1504 | BN84: 3318.7645 | BO84: 0 | BP84: 129388.68 | BR84: 0 | BS84: 0 | BT84: 0 | BU84: 0 | BV84: 0 | BW84: 0 | BX84: 0 | BY84: 0 | BZ84: 0 | CA84: 0 | CB84: 0 | CC84: 0 | CD84: 0
A85: Immediate - Interest Income | E85: =AVERAGE(E76,E83)*E84/12 -> 0.16550943 | F85: =AVERAGE(F76,F83)*F84/12 -> 0.16550977 | G85: =AVERAGE(G76,G83)*G84/12 -> 0.34335434 | H85: =AVERAGE(H76,H83)*H84/12 -> 0.35916312 | I85: =AVERAGE(I76,I83)*I84/12 -> 0.18527069 | J85: =AVERAGE(J76,J83)*J84/12 -> 0.24652789 | K85: =AVERAGE(K76,K83)*K84/12 -> 0.30185744 | L85: =AVERAGE(L76,L83)*L84/12 -> 0.22479158 | ... P85: =AVERAGE(P76,P83)*P84/12 -> 0.3431693 | Q85: =SUM(E85:P85) -> 2.9717967 | S85: =AVERAGE(S76,S83)*S84 -> 15.583393 | T85: =AVERAGE(T76,T83)*T84 -> 17.528922 | U85: =AVERAGE(U76,U83)*U84 -> 19.571777 | V85: =AVERAGE(V76,V83)*V84 -> 21.716827 | W85: =AVERAGE(W76,W83)*W84 -> 23.969179 | X85: =AVERAGE(X76,X83)*X84 -> 26.334199 | Y85: =AVERAGE(Y76,Y83)*Y84 -> 28.817521 | Z85: =AVERAGE(Z76,Z83)*Z84 -> 31.425059 | ... AL85: =AVERAGE(AL76,AL83)*AL84 -> 75.009564 | AX85: Medium | AY85: =Q107 -> 5395.701 | AZ85: 5395.701 | BA85: 5395.701 | BR85: 1 | BS85: 0 | BT85: 0 | BU85: 0 | BV85: 0 | BW85: 0 | BX85: 0 | BY85: 0 | BZ85: 0 | CA85: 0 | CB85: 0 | CC85: 26245.126 | CD85: 0
A86: Immediate - Interest Income After-Tax | C86: Tax rate | D86: =1-OPTIMIZER!AY24/OPTIMIZER!AW24 -> 0.47 | E86: =+E85*(1-$D$86) -> 0.087719995 | F86: =+F85*(1-$D$86) -> 0.087720179 | G86: =+G85*(1-$D$86) -> 0.1819778 | H86: =+H85*(1-$D$86) -> 0.19035645 | I86: =+I85*(1-$D$86) -> 0.098193463 | J86: =+J85*(1-$D$86) -> 0.13065978 | K86: =+K85*(1-$D$86) -> 0.15998444 | L86: =+L85*(1-$D$86) -> 0.11913954 | ... P86: =+P85*(1-$D$86) -> 0.18187973 | Q86: =SUM(E86:P86) -> 1.5750523 | S86: =+S85*(1-$D$86) -> 8.2591981 | T86: =+T85*(1-$D$86) -> 9.2903284 | U86: =+U85*(1-$D$86) -> 10.373042 | V86: =+V85*(1-$D$86) -> 11.509918 | W86: =+W85*(1-$D$86) -> 12.703665 | X86: =+X85*(1-$D$86) -> 13.957125 | Y86: =+Y85*(1-$D$86) -> 15.273286 | Z86: =+Z85*(1-$D$86) -> 16.655281 | ... AL86: =+AL85*(1-$D$86) -> 39.755069 | BE86: =A104 -> Medium - Ending
F87: =F83-E83 -> 0 | AZ87: Optimizer | BE87: =+BE75 -> January | BF87: =+BF75 -> February | BG87: =+BG75 -> March | BH87: =+BH75 -> April | BI87: =+BI75 -> May | BJ87: =+BJ75 -> June | BK87: =+BK75 -> July | BL87: =+BL75 -> August | ... BP87: =+BP75 -> December | BS87: =+A90 -> Income allocation to Short-Term
A88: Short - Beginning (Assumes Interest Accrued End of Month) | E88: =D95 -> 129384.79 | F88: =E95+E98 -> 110037.41 | G88: =F95+F98 -> 108165.42 | H88: =G95+G98 -> 61236.674 | I88: =H95+H98 -> 55246.462 | J88: =I95+I98 -> 52245.8 | K88: =J95+J98 -> 30716.512 | L88: =K95+K98 -> 13642.352 | M88: =L95+L98 -> 11545.922 | ... P88: =O95+O98 -> 3.8822881 | Q88: =D95 -> 129384.79 | S88: =P95+P98 -> 129539.36 | T88: =S95+S98 -> 269977.14 | U88: =T95+T98 -> 287128.18 | V88: =U95+U98 -> 305368.8 | W88: =V95+V98 -> 324768.2 | X88: =W95+W98 -> 345400 | Y88: =X95+X98 -> 367342.49 | Z88: =Y95+Y98 -> 390678.94 | AA88: =Z95+Z98 -> 415497.91 | ... AL88: =AK95+AK98 -> 818099.33 | AX88: Annual Pre-Tax Income | AZ88: 0 | BA88: 1 | BD88: Optimizer | BE88: =+E104 -> 135000 | BF88: =+F104 -> 135288.84 | BG88: =+G104 -> 135578.31 | BH88: =+H104 -> 135868.39 | BI88: =+I104 -> 136159.09 | BJ88: =+J104 -> 136450.41 | BK88: =+K104 -> 136742.36 | BL88: =+L104 -> 137034.93 | ... BP88: =+P104 -> 138211.49 | BS88: =BE$75 -> January | BT88: =BF$75 -> February | BU88: =BG$75 -> March | BV88: =BH$75 -> April | BW88: =BI$75 -> May | BX88: =BJ$75 -> June | BY88: =BK$75 -> July | BZ88: =BL$75 -> August | ... CD88: =BP$75 -> December
A89: Paycheck allocation | E89: =IF($C$71=1,OPTIMIZER!$X$25,0) -> 0 | F89: =IF($C$71=1,OPTIMIZER!$X$25,0) -> 0 | G89: =IF($C$71=1,OPTIMIZER!$X$25,0) -> 0 | H89: =IF($C$71=1,OPTIMIZER!$X$25,0) -> 0 | I89: =IF($C$71=1,OPTIMIZER!$X$25,0) -> 0 | J89: =IF($C$71=1,OPTIMIZER!$X$25,0) -> 0 | K89: =IF($C$71=1,OPTIMIZER!$X$25,0) -> 0 | L89: =IF($C$71=1,OPTIMIZER!$X$25,0) -> 0 | ... O89: =IF($C$71=1,OPTIMIZER!$X$25,0) -> 0 | P89: =IF($C$71=1,OPTIMIZER!R25,1-P77) -> 0.54951157 | Q89: =+Q90/$Q$16 -> 0.31031264 | S89: =+S90/S10 -> 0.027323781 | T89: =+T90/T10 -> 0.027675809 | U89: =+U90/U10 -> 0.028032373 | V89: =+V90/V10 -> 0.028393531 | W89: =+W90/W10 -> 0.028759342 | X89: =+X90/X10 -> 0.029129865 | Y89: =+Y90/Y10 -> 0.029505163 | Z89: =+Z90/Z10 -> 0.029885295 | ... AL89: =+AL90/AL10 -> 0.03484753 | AX89: Immediate | AY89: =Q86 -> 1.5750523 | AZ89: 6.736901 | BA89: 1.5750523 | BD89: 0 | BE89: 135000 | BF89: 135288.84 | BG89: 135578.31 | BH89: 135868.39 | BI89: 136159.09 | BJ89: 136450.41 | BK89: 136742.36 | BL89: 137034.93 | BM89: 137328.13 | BN89: 137621.95 | BO89: 137916.41 | BP89: 138211.49 | BR89: Optimizer | BS89: =+E90 -> 0 | BT89: =+F90 -> 0 | BU89: =+G90 -> 0 | BV89: =+H90 -> 0 | BW89: =+I90 -> 0 | BX89: =+J90 -> 0 | BY89: =+K90 -> 0 | BZ89: =+L90 -> 0 | ... CD89: =+P90 -> 129384.79
A90: Income allocation to Short-Term | E90: =E89*E$10 -> 0 | F90: =F89*F$10 -> 0 | G90: =G89*G$10 -> 0 | H90: =H89*H$10 -> 0 | I90: =I89*I$10 -> 0 | J90: =J89*J$10 -> 0 | K90: =K89*K$10 -> 0 | L90: =L89*L$10 -> 0 | ... P90: =P89*P$10 -> 129384.79 | Q90: =SUM(E90:P90) -> 129384.79 | S90: =MIN(S93-S91-S88,S10-S78) -> 12692.529 | T90: =MIN(T93-T91-T88,T10-T78) -> 13498.857 | U90: =MIN(U93-U91-U88,U10-U78) -> 14356.409 | V90: =MIN(V93-V91-V88,V10-V78) -> 15268.44 | W90: =MIN(W93-W91-W88,W10-W78) -> 16238.41 | X90: =MIN(X93-X91-X88,X10-X78) -> 17270 | Y90: =MIN(Y93-Y91-Y88,Y10-Y78) -> 18367.125 | Z90: =MIN(Z93-Z91-Z88,Z10-Z78) -> 19533.947 | ... AL90: =MIN(AL93-AL91-AL88,AL10-AL78) -> 40904.966 | AX90: Short | AY90: =Q98 -> 1361.1653 | AZ90: 3258.8776 | BA90: 1361.1653 | BD90: 1 | BE90: 135000 | BF90: 135288.84 | BG90: 135578.31 | BH90: 135868.39 | BI90: 136159.09 | BJ90: 136450.41 | BK90: 136742.36 | BL90: 137034.93 | BM90: 137328.13 | BN90: 137621.95 | BO90: 137916.41 | BP90: 138211.49 | BR90: 0 | BS90: 0 | BT90: 0 | BU90: 0 | BV90: 0 | BW90: 0 | BX90: 0 | BY90: 0 | BZ90: 0 | CA90: 0 | CB90: 0 | CC90: 0 | CD90: 139970.96
A91: Cash moved to immediate term | E91: =-E82 -> -19625.89 | F91: =-F82 -> -2125.8026 | G91: =-G82 -> -47125.803 | H91: =-H82 -> -6125.7084 | I91: =-I82 -> -3125.7 | J91: =-J82 -> -21625.792 | K91: =-K82 -> -17125.76 | L91: =-L82 -> -2125.7304 | ... P91: =-P82 -> 0 | Q91: =SUM(E91:P91) -> -156836.51 | R91: =+Q91=SUM(E91:P91) -> TRUE | S91: =-S82 -> 0 | T91: =-T82 -> 0 | U91: =-U82 -> 0 | V91: =-V82 -> 0 | W91: =-W82 -> 0 | X91: =-X82 -> 0 | Y91: =-Y82 -> 0 | Z91: =-Z82 -> 0 | ... AL91: =-AL82 -> 0 | AX91: Medium | AY91: =Q108 -> 3507.2057 | AZ91: 3507.2057 | BA91: 3507.2057 | BR91: 1 | BS91: 0 | BT91: 0 | BU91: 0 | BV91: 0 | BW91: 0 | BX91: 0 | BY91: 0 | BZ91: 0 | CA91: 0 | CB91: 0 | CC91: 0 | CD91: 129384.79
A92: Subtotal Cash | E92: =+E88+E90+E91 -> 109758.9 | F92: =+F88+F90+F91 -> 107911.6 | G92: =+G88+G90+G91 -> 61039.621 | H92: =+H88+H90+H91 -> 55110.966 | I92: =+I88+I90+I91 -> 52120.762 | J92: =+J88+J90+J91 -> 30620.008 | K92: =+K88+K90+K91 -> 13590.753 | L92: =+L88+L90+L91 -> 11516.622 | ... Q92: =+Q88+Q90+Q91 -> 101933.07 | S92: =+S88+S90+S91 -> 266543.1 | T92: =+T88+T90+T91 -> 283475.99 | U92: =+U88+U90+U91 -> 301484.59 | V92: =+V88+V90+V91 -> 320637.24 | W92: =+W88+W90+W91 -> 341006.61 | X92: =+X88+X90+X91 -> 362670 | Y92: =+Y88+Y90+Y91 -> 385709.62 | Z92: =+Z88+Z90+Z91 -> 410212.89 | ... AL92: =+AL88+AL90+AL91 -> 859004.3 | BE92: =A116 -> Long - Ending
A93: Minimum Threshold for Ending Balance | E93: 0 | F93: =+E93 -> 0 | G93: =+F93 -> 0 | H93: =+G93 -> 0 | I93: =+H93 -> 0 | J93: =+I93 -> 0 | K93: =+J93 -> 0 | L93: =+K93 -> 0 | M93: =+L93 -> 0 | ... P93: =+O93 -> 0 | S93: =+S88*(1+S64) -> 136016.33 | T93: =+T88*(1+T64) -> 283475.99 | U93: =+U88*(1+U64) -> 301484.59 | V93: =+V88*(1+V64) -> 320637.24 | W93: =+W88*(1+W64) -> 341006.61 | X93: =+X88*(1+X64) -> 362670 | Y93: =+Y88*(1+Y64) -> 385709.62 | Z93: =+Z88*(1+Z64) -> 410212.89 | ... AL93: =+AL88*(1+AL64) -> 859004.3 | BE93: =+BE75 -> January | BF93: =+BF75 -> February | BG93: =+BG75 -> March | BH93: =+BH75 -> April | BI93: =+BI75 -> May | BJ93: =+BJ75 -> June | BK93: =+BK75 -> July | BL93: =+BL75 -> August | ... BP93: =+BP75 -> December | BS93: =+A102 -> Income allocation to Medium-Term
A94: Move cash from Medium-Term to Short-Term | E94: =IF(E92>E93,0,-(E92-E93)) -> 0 | F94: =IF(F92>F93,0,-(F92-F93)) -> 0 | G94: =IF(G92>G93,0,-(G92-G93)) -> 0 | H94: =IF(H92>H93,0,-(H92-H93)) -> 0 | I94: =IF(I92>I93,0,-(I92-I93)) -> 0 | J94: =IF(J92>J93,0,-(J92-J93)) -> 0 | K94: =IF(K92>K93,0,-(K92-K93)) -> 0 | L94: =IF(L92>L93,0,-(L92-L93)) -> 0 | ... P94: =IF(P92>P93,0,-(P92-P93)) -> 0 | Q94: =SUM(E94:P94) -> 26245.126 | S94: =IF(S92>S93,0,-(S92-S93)) -> 0 | T94: =IF(T92>T93,0,-(T92-T93)) -> 0 | U94: =IF(U92>U93,0,-(U92-U93)) -> 0 | V94: =IF(V92>V93,0,-(V92-V93)) -> 0 | W94: =IF(W92>W93,0,-(W92-W93)) -> 0 | X94: =IF(X92>X93,0,-(X92-X93)) -> 0 | Y94: =IF(Y92>Y93,0,-(Y92-Y93)) -> 0 | Z94: =IF(Z92>Z93,0,-(Z92-Z93)) -> 0 | ... AL94: =IF(AL92>AL93,0,-(AL92-AL93)) -> 0 | BD94: Optimizer | BE94: =E116 -> 2524138.8 | BF94: =F116 -> 2538862.9 | BG94: =G116 -> 2553672.9 | BH94: =H116 -> 2568569.4 | BI94: =I116 -> 2583552.7 | BJ94: =J116 -> 2598623.4 | BK94: =K116 -> 2613782 | BL94: =L116 -> 2629029.1 | ... BP94: =P116 -> 2690912 | BS94: =BE$75 -> January | BT94: =BF$75 -> February | BU94: =BG$75 -> March | BV94: =BH$75 -> April | BW94: =BI$75 -> May | BX94: =BJ$75 -> June | BY94: =BK$75 -> July | BZ94: =BL$75 -> August | ... CD94: =BP$75 -> December
A95: Short - Ending | D95: =IF($C$71=1,OPTIMIZER!AR25,'Balance Sheet'!B13) -> 129384.79 | E95: =+E92+E94 -> 109758.9 | F95: =+F92+F94 -> 107911.6 | G95: =+G92+G94 -> 61039.621 | H95: =+H92+H94 -> 55110.966 | I95: =+I92+I94 -> 52120.762 | J95: =+J92+J94 -> 30620.008 | K95: =+K92+K94 -> 13590.753 | L95: =+L92+L94 -> 11516.622 | ... P95: =+P92+P94 -> 129388.68 | Q95: =+Q92+Q94+SUM(E98:P98) -> 129539.36 | R95: =ROUND(Q95,3)=ROUND(P95+P98,3) -> TRUE | S95: =+S92+S94 -> 266543.1 | T95: =+T92+T94 -> 283475.99 | U95: =+U92+U94 -> 301484.59 | V95: =+V92+V94 -> 320637.24 | W95: =+W92+W94 -> 341006.61 | X95: =+X92+X94 -> 362670 | Y95: =+Y92+Y94 -> 385709.62 | Z95: =+Z92+Z94 -> 410212.89 | ... AL95: =+AL92+AL94 -> 859004.3 | BD95: 0 | BE95: 2524138.8 | BF95: 2538862.9 | BG95: 2553672.9 | BH95: 2568569.4 | BI95: 2583552.7 | BJ95: 2598623.4 | BK95: 2613782 | BL95: 2629029.1 | BM95: 2644365.1 | BN95: 2659790.6 | BO95: 2675306 | BP95: 2690912 | BR95: Optimizer | BS95: =+E102 -> 0 | BT95: =+F102 -> 0 | BU95: =+G102 -> 0 | BV95: =+H102 -> 0 | BW95: =+I102 -> 0 | BX95: =+J102 -> 0 | BY95: =+K102 -> 0 | BZ95: =+L102 -> 0 | ... CD95: =+P102 -> 67629.96
A96: Yield | D96: =IF($C$71=1,OPTIMIZER!$AW$25,'Balance Sheet'!$E$13) -> 0.043 | E96: =+D96 -> 0.043 | F96: =+E96 -> 0.043 | G96: =+F96 -> 0.043 | H96: =+G96 -> 0.043 | I96: =+H96 -> 0.043 | J96: =+I96 -> 0.043 | K96: =+J96 -> 0.043 | L96: =+K96 -> 0.043 | ... P96: =+O96 -> 0.043 | Q96: =+Q97/AVERAGE(Q88,Q95) -> 0.016175396 | S96: =+Q96 -> 0.016175396 | T96: =+S96 -> 0.016175396 | U96: =+T96 -> 0.016175396 | V96: =+U96 -> 0.016175396 | W96: =+V96 -> 0.016175396 | X96: =+W96 -> 0.016175396 | Y96: =+X96 -> 0.016175396 | Z96: =+Y96 -> 0.016175396 | AA96: =+Z96 -> 0.016175396 | ... AL96: =+AK96 -> 0.016175396 | BD96: 1 | BE96: 2524138.8 | BF96: 2538862.9 | BG96: 2553672.9 | BH96: 2568569.4 | BI96: 2583552.7 | BJ96: 2598623.4 | BK96: 2613782 | BL96: 2629029.1 | BM96: 2644365.1 | BN96: 2659790.6 | BO96: 2675306 | BP96: 2690912 | BR96: 0 | BS96: 0 | BT96: 0 | BU96: 0 | BV96: 0 | BW96: 0 | BX96: 0 | BY96: 0 | BZ96: 0 | CA96: 0 | CB96: 0 | CC96: 0 | CD96: 0
A97: Short - Interest Income | E97: =AVERAGE(E88,E95)*E96/12 -> 428.46579 | F97: =AVERAGE(F88,F95)*F96/12 -> 390.49198 | G97: =AVERAGE(G88,G95)*G96/12 -> 303.15904 | H97: =AVERAGE(H88,H95)*H96/12 -> 208.45619 | I97: =AVERAGE(I88,I95)*I96/12 -> 192.36628 | J97: =AVERAGE(J88,J95)*J96/12 -> 148.46791 | K97: =AVERAGE(K88,K95)*K96/12 -> 79.38385 | L97: =AVERAGE(L88,L95)*L96/12 -> 45.076495 | ... P97: =AVERAGE(P88,P95)*P96/12 -> 231.82833 | Q97: =+SUM(E97:P97) -> 2094.1005 | S97: =AVERAGE(S88,S95)*S96 -> 6479.3081 | T97: =AVERAGE(T88,T95)*T96 -> 6890.9241 | U97: =AVERAGE(U88,U95)*U96 -> 7328.6891 | V97: =AVERAGE(V88,V95)*V96 -> 7794.2645 | W97: =AVERAGE(W88,W95)*W96 -> 8289.4167 | X97: =AVERAGE(X88,X95)*X96 -> 8816.0249 | Y97: =AVERAGE(Y88,Y95)*Y96 -> 9376.0874 | Z97: =AVERAGE(Z88,Z95)*Z96 -> 9971.7293 | ... AL97: =AVERAGE(AL88,AL95)*AL96 -> 20881.251 | BR97: 1 | BS97: 0 | BT97: 0 | BU97: 0 | BV97: 0 | BW97: 0 | BX97: 0 | BY97: 0 | BZ97: 0 | CA97: 0 | CB97: 0 | CC97: 0 | CD97: 67629.96
A98: Short - Interest Income After-Tax | C98: Tax Rate | D98: =IF(C71=1,1-OPTIMIZER!AY25/OPTIMIZER!AW25,BB9) -> 0.35 | E98: =+E97*(1-$D$98) -> 278.50276 | F98: =+F97*(1-$D$98) -> 253.81978 | G98: =+G97*(1-$D$98) -> 197.05337 | H98: =+H97*(1-$D$98) -> 135.49652 | I98: =+I97*(1-$D$98) -> 125.03808 | J98: =+J97*(1-$D$98) -> 96.50414 | K98: =+K97*(1-$D$98) -> 51.599503 | L98: =+L97*(1-$D$98) -> 29.299722 | ... P98: =+P97*(1-$D$98) -> 150.68842 | Q98: =SUM(E98:P98) -> 1361.1653 | S98: =+S97*(1-$D$98) -> 3434.0333 | T98: =+T97*(1-$D$98) -> 3652.1898 | U98: =+U97*(1-$D$98) -> 3884.2052 | V98: =+V97*(1-$D$98) -> 4130.9602 | W98: =+W97*(1-$D$98) -> 4393.3909 | X98: =+X97*(1-$D$98) -> 4672.4932 | Y98: =+Y97*(1-$D$98) -> 4969.3263 | Z98: =+Z97*(1-$D$98) -> 5285.0165 | ... AL98: =+AL97*(1-$D$98) -> 11067.063 | BE98: =A124 -> Net Worth - Ending
BE99: =+BE81 -> January | BF99: =+BF81 -> February | BG99: =+BG81 -> March | BH99: =+BH81 -> April | BI99: =+BI81 -> May | BJ99: =+BJ81 -> June | BK99: =+BK81 -> July | BL99: =+BL81 -> August | ... BP99: =+BP81 -> December | BS99: Immediate Interest Income
A100: Medium - Beginning (Assumes Interest Accrued End of Month) | E100: =D104 -> 135000 | F100: =+E104+E108 -> 135288.84 | G100: =+F104+F108 -> 135578.31 | H100: =+G104+G108 -> 135868.39 | I100: =+H104+H108 -> 136159.09 | J100: =+I104+I108 -> 136450.41 | K100: =+J104+J108 -> 136742.36 | L100: =+K104+K108 -> 137034.93 | M100: =+L104+L108 -> 137328.13 | ... P100: =+O104+O108 -> 138211.49 | Q100: =D104 -> 135000 | S100: =+P104+P108 -> 138507.21 | T100: =+S104+S108 -> 167017.54 | U100: =+T104+T108 -> 197333.05 | V100: =+U104+U108 -> 229542.7 | W100: =+V104+V108 -> 263739.15 | X100: =+W104+W108 -> 300018.88 | Y100: =+X104+X108 -> 338482.35 | Z100: =+Y104+Y108 -> 368842.75 | AA100: =+Z104+Z108 -> 378302.16 | ... AL100: =+AK104+AK108 -> 499818.11 | AX100: T-bills accrue at end of the period and Treasuries (1 year+) semi annually | BD100: Optimizer | BE100: =E124 -> 4643396.8 | BF100: =F124 -> 4656656.4 | BG100: =G124 -> 4669985.5 | BH100: =H124 -> 4638398.7 | BI100: =I124 -> 4647860.3 | BJ100: =J124 -> 4660367.3 | BK100: =K124 -> 4654455.9 | BL100: =L124 -> 4653113.9 | ... BP100: =P124 -> 4893652.8 | BS100: =BE$75 -> January | BT100: =BF$75 -> February | BU100: =BG$75 -> March | BV100: =BH$75 -> April | BW100: =BI$75 -> May | BX100: =BJ$75 -> June | BY100: =BK$75 -> July | BZ100: =BL$75 -> August | ... CD100: =BP$75 -> December
A101: Paycheck allocation | E101: =IF($C$71=1,OPTIMIZER!$X$26,0) -> 0 | F101: =IF($C$71=1,OPTIMIZER!$X$26,0) -> 0 | G101: =IF($C$71=1,OPTIMIZER!$X$26,0) -> 0 | H101: =IF($C$71=1,OPTIMIZER!$X$26,0) -> 0 | I101: =IF($C$71=1,OPTIMIZER!$X$26,0) -> 0 | J101: =IF($C$71=1,OPTIMIZER!$X$26,0) -> 0 | K101: =IF($C$71=1,OPTIMIZER!$X$26,0) -> 0 | L101: =IF($C$71=1,OPTIMIZER!$X$26,0) -> 0 | ... O101: =IF($C$71=1,OPTIMIZER!$X$26,0) -> 0 | P101: =IF($C$71=1,OPTIMIZER!R26,0) -> 0.28723194 | Q101: =IF($C$71=1,OPTIMIZER!$X$26,0) -> 0 | S101: =+S102/S10 -> 0.053048301 | T101: =+T102/T10 -> 0.052696272 | U101: =+U102/U10 -> 0.052339708 | V101: =+V102/V10 -> 0.051978551 | W101: =+W102/W10 -> 0.05161274 | X101: =+X102/X10 -> 0.051242216 | Y101: =+Y102/Y10 -> 0.034385479 | Z101: =+Z102/Z10 -> 0 | ... AL101: =+AL102/AL10 -> 0 | BD101: 0 | BE101: 4643396.8 | BF101: 4656656.4 | BG101: 4669985.5 | BH101: 4638398.7 | BI101: 4647860.3 | BJ101: 4660367.3 | BK101: 4654455.9 | BL101: 4653113.9 | BM101: 4666830.6 | BN101: 4680622.2 | BO101: 4690501.3 | BP101: 4893652.8 | BR101: Optimizer | BS101: =+E86 -> 0.087719995 | BT101: =+F86 -> 0.087720179 | BU101: =+G86 -> 0.1819778 | BV101: =+H86 -> 0.19035645 | BW101: =+I86 -> 0.098193463 | BX101: =+J86 -> 0.13065978 | BY101: =+K86 -> 0.15998444 | BZ101: =+L86 -> 0.11913954 | ... CD101: =+P86 -> 0.18187973
A102: Income allocation to Medium-Term | E102: =E101*E$10 -> 0 | F102: =F101*F$10 -> 0 | G102: =G101*G$10 -> 0 | H102: =H101*H$10 -> 0 | I102: =I101*I$10 -> 0 | J102: =J101*J$10 -> 0 | K102: =K101*K$10 -> 0 | L102: =L101*L$10 -> 0 | ... P102: =P101*P$10 -> 67629.96 | Q102: =SUM(E102:P102) -> 67629.96 | S102: =MIN(S10-S78-S90,MAX(S110-S100,0)) -> 24642.164 | T102: =MIN(T10-T78-T90,MAX(T110-T100,0)) -> 25702.57 | U102: =MIN(U10-U78-U90,MAX(U110-U100,0)) -> 26805.089 | V102: =MIN(V10-V78-V90,MAX(V110-V100,0)) -> 27951.134 | W102: =MIN(W10-W78-W90,MAX(W110-W100,0)) -> 29142.142 | X102: =MIN(X10-X78-X90,MAX(X110-X100,0)) -> 30379.58 | Y102: =MIN(Y10-Y78-Y90,MAX(Y110-Y100,0)) -> 21405.148 | Z102: =MIN(Z10-Z78-Z90,MAX(Z110-Z100,0)) -> 0 | ... AL102: =MIN(AL10-AL78-AL90,MAX(AL110-AL100,0)) -> 0 | BD102: 1 | BE102: 4643396.8 | BF102: 4656656.4 | BG102: 4669985.5 | BH102: 4638398.7 | BI102: 4647860.3 | BJ102: 4660367.3 | BK102: 4654455.9 | BL102: 4653113.9 | BM102: 4666830.6 | BN102: 4680622.2 | BO102: 4690501.3 | BP102: 4893652.8 | BR102: 0 | BS102: 0.5531875 | BT102: 0.55318866 | BU102: 0.55318866 | BV102: 0.55318866 | BW102: 0.55318866 | BX102: 0.55318866 | BY102: 0.55318866 | BZ102: 0.55318866 | CA102: 0.55318866 | CB102: 0.55318866 | CC102: 0.55318866 | CD102: 0.65182693
...

Sheet OPTIMIZER
B1: Next Month | D1: 1 | E1: =+D1+1 -> 2 | F1: =+E1+1 -> 3 | G1: =+F1+1 -> 4 | H1: =+G1+1 -> 5 | I1: =+H1+1 -> 6 | J1: =+I1+1 -> 7 | K1: =+J1+1 -> 8 | L1: =+K1+1 -> 9 | ... O1: =+N1+1 -> 12
B2: Monthly Income | D2: =Charts!E28 -> 19092.12 | E2: =Charts!F28 -> 19067.437 | F2: =Charts!G28 -> 19010.765 | G2: =Charts!H28 -> 18949.217 | H2: =Charts!I28 -> 18938.666 | I2: =Charts!J28 -> 18910.164 | J2: =Charts!K28 -> 18865.289 | K2: =Charts!L28 -> 18842.949 | ... O2: =Charts!P28 -> 241147.11
B3: Expenses | D3: =+Charts!E42 -> -38439.42 | E3: =+Charts!F42 -> -20939.42 | F3: =+Charts!G42 -> -20939.42 | G3: =+Charts!H42 -> -65939.42 | H3: =+Charts!I42 -> -24939.42 | I3: =+Charts!J42 -> -21939.42 | J3: =+Charts!K42 -> -40439.42 | K3: =+Charts!L42 -> -35939.42 | ... O3: =+Charts!P42 -> -48392.38
B4: Net Cash Flow Excl Interest Income | D4: =+'Cash Flow'!E68 -> -19625.89 | E4: =+'Cash Flow'!F68 -> -2125.8904 | F4: =+'Cash Flow'!G68 -> -2125.8904 | G4: =+'Cash Flow'!H68 -> -47125.89 | H4: =+'Cash Flow'!I68 -> -6125.8904 | I4: =+'Cash Flow'!J68 -> -3125.8904 | J4: =+'Cash Flow'!K68 -> -21625.89 | K4: =+'Cash Flow'!L68 -> -17125.89 | ... O4: =+'Cash Flow'!P68 -> 187061.79
B5: Cumulative Net Cash Flow Excl Interest Income | D5: =+SUM(D$4:$D4) -> -19625.89 | E5: =+SUM($D$4:E4) -> -21751.781 | F5: =+SUM($D$4:F4) -> -23877.671 | G5: =+SUM($D$4:G4) -> -71003.561 | H5: =+SUM($D$4:H4) -> -77129.452 | I5: =+SUM($D$4:I4) -> -80255.342 | J5: =+SUM($D$4:J4) -> -101881.23 | K5: =+SUM($D$4:K4) -> -119007.12 | L5: =+SUM($D$4:L4) -> -121133.01 | ... O5: =+SUM($D$4:O4) -> 57677
B10: IMMEDIATE | F10: IMMEDIATE | M10: Paycheck Allocation
B11: Emergency fund calculation | F11: Emergency fund calculation | H11: 1 | J11: 3 | M11: Monthly paycheck | P11: =+'Cash Flow'!E10 -> 18813.53
B12: ="Average Monthly Expenses Next "&#REF!&" months" -> #REF! | F12: ="Average Monthly Expenses Next "&J11&" months" -> Average Monthly Expenses Next 3 months | H12: =-AVERAGE(E3:E3) -> 20939.42 | J12: =-AVERAGE(F3:I3) -> 33439.42
B13: ="Total expenses for "&E11&" months" -> Total expenses for months | F13: ="Total expenses for "&J11&" months" -> Total expenses for 3 months | H13: =H12*H11 -> 20939.42 | J13: =+J12*J11 -> 100318.26
F14: SHORT
F15: Cumulative Net Cash Flow Trough
F16: Trough over next 12 months | J16: =-IF(MIN(D5:O5)>0,0,MIN(D5:O5)) -> 129384.79
F17: Less amount hold in immediate | J17: 0
F18: Take minimum | J18: =+J16-J17 -> 129384.79
O21: GURU Suggestion | X21: Make Your Selection
E22: Balances | O22: Allocate Monthly Paycheck | R22: Allocate Year-End Bonus | U22: Next 12 Months Snapshot | V22: Increase From Today | X22: Allocate Monthly Paycheck | AA22: Allocate Year-End Bonus | AC22: Next 12 Months Snapshot | AD22: Increase From Today | AM22: Current | AT22: Allocation of: | BB22: Current | BH22: Breaking down how the Income is generated
D23: Products used Today | E23: Current | F23: % of Total | G23: GURU Suggestion | H23: Change | I23: GURU's Suggested Calculation | J23: % of Total | K23: Make your Selection | O23: % | P23: Implied $ | R23: % | S23: Implied $ | X23: % Make Your Selection | Y23: Implied $ | AA23: % Make Your Selection | AB23: Implied $ | AE23: Beginning balance | AF23: Paycheck accumulation | AG23: Paycheck accumulation + Interest Earned | AH23: Only Paycheck accumulation | AM23: Balance | AN23: % of Total | AO23: Yield Today | AP23: Tax Effected Yield | AQ23: GURU Suggested Balance | AR23: Your Selection | AS23: Money to Move Today | AT23: Monthly Paycheck | AU23: Year-End Bonus | AV23: Your Product Selection | AW23: Yield | AX23: Annual Pre-Tax Income | AY23: Tax Effected Yield | AZ23: Annual Cash Income | BA23: implied tax rate | BB23: Yield | BC23: Income | BD23: After Tax Yield | BE23: Cash Flow | BF23: Implied Tax Rate | BH23: Impact just product selection | BI23: Impact of realllocating cash | BJ23: Increased Investments
B24: Immediate | C24: 2-3 months of liquid cash for immediate expenditures | D24: Checking Account | E24: =+'Balance Sheet'!B9 -> 132050 | F24: =+E24/$E$29 -> 0.022020995 | G24: =+H13 -> 20939.42 | H24: =+G24-E24 -> -111110.58 | I24: =+H11&" months of expenses" -> 1 months of expenses | J24: =+G24/$G$29 -> 0.0034919112 | K24: [$] | L24: =+SUM(E24:E25)-SUM(G24:G25) -> 221725.79 | N24: Immediate | O24: =MIN(H12/P11,1) -> 1 | P24: =+O24*$P$11 -> 18813.53 | R24: =(-'Cash Flow'!E63)/'Cash Flow'!$P$10 -> 0.16325648 | S24: =+R24*('Cash Flow'!$P$10) -> 38439.42 | U24: =AH24 -> 38439.755 | V24: =+U24-G24 -> 17500.335 | X24: =O24 -> 1 | Y24: [$] | AA24: =+R24 -> 0.16325648 | AB24: [$] | AC24: [$] | AD24: [$] | AE24: =+G24 -> 20939.42 | AH24: =+'Cash Flow'!BA77 -> 38439.755 | AK24: Immediate | AL24: 2-3 months of liquid cash for immediate expenditures | AM24: =+E24 -> 132050 | AN24: =+F24 -> 0.022020995 | AO24: =+BB24 -> 9.4850435e-05 | AP24: =+BD24 -> 5.0270731e-05 | AQ24: =+G24 -> 20939.42 | AR24: =+AQ24 -> 20939.42 | AS24: =+G24-E24 -> -111110.58 | AT24: =+P24 -> 18813.53 | AU24: =S24 -> 38439.42 | AV24: CIT Money Market Fund | AW24: 0.0431 | AX24: ='Cash Flow'!BA83 -> 2.9717967 | AY24: =AW24*(1-'Cash Flow'!BB9) -> 0.022843 | AZ24: ='Cash Flow'!BA89 -> 1.5750523 | BA24: =1-AZ24/AX24 -> 0.47 | BB24: =+'Balance Sheet'!E9 -> 9.4850435e-05 | BC24: ='Cash Flow'!AZ83 -> 12.711134 | BD24: =+BB24*(1-'Cash Flow'!$BB$9) -> 5.0270731e-05 | BE24: ='Cash Flow'!AZ89 -> 6.736901 | BF24: =1-BE24/BC24 -> 0.47 | BH24: =+(AY24-AP24)*AQ24 -> 477.26653 | BI24: =+(AR24-AM24)*AP24 -> -5.5856101
B25: Short-Term | C25: Extra cash for the next one year for unanticipated expenditures, months of cash outflow or a "just in case buffer" | D25: Money Market Account | E25: =+'Balance Sheet'!B13 -> 240000 | F25: =+E25/$E$29 -> 0.040023013 | G25: =+J18 -> 129384.79 | H25: =+G25-E25 -> -110615.21 | I25: Additional cash outflow over the next 12 months | J25: =+G25/$G$29 -> 0.021576539 | K25: [$] | N25: Short-Term | O25: 0 | P25: =+O25*$P$11 -> 0 | R25: =G25/'Cash Flow'!$P$10 -> 0.54951157 | S25: =+R25*('Cash Flow'!$P$10) -> 129384.79 | U25: =AH25 -> 129539.36 | V25: =+U25-G25 -> 154.57071 | X25: =O25 -> 0 | Y25: [$] | AA25: =+R25 -> 0.54951157 | AB25: [$] | AC25: [$] | AD25: [$] | AE25: =+G25 -> 129384.79 | AH25: =+'Cash Flow'!BA78 -> 129539.36 | AK25: Short-Term | AL25: Extra cash for the next one year for unanticipated expenditures or as a "just in case buffer" | AM25: =+E25 -> 240000 | AN25: =+F25 -> 0.040023013 | AO25: =+BB25 -> 0.03658125 | AP25: =+BD25 -> 0.019388063 | AQ25: =+G25 -> 129384.79 | AR25: =+AQ25 -> 129384.79 | AS25: =+G25-E25 -> -110615.21 | AT25: =+P25 -> 0 | AU25: =S25 -> 129384.79 | AV25: JPMorgan 100% Treasuries Money Market Fund | AW25: 0.043 | AX25: ='Cash Flow'!BA84 -> 2094.1005 | AY25: =AW25*(1-'Cash Flow'!BB8) -> 0.02795 | AZ25: ='Cash Flow'!BA90 -> 1361.1653 | BA25: =1-AZ25/AX25 -> 0.35 | BB25: =+'Balance Sheet'!E13 -> 0.03658125 | BC25: ='Cash Flow'!AZ84 -> 6148.8257 | BD25: =+BB25*(1-'Cash Flow'!$BB$9) -> 0.019388063 | BE25: ='Cash Flow'!AZ90 -> 3258.8776 | BF25: =1-BE25/BC25 -> 0.47 | BH25: =+(AY25-AP25)*AQ25 -> 1107.7845 | BI25: =+(AR25-AM25)*AP25 -> -2144.6145
B26: Medium-Term | C26: Next 3 year saving for large expenditures | D26: Treasuries | E26: =+'Balance Sheet'!B15 -> 135000 | F26: =+E26/$E$29 -> 0.022512945 | G26: =+'Rent vs. Buy'!C19 -> 194041.71 | H26: =+G26-E26 -> 59041.711 | I26: Building downpayment for larger apartment in 3 years | J26: =+G26/$G$29 -> 0.032358892 | K26: [$] | N26: Medium-Term | O26: =1-O25-O24 -> 0 | P26: =+O26*$P$11 -> 0 | R26: =1-SUM(R24:R25) -> 0.28723194 | S26: =+R26*('Cash Flow'!$P$10) -> 67629.96 | U26: =AH26 -> 138507.21 | V26: =+U26-G26 -> -55534.506 | X26: =O26 -> 0 | Y26: [$] | AA26: =+R26 -> 0.28723194 | AB26: [$] | AC26: [$] | AD26: [$] | AE26: =+G26 -> 194041.71 | AH26: =+'Cash Flow'!BA79 -> 138507.21 | AK26: Medium-Term | AL26: Next 3 year saving for large expenditures (real estate down payment) | AM26: =+E26 -> 135000 | AN26: =+F26 -> 0.022512945 | AO26: =+BB26 -> 0.0395 | AP26: =+BD26 -> 0.025675 | AQ26: =+G26 -> 194041.71 | AR26: =+AQ26 -> 194041.71 | AS26: =+G26-E26 -> 59041.711 | AT26: =+P26 -> 0 | AU26: =S26 -> 67629.96 | AV26: 1 Year Treasuries + 2028 Muni Bonds | AW26: =(4%+2.67%)/2 -> 0.03335 | AX26: ='Cash Flow'!BA85 -> 5395.701 | AY26: =(4%*(1-'Cash Flow'!BB8)+2.67%)/2 -> 0.02635 | AZ26: ='Cash Flow'!BA91 -> 3507.2057 | BA26: =1-AZ26/AX26 -> 0.35 | BB26: ='Balance Sheet'!E15 -> 0.0395 | BC26: ='Cash Flow'!AZ85 -> 5395.701 | BD26: =+BB26*(1-'Cash Flow'!BB8) -> 0.025675 | BE26: ='Cash Flow'!AZ91 -> 3507.2057 | BF26: =1-BE26/BC26 -> 0.35 | BH26: =+(AY26-AP26)*AQ26 -> 130.97816 | BI26: =+(AR26-AM26)*AP26 -> 1515.8959
B27: Long-Term | C27: 5 years + investment horizon. Taxable Brokerage + Retirement | E27: =+'Balance Sheet'!B16+'Balance Sheet'!B17+'Balance Sheet'!B18+'Balance Sheet'!B36 -> 2509500 | F27: =+E27/$E$29 -> 0.41849063 | G27: =+G29-SUM(G24:G26,G28) -> 2672184.1 | H27: =+G27-E27 -> 162684.07 | I27: Remaining asets | J27: =+G27/$G$29 -> 0.44562024 | K27: [$] | N27: Long-Term | O27: =100%-SUM(O24:O26) -> 0 | P27: =+O27*$P$11 -> 0 | R27: 0 | S27: =+R27*('Cash Flow'!$P$7+'Cash Flow'!$P$9) -> 0 | U27: =+AG27 -> 2865356.5 | V27: =+U27-G27 -> 193172.4 | X27: =O27 -> 0 | Y27: [$] | AA27: =+R27 -> 0 | AB27: [$] | AC27: [$] | AD27: [$] | AE27: =+G27 -> 2672184.1 | AF27: =+P27/1000*12 -> 0 | AG27: =FV(AW27/12,12,-P27,-AE27,0) -> 2865356.5 | AH27: =+AE27+AF27 -> 2672184.1 | AK27: Long-Term | AL27: 5 years + investment horizon. Remaining assets including retirement | AM27: =+E27 -> 2509500 | AN27: =+F27 -> 0.41849063 | AO27: =+BB27 -> 0.07 | AP27: =+BD27 -> 0.056 | AQ27: =+G27 -> 2672184.1 | AR27: =+AQ27 -> 2672184.1 | AS27: =+G27-E27 -> 162684.07 | AT27: =+P27 -> 0 | AU27: =S27 -> 0 | AV27: Growth equity market ETFs | AW27: 0.07 | AX27: =+AW27*AQ27 -> 187052.89 | AY27: =7%*(1-'Cash Flow'!BB15) -> 0.056 | AZ27: =+AY27*AR27 -> 149642.31 | BA27: =1-AZ27/AX27 -> 0.2 | BB27: =+AW27 -> 0.07 | BC27: =+BB27*AM27 -> 175665 | BD27: =+BB27*(1-'Cash Flow'!BB15) -> 0.056 | BE27: =+BD27*AM27 -> 140532 | BF27: =1-BE27/BC27 -> 0.2 | BH27: =+(AY27-AP27)*AQ27 -> 0 | BJ27: =+AZ29-BI28-BH28 -> 6125.709
B28: Long-Term (Other) | C28: Real estate, alternative assets and stock compensation | E28: ='Balance Sheet'!B22+'Balance Sheet'!B29+'Balance Sheet'!B33 -> 2980000 | F28: =+E28/$E$29 -> 0.49695241 | G28: =+E28 -> 2980000 | H28: =+G28-E28 -> 0 | I28: Remaining asets | J28: =+G28/$G$29 -> 0.49695241 | K28: [$] | N28: Total | O28: =SUM(O24:O27) -> 1 | P28: =SUM(P24:P27) -> 18813.53 | S28: =SUM(S24:S27) -> 235454.17 | U28: =SUM(U24:U27) -> 3171842.8 | V28: =SUM(V24:V27) -> 155292.8 | AK28: =+N28 -> Total | AL28: =+#REF! -> #REF! | AM28: =SUM(AM24:AM27) -> 3016550 | AN28: =SUM(AN24:AN27) -> 0.50304759 | AQ28: =+SUM(AQ24:AQ27) -> 3016550 | AR28: =+SUM(AR24:AR27) -> 3016550 | AS28: No Change | AT28: =SUM(AT24:AT27) -> 18813.53 | AU28: =SUM(AU24:AU27) -> 235454.17 | AX28: =+SUM(AX24:AX27) -> 194545.66 | AZ28: =+SUM(AZ24:AZ27) -> 154512.25 | BC28: =SUM(BC24:BC27) -> 187222.24 | BE28: =SUM(BE24:BE27) -> 147304.82 | BH28: =SUM(BH24:BH27) -> 1716.0292 | BI28: =SUM(BI24:BI27) -> -634.3042 | BJ28: =SUM(BJ24:BJ27) -> 6125.709
B29: Total | E29: =SUM(E24:E28) -> 5996550 | F29: =SUM(F24:F28) -> 1 | G29: =+E29 -> 5996550 | J29: =SUM(J24:J28) -> 1 | AG29: =+AG27/AE27-1 -> 0.072290081 | AV29: Increase from Current - Total | AX29: =+AX28-BC28 -> 7323.4207 | AZ29: =+AZ28-BE28 -> 7207.434 | BD29: implied tax effected yield
H30: from b/s | AV30: Increase from Current - immediate,short and medium | AX30: =+SUM(AX24:AX26)-SUM(BC24:BC26) -> -4064.4646 | AZ30: =SUM(AZ24:AZ26)-SUM(BE24:BE26) -> -1902.8742 | BH30: reallocating cash toward long term investments | BJ30: =+BJ27+BI28 -> 5491.4048
H31: check | AV31: Yield on immediate, short and medium | AW31: =SUM(AX24:AX26)/SUM(AQ24:AQ26) -> 0.021758173 | AZ31: =SUM(AZ24:AZ26)/SUM(AQ24:AQ26) -> 0.014141777 | BB31: {=SUM(BC24:BC26/SUM(AM24:AM26))} -> 0.022793093 | BD31: {=SUM(BE24:BE26/SUM(AM24:AM26))} -> 0.013357302 | BH31: better cash management product selection | BJ31: =+BH28 -> 1716.0292
AV32: Change in yield | AW32: =AW31-BB31 -> -0.0010349203 | AZ32: =AZ31-BE30 -> 0.014141777
B33: Total Assets | E33: =+E29+E32 -> 5996550
E34: =+E33='Balance Sheet'!B37 -> TRUE

Sheet Investment Breakdown
D3: Gain | F3: Composition
A4: Brokerage | C4: Cost Basis | D4: $ | E4: Y
A5: Treasuries
A6: Total Market Index Fund | B6: =+F6*$B$14 -> 379877.58 | F6: 0.25325172 | G6: Fund
A7: US Large Cap | B7: =+F7*$B$14 -> 375000 | F7: 0.25
A8: International Index Fund | B8: =+F8*$B$14 -> 116538.3 | F8: 0.0776922 | G8: Fund | I8: 98% developed
A9: Cash | B9: =+F9*$B$14 -> 186585.93 | F9: =1-SUM(F6:F8,F10:F13) -> 0.12439062 | G9: Fund
A10: Fidelity Small Cap Value Index FD | B10: =+F10*$B$14 -> 49317.756 | F10: 0.032878504 | G10: Fund
A11: JP Morgan Equity Income Fund | B11: =+F11*$B$14 -> 94368.991 | F11: 0.062912661 | G11: Fund
A12: Meta | B12: =+F12*$B$14 -> 238311.43 | F12: 0.15887429 | G12: Stock
A13: Bank of America | B13: =+F13*$B$14 -> 60000 | F13: 0.04 | G13: Stock
A14: Fidelity | B14: 1500000
A15: Coinbase | B15: 9500
A16: Retirements
A17: International Index | B17: =+F17*$B$22 -> 78746.25 | F17: 0.12701008
A18: Total Market Index Fund | B18: =+F18*$B$22 -> 248000 | F18: 0.4
A19: S&P 500 | B19: =+F19*$B$22 -> 62000 | F19: 0.1
A20: Small Cap Value Index FD | B20: =+F20*$B$22 -> 170043.97 | F20: 0.27426447
A21: US Bond Index | B21: =+F21*$B$22 -> 61209.776 | F21: =1-SUM(F17:F20) -> 0.098725444
A22: 401(k) | B22: 620000
A23: International Index | B23: =+F23*$B$30 -> 49400 | F23: 0.13 | G23: =SUM(F23:F29) -> 1 | I23: 84% developed | J23: 14.5% emerging
A24: Total Market Index Fund | B24: =+F24*$B$30 -> 152000 | F24: 0.4
A25: S&P 500 | B25: =+F25*$B$30 -> 38000 | F25: 0.1
A26: Kinsale | B26: =+F26*$B$30 -> 0 | C26: 2189.2 | D26: =+B26-C26 -> -2189.2 | E26: =+B26/C26-1 -> -1 | F26: 0
A27: Lemonade | B27: =+F27*$B$30 -> 0 | C27: 475 | D27: =+B27-C27 -> -475 | E27: =+B27/C27-1 -> -1 | F27: 0
A28: Small Cap Value Index FD | B28: =+F28*$B$30 -> 104220.5 | F28: 0.27426447
A29: Cash Sweep | B29: =+F29*$B$30 -> 36379.5 | F29: =1-SUM(F23:F28) -> 0.095735525
A30: Roth IRA | B30: 380000
A31: Retirements | B31: =+B30+B22 -> 1000000 | C31: =+B31=SUM(B23:B29,B17:B21) -> TRUE
A32: Total | B32: =+B31+B14+B15 -> 2509500
A34: Liquid Investment Assets
A35: Cash | B35: =+B9 -> 186585.93
A36: International | B36: =+B8 -> 116538.3
A37: US Total Market | B37: =+B6 -> 379877.58
A38: US Large Cap | B38: =+B7+B13 -> 435000
A39: US Small Cap | B39: =+B10 -> 49317.756
A40: US Dividend / Value | B40: =+B11 -> 94368.991
A41: Meta | B41: =+B12 -> 238311.43
A42: Other Single Stock | B42: 0
A43: Crypto | B43: =+B15 -> 9500
A44: Total | B44: =+SUM(B35:B43) -> 1509500 | C44: =B44=B14+B15 -> TRUE
A46: Retirement by Taxable
A47: Pre-Tax | B47: =+B22 -> 620000
A48: After- Tax | B48: =+B30 -> 380000
A49: Total | B49: =+SUM(B47:B48) -> 1000000
A51: Retirement by Category
A52: International | B52: =+B17+B23 -> 128146.25
A53: US Total Market | B53: =+B18+B24 -> 400000
A54: US Large Cap | B54: =B25+B19 -> 100000
A55: US Small Cap | B55: =B28+B20 -> 274264.47
A56: Bonds | B56: =+B21 -> 61209.776
A57: Other Single Stock | B57: =+B26+B27 -> 0
A58: Cash | B58: =+B29 -> 36379.5
A59: Total | B59: =SUM(B52:B58) -> 1000000 | C59: =+B59=B49 -> TRUE

Sheet Portfolio_Positions_Apr-05-2025
A1: Account Number | B1: Account Name | C1: Symbol | D1: Description | E1: Quantity | F1: Last Price | G1: Last Price Change | H1: Current Value | I1: Today's Gain/Loss Dollar | J1: Today's Gain/Loss Percent | K1: Total Gain/Loss Dollar | L1: Total Gain/Loss Percent | M1: Percent Of Account | N1: Cost Basis Total | O1: Average Cost Basis | P1: Type
B2: Brokerage Account | C2: FCASH** | D2: HELD IN FCASH | H2: 106408.51 | M2: 0.3923 | P2: Cash
B3: Brokerage Account | C3: FSKAX | D3: FIDELITY TOTAL MARKET INDEX FUND | E3: 495.294 | F3: 138.7 | G3: -8.65 | H3: 68697.27 | I3: -4284.3 | J3: -0.0588 | K3: 35096.7 | L3: 1.0445 | M3: 0.2533 | N3: 33600.57 | O3: 67.84 | P3: Cash
B4: Brokerage Account | C4: META | D4: META PLATFORMS INC CLASS A COMMON STOCK | E4: 85.385 | F4: 504.73 | G4: -26.89 | H4: 43096.37 | I4: -2296.01 | J4: -0.0506 | K4: 40858.89 | L4: 18.2611 | M4: 0.1589 | N4: 2237.48 | O4: 26.2 | P4: Cash
B5: Brokerage Account | C5: FSPSX | D5: FIDELITY INTERNATL INDEX FUND | E5: 445.84 | F5: 47.27 | G5: -3.33 | H5: 21074.85 | I5: -1484.65 | J5: -0.0659 | K5: 3689.53 | L5: 0.2122 | M5: 0.0777 | N5: 17385.32 | O5: 38.99 | P5: Cash
B6: Brokerage Account | C6: OIEIX | D6: JPMORGAN EQUITY INCOME FUND CL A | E6: 787.892 | F6: 21.66 | G6: -1.37 | H6: 17065.74 | I6: -1079.42 | J6: -0.0595 | K6: 7107.11 | L6: 0.7136 | M6: 0.0629 | N6: 9958.63 | O6: 12.64 | P6: Cash
B7: Brokerage Account | C7: FISVX | D7: FIDELITY SMALL CAP VALUE INDEX FD | E7: 415.982 | F7: 21.44 | G7: -0.91 | H7: 8918.65 | I7: -378.55 | J7: -0.0408 | K7: -1260.97 | L7: -0.1239 | M7: 0.0329 | N7: 10179.62 | O7: 24.47 | P7: Cash
B8: Brokerage Account | C8: BAC | D8: BANK AMERICA CORP COM | E8: 89.744 | F8: 34.39 | G8: -2.83 | H8: 3086.29 | I8: -253.98 | J8: -0.0761 | K8: 2036.39 | L8: 1.9396 | M8: 0.0114 | N8: 1049.9 | O8: 11.7 | P8: Cash
B9: Brokerage Account | C9: PINS | D9: PINTEREST INC CL A | E9: 113 | F9: 25.78 | G9: -1.73 | H9: 2913.14 | I9: -195.49 | J9: -0.0629 | K9: 879.14 | L9: 0.4322 | M9: 0.0107 | N9: 2034 | O9: 18 | P9: Cash
H10: =SUM(H3:H9) -> 164852.31 | I10: =SUM(I3:I9) -> -9972.4 | J10: =+I10/H10 -> -0.060492935
B12: Roth IRA | C12: FZROX | D12: FIDELITY ZERO TOTAL MARKET INDEX | E12: 3761.335 | F12: 17.53 | G12: -1.09 | H12: 65936.2 | I12: -4099.86 | J12: -0.0586 | K12: 10626.46 | L12: 0.1921 | M12: 0.4148 | N12: 55309.74 | O12: 14.7 | P12: Cash
B13: Roth IRA | C13: FZILX | D13: FIDELITY ZERO INTERNATIONAL INDEX | E13: 3925.341 | F13: 11.15 | G13: -0.72 | H13: 43767.55 | I13: -2826.25 | J13: -0.0607 | K13: 2487.81 | L13: 0.0602 | M13: 0.2753 | N13: 41279.74 | O13: 10.52 | P13: Cash
B14: Roth IRA | C14: FISVX | D14: FIDELITY SMALL CAP VALUE INDEX FD | E14: 1656.781 | F14: 21.44 | G14: -0.91 | H14: 35521.38 | I14: -1507.68 | J14: -0.0408 | K14: -2018.09 | L14: -0.0538 | M14: 0.2234 | N14: 37539.47 | O14: 22.66 | P14: Cash
B15: Roth IRA | C15: CORE** | D15: FDIC-INSURED DEPOSIT SWEEP | H15: 7036.79 | M15: 0.0443 | P15: Cash
B16: Roth IRA | C16: KNSL | D16: KINSALE CAP GROUP INC COM | E16: 13.094 | F16: 459.11 | G16: -39.49 | H16: 6011.58 | I16: -517.09 | J16: -0.0793 | K16: 3822.38 | L16: 1.746 | M16: 0.0378 | N16: 2189.2 | O16: 167.19 | P16: Cash
B17: Roth IRA | C17: LMND | D17: LEMONADE INC COM | E17: 25 | F17: 28.17 | G17: -1.81 | H17: 704.25 | I17: -45.25 | J17: -0.0604 | K17: 229.25 | L17: 0.4826 | M17: 0.0044 | N17: 475 | O17: 19 | P17: Cash
B18: 401(k) | D18: BROKERAGELINK | E18: 344749.17 | F18: 1 | G18: 0 | H18: 344749.17 | I18: 0 | J18: 0 | K18: 0 | L18: 0 | M18: -- | N18: 344749.17 | O18: 1
B19: 401(k) | C19: 48128E733 | D19: JPMCB SR PB 2055 CFA | E19: 6.392 | F19: 38.45 | G19: -2.16 | H19: 245.77 | I19: -13.81 | J19: -0.0532 | K19: 25.89 | L19: 0.1177 | M19: 0.9977 | N19: 219.88 | O19: 34.4
B20: 401(k) | C20: FXNAX | D20: FID US BOND IDX | E20: 0.053 | F20: 10.49 | G20: 0.01 | H20: 0.56 | I20: 0 | J20: 0.0082 | K20: -0.08 | L20: -0.125 | M20: 0.0023 | N20: 0.64 | O20: 12.08
B21: BrokerageLink | C21: FZROX | D21: FIDELITY ZERO TOTAL MARKET INDEX | E21: 9838.787 | F21: 17.53 | G21: -1.09 | H21: 172473.93 | I21: -10724.28 | J21: -0.0586 | K21: 32566.67 | L21: 0.2327 | M21: 0.5003 | N21: 139907.26 | O21: 14.22 | P21: Cash
B22: BrokerageLink | C22: FISVX | D22: FIDELITY SMALL CAP VALUE INDEX FD | E22: 4410.096 | F22: 21.44 | G22: -0.91 | H22: 94552.45 | I22: -4013.19 | J22: -0.0408 | K22: -8948.38 | L22: -0.0865 | M22: 0.2743 | N22: 103500.83 | O22: 23.47 | P22: Cash
B23: BrokerageLink | C23: FZILX | D23: FIDELITY ZERO INTERNATIONAL INDEX | E23: 3927.052 | F23: 11.15 | G23: -0.72 | H23: 43786.62 | I23: -2827.48 | J23: -0.0607 | K23: 1503.31 | L23: 0.0355 | M23: 0.127 | N23: 42283.31 | O23: 10.77 | P23: Cash
B24: BrokerageLink | C24: FXNAX | D24: FIDELITY U.S. BOND INDEX FUND | E24: 3235.098 | F24: 10.49 | G24: 0.01 | H24: 33936.17 | I24: 32.35 | J24: 0.0009 | K24: -715.72 | L24: -0.0207 | M24: 0.0984 | N24: 34651.89 | O24: 10.71 | P24: Cash
A26: The data and information in this spreadsheet is provided to you solely for your use and is not for distribution. The spreadsheet is provided for informational purposes only, and is not intended to provide advice, nor should it be construed as an offer to sell, a solicitation of an offer to buy or a recommendation for any security by Fidelity or any third party. Data and information shown is based on information known to Fidelity as of the date it was exported and is subject to change. It should not be used in place of your account statements or trade confirmations and is not intended for tax reporting purposes. For more information on the data included in this spreadsheet, including any limitations thereof, go to Fidelity.com.
A28: Brokerage services are provided by Fidelity Brokerage Services LLC (FBS), 900 Salem Street, Smithfield, RI 02917. Custody and other services provided by National Financial Services LLC (NFS). Both are Fidelity Investment companies and members SIPC, NYSE. Neither FBS nor NFS offer crypto as a direct investment nor provide trading or custody services for such assets.
A30: Date downloaded Apr-05-2025 at 10:13 a.m ET

Sheet Investment Breakdown (3.19.25)
D3: Gain | F3: Composition
A4: Brokerage | C4: Cost Basis | D4: $ | E4: Y
A5: Fidelity Total Market Index Fund | B5: 80767.59 | F5: =+B5/$B$13 -> 0.26328722 | G5: Fund
A6: Fidelity International Index Fund | B6: 22902.8 | F6: =+B6/$B$13 -> 0.074658839 | G6: Fund
A7: Fidelity Zero International Index | B7: 107816.63 | F7: =+B7/$B$13 -> 0.35146202 | G7: Fund
A8: Fidelity Small Cap Value Index FD | B8: 10449.47 | F8: =+B8/$B$13 -> 0.034063315 | G8: Fund
A9: JP Morgan Equity Income Fund | B9: 19531.84 | F9: =+B9/$B$13 -> 0.06367014 | G9: Fund
A10: Meta | B10: 57006.81 | C10: 2192.69 | D10: =+B10-C10 -> 54814.12 | E10: =+B10/C10-1 -> 24.998573 | F10: =+B10/$B$13 -> 0.18583152 | G10: Stock
A11: Bank of America | B11: 4112.21 | C11: 1026.71 | D11: =+B11-C11 -> 3085.5 | E11: =+B11/C11-1 -> 3.0052303 | F11: =+B11/$B$13 -> 0.013405034 | G11: Stock
A12: Pinterest | B12: 4178.74 | C12: 2034 | D12: =+B12-C12 -> 2144.74 | E12: =+B12/C12-1 -> 1.0544444 | F12: =+B12/$B$13 -> 0.01362191 | G12: Stock
A13: Fidelity | B13: =SUM(B5:B12) -> 306766.09
A14: Coinbase | B14: 5976.47 | C14: 2800 | D14: =+B14-C14 -> 3176.47 | E14: =+B14/C14-1 -> 1.1344536
A15: Retirements
A16: Fidelity Zero International Index | B16: =+'Portfolio_Positions_Apr-05-2025'!H12 -> 65936.2 | F16: =+B16/$B$20 -> 0.1596247
A17: Fidelity Zero Total Market Index Fund | B17: 202679.01 | F17: =+B17/$B$20 -> 0.49066487
A18: Fidelity Small Cap Value Index FD | B18: 110781.61 | F18: =+B18/$B$20 -> 0.26819079
A19: Fidelity US Bond Index | B19: 33673.33 | F19: =+B19/$B$20 -> 0.08151964
A20: 401(k) | B20: =SUM(B16:B19) -> 413070.15
A21: Fidelity Zero International Index | B21: 47221.85 | F21: =+B21/$B$20 -> 0.1143192
A22: Fidelity Zero Total Market Index Fund | B22: 77483.5 | F22: =+B22/$B$20 -> 0.18757952
A23: Fidelity Small Cap Value Index FD | B23: 41618.34 | F23: =+B23/$B$20 -> 0.10075369
A24: Kinsale | B24: 5652.48 | C24: 2189.2 | D24: =+B24-C24 -> 3463.28 | E24: =+B24/C24-1 -> 1.5819843 | F24: =+B24/$B$20 -> 0.013684068
A25: Lemonade | B25: 908.75 | C25: 475 | D25: =+B25-C25 -> 433.75 | E25: =+B25/C25-1 -> 0.91315789 | F25: =+B25/$B$20 -> 0.0021999895
A26: Roth IRA | B26: =SUM(B21:B25) -> 172884.92
A27: Retirements | B27: =+B26+B20 -> 585955.07
A28: Total | B28: =+B27+B13+B14 -> 898697.63
A30: Liquid Investment Assets
A31: International | B31: =+B6+B7 -> 130719.43
A32: US Total Market (Dow Jones Index) | B32: =+B5 -> 80767.59
A33: US Small Cap | B33: =+B8 -> 10449.47
A34: US Dividend / Value | B34: =+B9 -> 19531.84
A35: Meta | B35: =+B10 -> 57006.81
A36: Other Single Stock | B36: =+B11+B12 -> 8290.95
A37: Crypto | B37: =+B14 -> 5976.47
A38: Total | B38: =+SUM(B31:B37) -> 312742.56 | C38: =B38=B13+B14 -> TRUE
A40: Retirement by Taxable
A41: Pre-Tax | B41: =+B20 -> 413070.15
A42: After- Tax | B42: =+B26 -> 172884.92
A43: Total | B43: =+SUM(B41:B42) -> 585955.07
A45: Retirement by Category
A46: International | B46: =+B16+B21 -> 113158.05
A47: US Total Market (Dow Jones Index) | B47: =+B17+B22 -> 280162.51
A48: US Small Cap | B48: =+B18+B23 -> 152399.95
A49: US Bonds | B49: =+B19 -> 33673.33
A50: Single Stock | B50: =+B24+B25 -> 6561.23
A51: Total | B51: =+SUM(B46:B50) -> 585955.07 | C51: =+B51=B43 -> TRUE
